Workbook

Sheet README
B2: POKEMON TCG INVESTMENT WORKBOOK v2
B3: Built May 11 2026 | 198-card watchlist | Quant scoring | Auto Buy/Sell signals | 90-day price history engine
B5: v2 — WHAT CHANGED FROM v1
B6: • Watchlist: 25 → 198 cards across vintage / modern / sealed / raw grading / Japanese
B7: • NEW Price History sheet: 90 days of seeded prices per card; refresh script appends new rows
B8: • NEW Quant Scoring: Momentum + Value + Scarcity + Liquidity → 0-100 composite + BUY/HOLD/SELL signal
B9: • NEW Weekly Buy List: auto-generated top 10 buys + top 5 sells every refresh
B10: • NEW Hot Singles: momentum leaders sorted by 7-day price change
B11: • Refresh script v2: appends to Price History + recomputes all signals + outputs weekly digest
B13: WHY THE QUANT SCORE WORKS (and why it's not 'AI' but better)
B14: The composite score (0-100) computes from four orthogonal factors every refresh:
B15: Momentum Score (40%) — recent 7D + 30D price change, weighted toward shorter window
... B66: RED fill = SELL signal / position underwater

Sheet Dashboard
B2: PORTFOLIO DASHBOARD
B3: Live KPIs from Inventory + Realized P&L. Allocation shows current $ vs target.
B5: PORTFOLIO KPIs | F5: ALLOCATION SNAPSHOT
B6: Total Cost Basis | D6: =SUM(Inventory!H5:H58) | F6: Category | G6: Current $ | H6: % of Port
B7: Total Current Value | D7: =SUM(Inventory!K5:K58) | F7: Sealed Modern | G7: =SUMIFS(Inventory!K:K,Inventory!C:C,F7) | H7: =IFERROR(G7/$D$7,0)
B8: Unrealized P&L ($) | D8: =D7-D6 | F8: Modern Chase PSA 10 | G8: =SUMIFS(Inventory!K:K,Inventory!C:C,F8) | H8: =IFERROR(G8/$D$7,0)
B9: Unrealized P&L (%) | D9: =IFERROR(D8/D6,0) | F9: Vintage Graded Singles | G9: =SUMIFS(Inventory!K:K,Inventory!C:C,F9) | H9: =IFERROR(G9/$D$7,0)
B10: Realized P&L (lifetime) | D10: =SUM('Realized P&L'!K5:K45)
B11: Realized + Unrealized | D11: =D8+D10
B12: # Positions Open | D12: =COUNTA(Inventory!B5:B58)
B13: # Cards Sold (lifetime) | D13: =COUNTA('Realized P&L'!B5:B45)
B14: Avg Holding Period (days) | D14: =IFERROR(AVERAGEIFS('Realized P&L'!L5:L45,'Realized P&L'!B5:B45,"<>"),0)
B15: Win Rate % | D15: =IFERROR(COUNTIFS('Realized P&L'!K5:K45,">0",'Realized P&L'!B5:B45,"<>")/COUNTA('Realized P&L'!B5:B45),0)
B17: MARKET PULSE (from Watchlist) | F17: TOP 5 UNREALIZED WINNERS
B18: Watchlist Avg Composite | D18: =AVERAGE(Watchlist!Y5:Y202) | F18: Item | G18: P&L $ | H18: P&L %
B19: # STRONG BUY signals | D19: =COUNTIF(Watchlist!Z5:Z202,"STRONG BUY") | F19: =IFERROR(INDEX(Inventory!D:D,MATCH(LARGE(Inventory!L5:L58,1),Inventory!L:L,0)),"") | G19: =IFERROR(LARGE(Inventory!L5:L58,1),0) | H19: =IFERROR(INDEX(Inventory!M:M,MATCH(LARGE(Inventory!L5:L58,1),Inventory!L:L,0)),0)
B20: # BUY signals | D20: =COUNTIF(Watchlist!Z5:Z202,"BUY") | F20: =IFERROR(INDEX(Inventory!D:D,MATCH(LARGE(Inventory!L5:L58,2),Inventory!L:L,0)),"") | G20: =IFERROR(LARGE(Inventory!L5:L58,2),0) | H20: =IFERROR(INDEX(Inventory!M:M,MATCH(LARGE(Inventory!L5:L58,2),Inventory!L:L,0)),0)
B21: # HOLD signals | D21: =COUNTIF(Watchlist!Z5:Z202,"HOLD") | F21: =IFERROR(INDEX(Inventory!D:D,MATCH(LARGE(Inventory!L5:L58,3),Inventory!L:L,0)),"") | G21: =IFERROR(LARGE(Inventory!L5:L58,3),0) | H21: =IFERROR(INDEX(Inventory!M:M,MATCH(LARGE(Inventory!L5:L58,3),Inventory!L:L,0)),0)
B22: # TRIM signals | D22: =COUNTIF(Watchlist!Z5:Z202,"TRIM") | F22: =IFERROR(INDEX(Inventory!D:D,MATCH(LARGE(Inventory!L5:L58,4),Inventory!L:L,0)),"") | G22: =IFERROR(LARGE(Inventory!L5:L58,4),0) | H22: =IFERROR(INDEX(Inventory!M:M,MATCH(LARGE(Inventory!L5:L58,4),Inventory!L:L,0)),0)
B23: # SELL signals | D23: =COUNTIF(Watchlist!Z5:Z202,"SELL") | F23: =IFERROR(INDEX(Inventory!D:D,MATCH(LARGE(Inventory!L5:L58,5),Inventory!L:L,0)),"") | G23: =IFERROR(LARGE(Inventory!L5:L58,5),0) | H23: =IFERROR(INDEX(Inventory!M:M,MATCH(LARGE(Inventory!L5:L58,5),Inventory!L:L,0)),0)
B24: Avg 30D Trend (watchlist) | D24: =AVERAGE(Watchlist!N5:N202)

Sheet Weekly Buy List
B2: WEEKLY BUY LIST — Auto-Generated
B3: Refreshed: Mon May 11, 2026. Top 10 BUY signals + Top 5 SELL signals. This is your Monday morning shopping list.
B5: TOP 10 BUY SIGNALS
B6: CardID | C6: Card Name | D6: Set | E6: Current Price | F6: Target Buy | G6: Upside to Sell | H6: 30D % | I6: Score | J6: Signal | K6: Why
B7: =IFERROR(INDEX(Watchlist!A:A,MATCH(LARGE(Watchlist!Y5:Y202,1),Watchlist!Y:Y,0)),"") | C7: =IFERROR(INDEX(Watchlist!D:D,MATCH(LARGE(Watchlist!Y5:Y202,1),Watchlist!Y:Y,0)),"") | D7: =IFERROR(INDEX(Watchlist!E:E,MATCH(LARGE(Watchlist!Y5:Y202,1),Watchlist!Y:Y,0)),"") | E7: =IFERROR(INDEX(Watchlist!H:H,MATCH(LARGE(Watchlist!Y5:Y202,1),Watchlist!Y:Y,0)),0) | F7: =IFERROR(INDEX(Watchlist!P:P,MATCH(LARGE(Watchlist!Y5:Y202,1),Watchlist!Y:Y,0)),0) | G7: =IFERROR((INDEX(Watchlist!Q:Q,MATCH(LARGE(Watchlist!Y5:Y202,1),Watchlist!Y:Y,0))/E7)-1,0) | H7: =IFERROR(INDEX(Watchlist!N:N,MATCH(LARGE(Watchlist!Y5:Y202,1),Watchlist!Y:Y,0)),0) | I7: =IFERROR(LARGE(Watchlist!Y5:Y202,1),0) | J7: =IFERROR(INDEX(Watchlist!Z:Z,MATCH(LARGE(Watchlist!Y5:Y202,1),Watchlist!Y:Y,0)),"") | K7: =IFERROR(LEFT(INDEX(Watchlist!AB:AB,MATCH(LARGE(Watchlist!Y5:Y202,1),Watchlist!Y:Y,0)),80),"")
B8: =IFERROR(INDEX(Watchlist!A:A,MATCH(LARGE(Watchlist!Y5:Y202,2),Watchlist!Y:Y,0)),"") | C8: =IFERROR(INDEX(Watchlist!D:D,MATCH(LARGE(Watchlist!Y5:Y202,2),Watchlist!Y:Y,0)),"") | D8: =IFERROR(INDEX(Watchlist!E:E,MATCH(LARGE(Watchlist!Y5:Y202,2),Watchlist!Y:Y,0)),"") | E8: =IFERROR(INDEX(Watchlist!H:H,MATCH(LARGE(Watchlist!Y5:Y202,2),Watchlist!Y:Y,0)),0) | F8: =IFERROR(INDEX(Watchlist!P:P,MATCH(LARGE(Watchlist!Y5:Y202,2),Watchlist!Y:Y,0)),0) | G8: =IFERROR((INDEX(Watchlist!Q:Q,MATCH(LARGE(Watchlist!Y5:Y202,2),Watchlist!Y:Y,0))/E8)-1,0) | H8: =IFERROR(INDEX(Watchlist!N:N,MATCH(LARGE(Watchlist!Y5:Y202,2),Watchlist!Y:Y,0)),0) | I8: =IFERROR(LARGE(Watchlist!Y5:Y202,2),0) | J8: =IFERROR(INDEX(Watchlist!Z:Z,MATCH(LARGE(Watchlist!Y5:Y202,2),Watchlist!Y:Y,0)),"") | K8: =IFERROR(LEFT(INDEX(Watchlist!AB:AB,MATCH(LARGE(Watchlist!Y5:Y202,2),Watchlist!Y:Y,0)),80),"")
B9: =IFERROR(INDEX(Watchlist!A:A,MATCH(LARGE(Watchlist!Y5:Y202,3),Watchlist!Y:Y,0)),"") | C9: =IFERROR(INDEX(Watchlist!D:D,MATCH(LARGE(Watchlist!Y5:Y202,3),Watchlist!Y:Y,0)),"") | D9: =IFERROR(INDEX(Watchlist!E:E,MATCH(LARGE(Watchlist!Y5:Y202,3),Watchlist!Y:Y,0)),"") | E9: =IFERROR(INDEX(Watchlist!H:H,MATCH(LARGE(Watchlist!Y5:Y202,3),Watchlist!Y:Y,0)),0) | F9: =IFERROR(INDEX(Watchlist!P:P,MATCH(LARGE(Watchlist!Y5:Y202,3),Watchlist!Y:Y,0)),0) | G9: =IFERROR((INDEX(Watchlist!Q:Q,MATCH(LARGE(Watchlist!Y5:Y202,3),Watchlist!Y:Y,0))/E9)-1,0) | H9: =IFERROR(INDEX(Watchlist!N:N,MATCH(LARGE(Watchlist!Y5:Y202,3),Watchlist!Y:Y,0)),0) | I9: =IFERROR(LARGE(Watchlist!Y5:Y202,3),0) | J9: =IFERROR(INDEX(Watchlist!Z:Z,MATCH(LARGE(Watchlist!Y5:Y202,3),Watchlist!Y:Y,0)),"") | K9: =IFERROR(LEFT(INDEX(Watchlist!AB:AB,MATCH(LARGE(Watchlist!Y5:Y202,3),Watchlist!Y:Y,0)),80),"")
B10: =IFERROR(INDEX(Watchlist!A:A,MATCH(LARGE(Watchlist!Y5:Y202,4),Watchlist!Y:Y,0)),"") | C10: =IFERROR(INDEX(Watchlist!D:D,MATCH(LARGE(Watchlist!Y5:Y202,4),Watchlist!Y:Y,0)),"") | D10: =IFERROR(INDEX(Watchlist!E:E,MATCH(LARGE(Watchlist!Y5:Y202,4),Watchlist!Y:Y,0)),"") | E10: =IFERROR(INDEX(Watchlist!H:H,MATCH(LARGE(Watchlist!Y5:Y202,4),Watchlist!Y:Y,0)),0) | F10: =IFERROR(INDEX(Watchlist!P:P,MATCH(LARGE(Watchlist!Y5:Y202,4),Watchlist!Y:Y,0)),0) | G10: =IFERROR((INDEX(Watchlist!Q:Q,MATCH(LARGE(Watchlist!Y5:Y202,4),Watchlist!Y:Y,0))/E10)-1,0) | H10: =IFERROR(INDEX(Watchlist!N:N,MATCH(LARGE(Watchlist!Y5:Y202,4),Watchlist!Y:Y,0)),0) | I10: =IFERROR(LARGE(Watchlist!Y5:Y202,4),0) | J10: =IFERROR(INDEX(Watchlist!Z:Z,MATCH(LARGE(Watchlist!Y5:Y202,4),Watchlist!Y:Y,0)),"") | K10: =IFERROR(LEFT(INDEX(Watchlist!AB:AB,MATCH(LARGE(Watchlist!Y5:Y202,4),Watchlist!Y:Y,0)),80),"")
B11: =IFERROR(INDEX(Watchlist!A:A,MATCH(LARGE(Watchlist!Y5:Y202,5),Watchlist!Y:Y,0)),"") | C11: =IFERROR(INDEX(Watchlist!D:D,MATCH(LARGE(Watchlist!Y5:Y202,5),Watchlist!Y:Y,0)),"") | D11: =IFERROR(INDEX(Watchlist!E:E,MATCH(LARGE(Watchlist!Y5:Y202,5),Watchlist!Y:Y,0)),"") | E11: =IFERROR(INDEX(Watchlist!H:H,MATCH(LARGE(Watchlist!Y5:Y202,5),Watchlist!Y:Y,0)),0) | F11: =IFERROR(INDEX(Watchlist!P:P,MATCH(LARGE(Watchlist!Y5:Y202,5),Watchlist!Y:Y,0)),0) | G11: =IFERROR((INDEX(Watchlist!Q:Q,MATCH(LARGE(Watchlist!Y5:Y202,5),Watchlist!Y:Y,0))/E11)-1,0) | H11: =IFERROR(INDEX(Watchlist!N:N,MATCH(LARGE(Watchlist!Y5:Y202,5),Watchlist!Y:Y,0)),0) | I11: =IFERROR(LARGE(Watchlist!Y5:Y202,5),0) | J11: =IFERROR(INDEX(Watchlist!Z:Z,MATCH(LARGE(Watchlist!Y5:Y202,5),Watchlist!Y:Y,0)),"") | K11: =IFERROR(LEFT(INDEX(Watchlist!AB:AB,MATCH(LARGE(Watchlist!Y5:Y202,5),Watchlist!Y:Y,0)),80),"")
B12: =IFERROR(INDEX(Watchlist!A:A,MATCH(LARGE(Watchlist!Y5:Y202,6),Watchlist!Y:Y,0)),"") | C12: =IFERROR(INDEX(Watchlist!D:D,MATCH(LARGE(Watchlist!Y5:Y202,6),Watchlist!Y:Y,0)),"") | D12: =IFERROR(INDEX(Watchlist!E:E,MATCH(LARGE(Watchlist!Y5:Y202,6),Watchlist!Y:Y,0)),"") | E12: =IFERROR(INDEX(Watchlist!H:H,MATCH(LARGE(Watchlist!Y5:Y202,6),Watchlist!Y:Y,0)),0) | F12: =IFERROR(INDEX(Watchlist!P:P,MATCH(LARGE(Watchlist!Y5:Y202,6),Watchlist!Y:Y,0)),0) | G12: =IFERROR((INDEX(Watchlist!Q:Q,MATCH(LARGE(Watchlist!Y5:Y202,6),Watchlist!Y:Y,0))/E12)-1,0) | H12: =IFERROR(INDEX(Watchlist!N:N,MATCH(LARGE(Watchlist!Y5:Y202,6),Watchlist!Y:Y,0)),0) | I12: =IFERROR(LARGE(Watchlist!Y5:Y202,6),0) | J12: =IFERROR(INDEX(Watchlist!Z:Z,MATCH(LARGE(Watchlist!Y5:Y202,6),Watchlist!Y:Y,0)),"") | K12: =IFERROR(LEFT(INDEX(Watchlist!AB:AB,MATCH(LARGE(Watchlist!Y5:Y202,6),Watchlist!Y:Y,0)),80),"")
B13: =IFERROR(INDEX(Watchlist!A:A,MATCH(LARGE(Watchlist!Y5:Y202,7),Watchlist!Y:Y,0)),"") | C13: =IFERROR(INDEX(Watchlist!D:D,MATCH(LARGE(Watchlist!Y5:Y202,7),Watchlist!Y:Y,0)),"") | D13: =IFERROR(INDEX(Watchlist!E:E,MATCH(LARGE(Watchlist!Y5:Y202,7),Watchlist!Y:Y,0)),"") | E13: =IFERROR(INDEX(Watchlist!H:H,MATCH(LARGE(Watchlist!Y5:Y202,7),Watchlist!Y:Y,0)),0) | F13: =IFERROR(INDEX(Watchlist!P:P,MATCH(LARGE(Watchlist!Y5:Y202,7),Watchlist!Y:Y,0)),0) | G13: =IFERROR((INDEX(Watchlist!Q:Q,MATCH(LARGE(Watchlist!Y5:Y202,7),Watchlist!Y:Y,0))/E13)-1,0) | H13: =IFERROR(INDEX(Watchlist!N:N,MATCH(LARGE(Watchlist!Y5:Y202,7),Watchlist!Y:Y,0)),0) | I13: =IFERROR(LARGE(Watchlist!Y5:Y202,7),0) | J13: =IFERROR(INDEX(Watchlist!Z:Z,MATCH(LARGE(Watchlist!Y5:Y202,7),Watchlist!Y:Y,0)),"") | K13: =IFERROR(LEFT(INDEX(Watchlist!AB:AB,MATCH(LARGE(Watchlist!Y5:Y202,7),Watchlist!Y:Y,0)),80),"")
B14: =IFERROR(INDEX(Watchlist!A:A,MATCH(LARGE(Watchlist!Y5:Y202,8),Watchlist!Y:Y,0)),"") | C14: =IFERROR(INDEX(Watchlist!D:D,MATCH(LARGE(Watchlist!Y5:Y202,8),Watchlist!Y:Y,0)),"") | D14: =IFERROR(INDEX(Watchlist!E:E,MATCH(LARGE(Watchlist!Y5:Y202,8),Watchlist!Y:Y,0)),"") | E14: =IFERROR(INDEX(Watchlist!H:H,MATCH(LARGE(Watchlist!Y5:Y202,8),Watchlist!Y:Y,0)),0) | F14: =IFERROR(INDEX(Watchlist!P:P,MATCH(LARGE(Watchlist!Y5:Y202,8),Watchlist!Y:Y,0)),0) | G14: =IFERROR((INDEX(Watchlist!Q:Q,MATCH(LARGE(Watchlist!Y5:Y202,8),Watchlist!Y:Y,0))/E14)-1,0) | H14: =IFERROR(INDEX(Watchlist!N:N,MATCH(LARGE(Watchlist!Y5:Y202,8),Watchlist!Y:Y,0)),0) | I14: =IFERROR(LARGE(Watchlist!Y5:Y202,8),0) | J14: =IFERROR(INDEX(Watchlist!Z:Z,MATCH(LARGE(Watchlist!Y5:Y202,8),Watchlist!Y:Y,0)),"") | K14: =IFERROR(LEFT(INDEX(Watchlist!AB:AB,MATCH(LARGE(Watchlist!Y5:Y202,8),Watchlist!Y:Y,0)),80),"")
B15: =IFERROR(INDEX(Watchlist!A:A,MATCH(LARGE(Watchlist!Y5:Y202,9),Watchlist!Y:Y,0)),"") | C15: =IFERROR(INDEX(Watchlist!D:D,MATCH(LARGE(Watchlist!Y5:Y202,9),Watchlist!Y:Y,0)),"") | D15: =IFERROR(INDEX(Watchlist!E:E,MATCH(LARGE(Watchlist!Y5:Y202,9),Watchlist!Y:Y,0)),"") | E15: =IFERROR(INDEX(Watchlist!H:H,MATCH(LARGE(Watchlist!Y5:Y202,9),Watchlist!Y:Y,0)),0) | F15: =IFERROR(INDEX(Watchlist!P:P,MATCH(LARGE(Watchlist!Y5:Y202,9),Watchlist!Y:Y,0)),0) | G15: =IFERROR((INDEX(Watchlist!Q:Q,MATCH(LARGE(Watchlist!Y5:Y202,9),Watchlist!Y:Y,0))/E15)-1,0) | H15: =IFERROR(INDEX(Watchlist!N:N,MATCH(LARGE(Watchlist!Y5:Y202,9),Watchlist!Y:Y,0)),0) | I15: =IFERROR(LARGE(Watchlist!Y5:Y202,9),0) | J15: =IFERROR(INDEX(Watchlist!Z:Z,MATCH(LARGE(Watchlist!Y5:Y202,9),Watchlist!Y:Y,0)),"") | K15: =IFERROR(LEFT(INDEX(Watchlist!AB:AB,MATCH(LARGE(Watchlist!Y5:Y202,9),Watchlist!Y:Y,0)),80),"")
B16: =IFERROR(INDEX(Watchlist!A:A,MATCH(LARGE(Watchlist!Y5:Y202,10),Watchlist!Y:Y,0)),"") | C16: =IFERROR(INDEX(Watchlist!D:D,MATCH(LARGE(Watchlist!Y5:Y202,10),Watchlist!Y:Y,0)),"") | D16: =IFERROR(INDEX(Watchlist!E:E,MATCH(LARGE(Watchlist!Y5:Y202,10),Watchlist!Y:Y,0)),"") | E16: =IFERROR(INDEX(Watchlist!H:H,MATCH(LARGE(Watchlist!Y5:Y202,10),Watchlist!Y:Y,0)),0) | F16: =IFERROR(INDEX(Watchlist!P:P,MATCH(LARGE(Watchlist!Y5:Y202,10),Watchlist!Y:Y,0)),0) | G16: =IFERROR((INDEX(Watchlist!Q:Q,MATCH(LARGE(Watchlist!Y5:Y202,10),Watchlist!Y:Y,0))/E16)-1,0) | H16: =IFERROR(INDEX(Watchlist!N:N,MATCH(LARGE(Watchlist!Y5:Y202,10),Watchlist!Y:Y,0)),0) | I16: =IFERROR(LARGE(Watchlist!Y5:Y202,10),0) | J16: =IFERROR(INDEX(Watchlist!Z:Z,MATCH(LARGE(Watchlist!Y5:Y202,10),Watchlist!Y:Y,0)),"") | K16: =IFERROR(LEFT(INDEX(Watchlist!AB:AB,MATCH(LARGE(Watchlist!Y5:Y202,10),Watchlist!Y:Y,0)),80),"")
B18: TOP 5 SELL / TRIM SIGNALS
B19: CardID | C19: Card Name | D19: Set | E19: Current Price | F19: Target Buy | G19: Upside to Sell | H19: 30D % | I19: Score | J19: Signal | K19: Why
B20: =IFERROR(INDEX(Watchlist!A:A,MATCH(SMALL(Watchlist!Y5:Y202,1),Watchlist!Y:Y,0)),"") | C20: =IFERROR(INDEX(Watchlist!D:D,MATCH(SMALL(Watchlist!Y5:Y202,1),Watchlist!Y:Y,0)),"") | D20: =IFERROR(INDEX(Watchlist!E:E,MATCH(SMALL(Watchlist!Y5:Y202,1),Watchlist!Y:Y,0)),"") | E20: =IFERROR(INDEX(Watchlist!H:H,MATCH(SMALL(Watchlist!Y5:Y202,1),Watchlist!Y:Y,0)),0) | F20: =IFERROR(INDEX(Watchlist!P:P,MATCH(SMALL(Watchlist!Y5:Y202,1),Watchlist!Y:Y,0)),0) | G20: =IFERROR((INDEX(Watchlist!Q:Q,MATCH(SMALL(Watchlist!Y5:Y202,1),Watchlist!Y:Y,0))/E20)-1,0) | H20: =IFERROR(INDEX(Watchlist!N:N,MATCH(SMALL(Watchlist!Y5:Y202,1),Watchlist!Y:Y,0)),0) | I20: =IFERROR(SMALL(Watchlist!Y5:Y202,1),0) | J20: =IFERROR(INDEX(Watchlist!Z:Z,MATCH(SMALL(Watchlist!Y5:Y202,1),Watchlist!Y:Y,0)),"") | K20: =IFERROR(LEFT(INDEX(Watchlist!AB:AB,MATCH(SMALL(Watchlist!Y5:Y202,1),Watchlist!Y:Y,0)),80),"")
B21: =IFERROR(INDEX(Watchlist!A:A,MATCH(SMALL(Watchlist!Y5:Y202,2),Watchlist!Y:Y,0)),"") | C21: =IFERROR(INDEX(Watchlist!D:D,MATCH(SMALL(Watchlist!Y5:Y202,2),Watchlist!Y:Y,0)),"") | D21: =IFERROR(INDEX(Watchlist!E:E,MATCH(SMALL(Watchlist!Y5:Y202,2),Watchlist!Y:Y,0)),"") | E21: =IFERROR(INDEX(Watchlist!H:H,MATCH(SMALL(Watchlist!Y5:Y202,2),Watchlist!Y:Y,0)),0) | F21: =IFERROR(INDEX(Watchlist!P:P,MATCH(SMALL(Watchlist!Y5:Y202,2),Watchlist!Y:Y,0)),0) | G21: =IFERROR((INDEX(Watchlist!Q:Q,MATCH(SMALL(Watchlist!Y5:Y202,2),Watchlist!Y:Y,0))/E21)-1,0) | H21: =IFERROR(INDEX(Watchlist!N:N,MATCH(SMALL(Watchlist!Y5:Y202,2),Watchlist!Y:Y,0)),0) | I21: =IFERROR(SMALL(Watchlist!Y5:Y202,2),0) | J21: =IFERROR(INDEX(Watchlist!Z:Z,MATCH(SMALL(Watchlist!Y5:Y202,2),Watchlist!Y:Y,0)),"") | K21: =IFERROR(LEFT(INDEX(Watchlist!AB:AB,MATCH(SMALL(Watchlist!Y5:Y202,2),Watchlist!Y:Y,0)),80),"")
B22: =IFERROR(INDEX(Watchlist!A:A,MATCH(SMALL(Watchlist!Y5:Y202,3),Watchlist!Y:Y,0)),"") | C22: =IFERROR(INDEX(Watchlist!D:D,MATCH(SMALL(Watchlist!Y5:Y202,3),Watchlist!Y:Y,0)),"") | D22: =IFERROR(INDEX(Watchlist!E:E,MATCH(SMALL(Watchlist!Y5:Y202,3),Watchlist!Y:Y,0)),"") | E22: =IFERROR(INDEX(Watchlist!H:H,MATCH(SMALL(Watchlist!Y5:Y202,3),Watchlist!Y:Y,0)),0) | F22: =IFERROR(INDEX(Watchlist!P:P,MATCH(SMALL(Watchlist!Y5:Y202,3),Watchlist!Y:Y,0)),0) | G22: =IFERROR((INDEX(Watchlist!Q:Q,MATCH(SMALL(Watchlist!Y5:Y202,3),Watchlist!Y:Y,0))/E22)-1,0) | H22: =IFERROR(INDEX(Watchlist!N:N,MATCH(SMALL(Watchlist!Y5:Y202,3),Watchlist!Y:Y,0)),0) | I22: =IFERROR(SMALL(Watchlist!Y5:Y202,3),0) | J22: =IFERROR(INDEX(Watchlist!Z:Z,MATCH(SMALL(Watchlist!Y5:Y202,3),Watchlist!Y:Y,0)),"") | K22: =IFERROR(LEFT(INDEX(Watchlist!AB:AB,MATCH(SMALL(Watchlist!Y5:Y202,3),Watchlist!Y:Y,0)),80),"")
B23: =IFERROR(INDEX(Watchlist!A:A,MATCH(SMALL(Watchlist!Y5:Y202,4),Watchlist!Y:Y,0)),"") | C23: =IFERROR(INDEX(Watchlist!D:D,MATCH(SMALL(Watchlist!Y5:Y202,4),Watchlist!Y:Y,0)),"") | D23: =IFERROR(INDEX(Watchlist!E:E,MATCH(SMALL(Watchlist!Y5:Y202,4),Watchlist!Y:Y,0)),"") | E23: =IFERROR(INDEX(Watchlist!H:H,MATCH(SMALL(Watchlist!Y5:Y202,4),Watchlist!Y:Y,0)),0) | F23: =IFERROR(INDEX(Watchlist!P:P,MATCH(SMALL(Watchlist!Y5:Y202,4),Watchlist!Y:Y,0)),0) | G23: =IFERROR((INDEX(Watchlist!Q:Q,MATCH(SMALL(Watchlist!Y5:Y202,4),Watchlist!Y:Y,0))/E23)-1,0) | H23: =IFERROR(INDEX(Watchlist!N:N,MATCH(SMALL(Watchlist!Y5:Y202,4),Watchlist!Y:Y,0)),0) | I23: =IFERROR(SMALL(Watchlist!Y5:Y202,4),0) | J23: =IFERROR(INDEX(Watchlist!Z:Z,MATCH(SMALL(Watchlist!Y5:Y202,4),Watchlist!Y:Y,0)),"") | K23: =IFERROR(LEFT(INDEX(Watchlist!AB:AB,MATCH(SMALL(Watchlist!Y5:Y202,4),Watchlist!Y:Y,0)),80),"")
B24: =IFERROR(INDEX(Watchlist!A:A,MATCH(SMALL(Watchlist!Y5:Y202,5),Watchlist!Y:Y,0)),"") | C24: =IFERROR(INDEX(Watchlist!D:D,MATCH(SMALL(Watchlist!Y5:Y202,5),Watchlist!Y:Y,0)),"") | D24: =IFERROR(INDEX(Watchlist!E:E,MATCH(SMALL(Watchlist!Y5:Y202,5),Watchlist!Y:Y,0)),"") | E24: =IFERROR(INDEX(Watchlist!H:H,MATCH(SMALL(Watchlist!Y5:Y202,5),Watchlist!Y:Y,0)),0) | F24: =IFERROR(INDEX(Watchlist!P:P,MATCH(SMALL(Watchlist!Y5:Y202,5),Watchlist!Y:Y,0)),0) | G24: =IFERROR((INDEX(Watchlist!Q:Q,MATCH(SMALL(Watchlist!Y5:Y202,5),Watchlist!Y:Y,0))/E24)-1,0) | H24: =IFERROR(INDEX(Watchlist!N:N,MATCH(SMALL(Watchlist!Y5:Y202,5),Watchlist!Y:Y,0)),0) | I24: =IFERROR(SMALL(Watchlist!Y5:Y202,5),0) | J24: =IFERROR(INDEX(Watchlist!Z:Z,MATCH(SMALL(Watchlist!Y5:Y202,5),Watchlist!Y:Y,0)),"") | K24: =IFERROR(LEFT(INDEX(Watchlist!AB:AB,MATCH(SMALL(Watchlist!Y5:Y202,5),Watchlist!Y:Y,0)),80),"")
B27: WEEKLY DEPLOYMENT SUMMARY
B28: Available Cash this Week | C28: 1500 | D28: ← edit to your weekly contribution
B29: # Strong Buy signals on Watchlist | C29: =COUNTIF(Watchlist!Z5:Z202,"STRONG BUY")
B30: # Buy signals on Watchlist | C30: =COUNTIF(Watchlist!Z5:Z202,"BUY")
B31: # Trim/Sell signals on Watchlist | C31: =COUNTIF(Watchlist!Z5:Z202,"TRIM")+COUNTIF(Watchlist!Z5:Z202,"SELL")
B32: Avg Composite Score (all 198) | C32: =AVERAGE(Watchlist!Y5:Y202)
B33: Market Heat Reading | C33: =IF(C32>=65,"HOT - selective buying",IF(C32>=50,"BALANCED",IF(C32>=40,"COOL - load up","FROZEN - bargain hunt")))

Sheet Hot Singles
B2: HOT SINGLES — Momentum Leaders
B3: Top 20 cards sorted by 30-day price change. Refreshes when Price History updates.
B5: TOP 20 MOMENTUM (by 30D %)
B6: CardID | C6: Card Name | D6: Set | E6: Current Price | F6: Variant | G6: 7D % | H6: 30D % | I6: 90D % | J6: Score | K6: Signal
B7: =IFERROR(INDEX(Watchlist!A:A,MATCH(LARGE(Watchlist!N5:N202,1),Watchlist!N:N,0)),"") | C7: =IFERROR(INDEX(Watchlist!D:D,MATCH(LARGE(Watchlist!N5:N202,1),Watchlist!N:N,0)),"") | D7: =IFERROR(INDEX(Watchlist!E:E,MATCH(LARGE(Watchlist!N5:N202,1),Watchlist!N:N,0)),"") | E7: =IFERROR(INDEX(Watchlist!H:H,MATCH(LARGE(Watchlist!N5:N202,1),Watchlist!N:N,0)),0) | F7: =IFERROR(INDEX(Watchlist!G:G,MATCH(LARGE(Watchlist!N5:N202,1),Watchlist!N:N,0)),"") | G7: =IFERROR(INDEX(Watchlist!M:M,MATCH(LARGE(Watchlist!N5:N202,1),Watchlist!N:N,0)),0) | H7: =IFERROR(LARGE(Watchlist!N5:N202,1),0) | I7: =IFERROR(INDEX(Watchlist!O:O,MATCH(LARGE(Watchlist!N5:N202,1),Watchlist!N:N,0)),0) | J7: =IFERROR(INDEX(Watchlist!Y:Y,MATCH(LARGE(Watchlist!N5:N202,1),Watchlist!N:N,0)),0) | K7: =IFERROR(INDEX(Watchlist!Z:Z,MATCH(LARGE(Watchlist!N5:N202,1),Watchlist!N:N,0)),"")
B8: =IFERROR(INDEX(Watchlist!A:A,MATCH(LARGE(Watchlist!N5:N202,2),Watchlist!N:N,0)),"") | C8: =IFERROR(INDEX(Watchlist!D:D,MATCH(LARGE(Watchlist!N5:N202,2),Watchlist!N:N,0)),"") | D8: =IFERROR(INDEX(Watchlist!E:E,MATCH(LARGE(Watchlist!N5:N202,2),Watchlist!N:N,0)),"") | E8: =IFERROR(INDEX(Watchlist!H:H,MATCH(LARGE(Watchlist!N5:N202,2),Watchlist!N:N,0)),0) | F8: =IFERROR(INDEX(Watchlist!G:G,MATCH(LARGE(Watchlist!N5:N202,2),Watchlist!N:N,0)),"") | G8: =IFERROR(INDEX(Watchlist!M:M,MATCH(LARGE(Watchlist!N5:N202,2),Watchlist!N:N,0)),0) | H8: =IFERROR(LARGE(Watchlist!N5:N202,2),0) | I8: =IFERROR(INDEX(Watchlist!O:O,MATCH(LARGE(Watchlist!N5:N202,2),Watchlist!N:N,0)),0) | J8: =IFERROR(INDEX(Watchlist!Y:Y,MATCH(LARGE(Watchlist!N5:N202,2),Watchlist!N:N,0)),0) | K8: =IFERROR(INDEX(Watchlist!Z:Z,MATCH(LARGE(Watchlist!N5:N202,2),Watchlist!N:N,0)),"")
B9: =IFERROR(INDEX(Watchlist!A:A,MATCH(LARGE(Watchlist!N5:N202,3),Watchlist!N:N,0)),"") | C9: =IFERROR(INDEX(Watchlist!D:D,MATCH(LARGE(Watchlist!N5:N202,3),Watchlist!N:N,0)),"") | D9: =IFERROR(INDEX(Watchlist!E:E,MATCH(LARGE(Watchlist!N5:N202,3),Watchlist!N:N,0)),"") | E9: =IFERROR(INDEX(Watchlist!H:H,MATCH(LARGE(Watchlist!N5:N202,3),Watchlist!N:N,0)),0) | F9: =IFERROR(INDEX(Watchlist!G:G,MATCH(LARGE(Watchlist!N5:N202,3),Watchlist!N:N,0)),"") | G9: =IFERROR(INDEX(Watchlist!M:M,MATCH(LARGE(Watchlist!N5:N202,3),Watchlist!N:N,0)),0) | H9: =IFERROR(LARGE(Watchlist!N5:N202,3),0) | I9: =IFERROR(INDEX(Watchlist!O:O,MATCH(LARGE(Watchlist!N5:N202,3),Watchlist!N:N,0)),0) | J9: =IFERROR(INDEX(Watchlist!Y:Y,MATCH(LARGE(Watchlist!N5:N202,3),Watchlist!N:N,0)),0) | K9: =IFERROR(INDEX(Watchlist!Z:Z,MATCH(LARGE(Watchlist!N5:N202,3),Watchlist!N:N,0)),"")
B10: =IFERROR(INDEX(Watchlist!A:A,MATCH(LARGE(Watchlist!N5:N202,4),Watchlist!N:N,0)),"") | C10: =IFERROR(INDEX(Watchlist!D:D,MATCH(LARGE(Watchlist!N5:N202,4),Watchlist!N:N,0)),"") | D10: =IFERROR(INDEX(Watchlist!E:E,MATCH(LARGE(Watchlist!N5:N202,4),Watchlist!N:N,0)),"") | E10: =IFERROR(INDEX(Watchlist!H:H,MATCH(LARGE(Watchlist!N5:N202,4),Watchlist!N:N,0)),0) | F10: =IFERROR(INDEX(Watchlist!G:G,MATCH(LARGE(Watchlist!N5:N202,4),Watchlist!N:N,0)),"") | G10: =IFERROR(INDEX(Watchlist!M:M,MATCH(LARGE(Watchlist!N5:N202,4),Watchlist!N:N,0)),0) | H10: =IFERROR(LARGE(Watchlist!N5:N202,4),0) | I10: =IFERROR(INDEX(Watchlist!O:O,MATCH(LARGE(Watchlist!N5:N202,4),Watchlist!N:N,0)),0) | J10: =IFERROR(INDEX(Watchlist!Y:Y,MATCH(LARGE(Watchlist!N5:N202,4),Watchlist!N:N,0)),0) | K10: =IFERROR(INDEX(Watchlist!Z:Z,MATCH(LARGE(Watchlist!N5:N202,4),Watchlist!N:N,0)),"")
B11: =IFERROR(INDEX(Watchlist!A:A,MATCH(LARGE(Watchlist!N5:N202,5),Watchlist!N:N,0)),"") | C11: =IFERROR(INDEX(Watchlist!D:D,MATCH(LARGE(Watchlist!N5:N202,5),Watchlist!N:N,0)),"") | D11: =IFERROR(INDEX(Watchlist!E:E,MATCH(LARGE(Watchlist!N5:N202,5),Watchlist!N:N,0)),"") | E11: =IFERROR(INDEX(Watchlist!H:H,MATCH(LARGE(Watchlist!N5:N202,5),Watchlist!N:N,0)),0) | F11: =IFERROR(INDEX(Watchlist!G:G,MATCH(LARGE(Watchlist!N5:N202,5),Watchlist!N:N,0)),"") | G11: =IFERROR(INDEX(Watchlist!M:M,MATCH(LARGE(Watchlist!N5:N202,5),Watchlist!N:N,0)),0) | H11: =IFERROR(LARGE(Watchlist!N5:N202,5),0) | I11: =IFERROR(INDEX(Watchlist!O:O,MATCH(LARGE(Watchlist!N5:N202,5),Watchlist!N:N,0)),0) | J11: =IFERROR(INDEX(Watchlist!Y:Y,MATCH(LARGE(Watchlist!N5:N202,5),Watchlist!N:N,0)),0) | K11: =IFERROR(INDEX(Watchlist!Z:Z,MATCH(LARGE(Watchlist!N5:N202,5),Watchlist!N:N,0)),"")
B12: =IFERROR(INDEX(Watchlist!A:A,MATCH(LARGE(Watchlist!N5:N202,6),Watchlist!N:N,0)),"") | C12: =IFERROR(INDEX(Watchlist!D:D,MATCH(LARGE(Watchlist!N5:N202,6),Watchlist!N:N,0)),"") | D12: =IFERROR(INDEX(Watchlist!E:E,MATCH(LARGE(Watchlist!N5:N202,6),Watchlist!N:N,0)),"") | E12: =IFERROR(INDEX(Watchlist!H:H,MATCH(LARGE(Watchlist!N5:N202,6),Watchlist!N:N,0)),0) | F12: =IFERROR(INDEX(Watchlist!G:G,MATCH(LARGE(Watchlist!N5:N202,6),Watchlist!N:N,0)),"") | G12: =IFERROR(INDEX(Watchlist!M:M,MATCH(LARGE(Watchlist!N5:N202,6),Watchlist!N:N,0)),0) | H12: =IFERROR(LARGE(Watchlist!N5:N202,6),0) | I12: =IFERROR(INDEX(Watchlist!O:O,MATCH(LARGE(Watchlist!N5:N202,6),Watchlist!N:N,0)),0) | J12: =IFERROR(INDEX(Watchlist!Y:Y,MATCH(LARGE(Watchlist!N5:N202,6),Watchlist!N:N,0)),0) | K12: =IFERROR(INDEX(Watchlist!Z:Z,MATCH(LARGE(Watchlist!N5:N202,6),Watchlist!N:N,0)),"")
B13: =IFERROR(INDEX(Watchlist!A:A,MATCH(LARGE(Watchlist!N5:N202,7),Watchlist!N:N,0)),"") | C13: =IFERROR(INDEX(Watchlist!D:D,MATCH(LARGE(Watchlist!N5:N202,7),Watchlist!N:N,0)),"") | D13: =IFERROR(INDEX(Watchlist!E:E,MATCH(LARGE(Watchlist!N5:N202,7),Watchlist!N:N,0)),"") | E13: =IFERROR(INDEX(Watchlist!H:H,MATCH(LARGE(Watchlist!N5:N202,7),Watchlist!N:N,0)),0) | F13: =IFERROR(INDEX(Watchlist!G:G,MATCH(LARGE(Watchlist!N5:N202,7),Watchlist!N:N,0)),"") | G13: =IFERROR(INDEX(Watchlist!M:M,MATCH(LARGE(Watchlist!N5:N202,7),Watchlist!N:N,0)),0) | H13: =IFERROR(LARGE(Watchlist!N5:N202,7),0) | I13: =IFERROR(INDEX(Watchlist!O:O,MATCH(LARGE(Watchlist!N5:N202,7),Watchlist!N:N,0)),0) | J13: =IFERROR(INDEX(Watchlist!Y:Y,MATCH(LARGE(Watchlist!N5:N202,7),Watchlist!N:N,0)),0) | K13: =IFERROR(INDEX(Watchlist!Z:Z,MATCH(LARGE(Watchlist!N5:N202,7),Watchlist!N:N,0)),"")
B14: =IFERROR(INDEX(Watchlist!A:A,MATCH(LARGE(Watchlist!N5:N202,8),Watchlist!N:N,0)),"") | C14: =IFERROR(INDEX(Watchlist!D:D,MATCH(LARGE(Watchlist!N5:N202,8),Watchlist!N:N,0)),"") | D14: =IFERROR(INDEX(Watchlist!E:E,MATCH(LARGE(Watchlist!N5:N202,8),Watchlist!N:N,0)),"") | E14: =IFERROR(INDEX(Watchlist!H:H,MATCH(LARGE(Watchlist!N5:N202,8),Watchlist!N:N,0)),0) | F14: =IFERROR(INDEX(Watchlist!G:G,MATCH(LARGE(Watchlist!N5:N202,8),Watchlist!N:N,0)),"") | G14: =IFERROR(INDEX(Watchlist!M:M,MATCH(LARGE(Watchlist!N5:N202,8),Watchlist!N:N,0)),0) | H14: =IFERROR(LARGE(Watchlist!N5:N202,8),0) | I14: =IFERROR(INDEX(Watchlist!O:O,MATCH(LARGE(Watchlist!N5:N202,8),Watchlist!N:N,0)),0) | J14: =IFERROR(INDEX(Watchlist!Y:Y,MATCH(LARGE(Watchlist!N5:N202,8),Watchlist!N:N,0)),0) | K14: =IFERROR(INDEX(Watchlist!Z:Z,MATCH(LARGE(Watchlist!N5:N202,8),Watchlist!N:N,0)),"")
B15: =IFERROR(INDEX(Watchlist!A:A,MATCH(LARGE(Watchlist!N5:N202,9),Watchlist!N:N,0)),"") | C15: =IFERROR(INDEX(Watchlist!D:D,MATCH(LARGE(Watchlist!N5:N202,9),Watchlist!N:N,0)),"") | D15: =IFERROR(INDEX(Watchlist!E:E,MATCH(LARGE(Watchlist!N5:N202,9),Watchlist!N:N,0)),"") | E15: =IFERROR(INDEX(Watchlist!H:H,MATCH(LARGE(Watchlist!N5:N202,9),Watchlist!N:N,0)),0) | F15: =IFERROR(INDEX(Watchlist!G:G,MATCH(LARGE(Watchlist!N5:N202,9),Watchlist!N:N,0)),"") | G15: =IFERROR(INDEX(Watchlist!M:M,MATCH(LARGE(Watchlist!N5:N202,9),Watchlist!N:N,0)),0) | H15: =IFERROR(LARGE(Watchlist!N5:N202,9),0) | I15: =IFERROR(INDEX(Watchlist!O:O,MATCH(LARGE(Watchlist!N5:N202,9),Watchlist!N:N,0)),0) | J15: =IFERROR(INDEX(Watchlist!Y:Y,MATCH(LARGE(Watchlist!N5:N202,9),Watchlist!N:N,0)),0) | K15: =IFERROR(INDEX(Watchlist!Z:Z,MATCH(LARGE(Watchlist!N5:N202,9),Watchlist!N:N,0)),"")
B16: =IFERROR(INDEX(Watchlist!A:A,MATCH(LARGE(Watchlist!N5:N202,10),Watchlist!N:N,0)),"") | C16: =IFERROR(INDEX(Watchlist!D:D,MATCH(LARGE(Watchlist!N5:N202,10),Watchlist!N:N,0)),"") | D16: =IFERROR(INDEX(Watchlist!E:E,MATCH(LARGE(Watchlist!N5:N202,10),Watchlist!N:N,0)),"") | E16: =IFERROR(INDEX(Watchlist!H:H,MATCH(LARGE(Watchlist!N5:N202,10),Watchlist!N:N,0)),0) | F16: =IFERROR(INDEX(Watchlist!G:G,MATCH(LARGE(Watchlist!N5:N202,10),Watchlist!N:N,0)),"") | G16: =IFERROR(INDEX(Watchlist!M:M,MATCH(LARGE(Watchlist!N5:N202,10),Watchlist!N:N,0)),0) | H16: =IFERROR(LARGE(Watchlist!N5:N202,10),0) | I16: =IFERROR(INDEX(Watchlist!O:O,MATCH(LARGE(Watchlist!N5:N202,10),Watchlist!N:N,0)),0) | J16: =IFERROR(INDEX(Watchlist!Y:Y,MATCH(LARGE(Watchlist!N5:N202,10),Watchlist!N:N,0)),0) | K16: =IFERROR(INDEX(Watchlist!Z:Z,MATCH(LARGE(Watchlist!N5:N202,10),Watchlist!N:N,0)),"")
B17: =IFERROR(INDEX(Watchlist!A:A,MATCH(LARGE(Watchlist!N5:N202,11),Watchlist!N:N,0)),"") | C17: =IFERROR(INDEX(Watchlist!D:D,MATCH(LARGE(Watchlist!N5:N202,11),Watchlist!N:N,0)),"") | D17: =IFERROR(INDEX(Watchlist!E:E,MATCH(LARGE(Watchlist!N5:N202,11),Watchlist!N:N,0)),"") | E17: =IFERROR(INDEX(Watchlist!H:H,MATCH(LARGE(Watchlist!N5:N202,11),Watchlist!N:N,0)),0) | F17: =IFERROR(INDEX(Watchlist!G:G,MATCH(LARGE(Watchlist!N5:N202,11),Watchlist!N:N,0)),"") | G17: =IFERROR(INDEX(Watchlist!M:M,MATCH(LARGE(Watchlist!N5:N202,11),Watchlist!N:N,0)),0) | H17: =IFERROR(LARGE(Watchlist!N5:N202,11),0) | I17: =IFERROR(INDEX(Watchlist!O:O,MATCH(LARGE(Watchlist!N5:N202,11),Watchlist!N:N,0)),0) | J17: =IFERROR(INDEX(Watchlist!Y:Y,MATCH(LARGE(Watchlist!N5:N202,11),Watchlist!N:N,0)),0) | K17: =IFERROR(INDEX(Watchlist!Z:Z,MATCH(LARGE(Watchlist!N5:N202,11),Watchlist!N:N,0)),"")
B18: =IFERROR(INDEX(Watchlist!A:A,MATCH(LARGE(Watchlist!N5:N202,12),Watchlist!N:N,0)),"") | C18: =IFERROR(INDEX(Watchlist!D:D,MATCH(LARGE(Watchlist!N5:N202,12),Watchlist!N:N,0)),"") | D18: =IFERROR(INDEX(Watchlist!E:E,MATCH(LARGE(Watchlist!N5:N202,12),Watchlist!N:N,0)),"") | E18: =IFERROR(INDEX(Watchlist!H:H,MATCH(LARGE(Watchlist!N5:N202,12),Watchlist!N:N,0)),0) | F18: =IFERROR(INDEX(Watchlist!G:G,MATCH(LARGE(Watchlist!N5:N202,12),Watchlist!N:N,0)),"") | G18: =IFERROR(INDEX(Watchlist!M:M,MATCH(LARGE(Watchlist!N5:N202,12),Watchlist!N:N,0)),0) | H18: =IFERROR(LARGE(Watchlist!N5:N202,12),0) | I18: =IFERROR(INDEX(Watchlist!O:O,MATCH(LARGE(Watchlist!N5:N202,12),Watchlist!N:N,0)),0) | J18: =IFERROR(INDEX(Watchlist!Y:Y,MATCH(LARGE(Watchlist!N5:N202,12),Watchlist!N:N,0)),0) | K18: =IFERROR(INDEX(Watchlist!Z:Z,MATCH(LARGE(Watchlist!N5:N202,12),Watchlist!N:N,0)),"")
B19: =IFERROR(INDEX(Watchlist!A:A,MATCH(LARGE(Watchlist!N5:N202,13),Watchlist!N:N,0)),"") | C19: =IFERROR(INDEX(Watchlist!D:D,MATCH(LARGE(Watchlist!N5:N202,13),Watchlist!N:N,0)),"") | D19: =IFERROR(INDEX(Watchlist!E:E,MATCH(LARGE(Watchlist!N5:N202,13),Watchlist!N:N,0)),"") | E19: =IFERROR(INDEX(Watchlist!H:H,MATCH(LARGE(Watchlist!N5:N202,13),Watchlist!N:N,0)),0) | F19: =IFERROR(INDEX(Watchlist!G:G,MATCH(LARGE(Watchlist!N5:N202,13),Watchlist!N:N,0)),"") | G19: =IFERROR(INDEX(Watchlist!M:M,MATCH(LARGE(Watchlist!N5:N202,13),Watchlist!N:N,0)),0) | H19: =IFERROR(LARGE(Watchlist!N5:N202,13),0) | I19: =IFERROR(INDEX(Watchlist!O:O,MATCH(LARGE(Watchlist!N5:N202,13),Watchlist!N:N,0)),0) | J19: =IFERROR(INDEX(Watchlist!Y:Y,MATCH(LARGE(Watchlist!N5:N202,13),Watchlist!N:N,0)),0) | K19: =IFERROR(INDEX(Watchlist!Z:Z,MATCH(LARGE(Watchlist!N5:N202,13),Watchlist!N:N,0)),"")
B20: =IFERROR(INDEX(Watchlist!A:A,MATCH(LARGE(Watchlist!N5:N202,14),Watchlist!N:N,0)),"") | C20: =IFERROR(INDEX(Watchlist!D:D,MATCH(LARGE(Watchlist!N5:N202,14),Watchlist!N:N,0)),"") | D20: =IFERROR(INDEX(Watchlist!E:E,MATCH(LARGE(Watchlist!N5:N202,14),Watchlist!N:N,0)),"") | E20: =IFERROR(INDEX(Watchlist!H:H,MATCH(LARGE(Watchlist!N5:N202,14),Watchlist!N:N,0)),0) | F20: =IFERROR(INDEX(Watchlist!G:G,MATCH(LARGE(Watchlist!N5:N202,14),Watchlist!N:N,0)),"") | G20: =IFERROR(INDEX(Watchlist!M:M,MATCH(LARGE(Watchlist!N5:N202,14),Watchlist!N:N,0)),0) | H20: =IFERROR(LARGE(Watchlist!N5:N202,14),0) | I20: =IFERROR(INDEX(Watchlist!O:O,MATCH(LARGE(Watchlist!N5:N202,14),Watchlist!N:N,0)),0) | J20: =IFERROR(INDEX(Watchlist!Y:Y,MATCH(LARGE(Watchlist!N5:N202,14),Watchlist!N:N,0)),0) | K20: =IFERROR(INDEX(Watchlist!Z:Z,MATCH(LARGE(Watchlist!N5:N202,14),Watchlist!N:N,0)),"")
B21: =IFERROR(INDEX(Watchlist!A:A,MATCH(LARGE(Watchlist!N5:N202,15),Watchlist!N:N,0)),"") | C21: =IFERROR(INDEX(Watchlist!D:D,MATCH(LARGE(Watchlist!N5:N202,15),Watchlist!N:N,0)),"") | D21: =IFERROR(INDEX(Watchlist!E:E,MATCH(LARGE(Watchlist!N5:N202,15),Watchlist!N:N,0)),"") | E21: =IFERROR(INDEX(Watchlist!H:H,MATCH(LARGE(Watchlist!N5:N202,15),Watchlist!N:N,0)),0) | F21: =IFERROR(INDEX(Watchlist!G:G,MATCH(LARGE(Watchlist!N5:N202,15),Watchlist!N:N,0)),"") | G21: =IFERROR(INDEX(Watchlist!M:M,MATCH(LARGE(Watchlist!N5:N202,15),Watchlist!N:N,0)),0) | H21: =IFERROR(LARGE(Watchlist!N5:N202,15),0) | I21: =IFERROR(INDEX(Watchlist!O:O,MATCH(LARGE(Watchlist!N5:N202,15),Watchlist!N:N,0)),0) | J21: =IFERROR(INDEX(Watchlist!Y:Y,MATCH(LARGE(Watchlist!N5:N202,15),Watchlist!N:N,0)),0) | K21: =IFERROR(INDEX(Watchlist!Z:Z,MATCH(LARGE(Watchlist!N5:N202,15),Watchlist!N:N,0)),"")
B22: =IFERROR(INDEX(Watchlist!A:A,MATCH(LARGE(Watchlist!N5:N202,16),Watchlist!N:N,0)),"") | C22: =IFERROR(INDEX(Watchlist!D:D,MATCH(LARGE(Watchlist!N5:N202,16),Watchlist!N:N,0)),"") | D22: =IFERROR(INDEX(Watchlist!E:E,MATCH(LARGE(Watchlist!N5:N202,16),Watchlist!N:N,0)),"") | E22: =IFERROR(INDEX(Watchlist!H:H,MATCH(LARGE(Watchlist!N5:N202,16),Watchlist!N:N,0)),0) | F22: =IFERROR(INDEX(Watchlist!G:G,MATCH(LARGE(Watchlist!N5:N202,16),Watchlist!N:N,0)),"") | G22: =IFERROR(INDEX(Watchlist!M:M,MATCH(LARGE(Watchlist!N5:N202,16),Watchlist!N:N,0)),0) | H22: =IFERROR(LARGE(Watchlist!N5:N202,16),0) | I22: =IFERROR(INDEX(Watchlist!O:O,MATCH(LARGE(Watchlist!N5:N202,16),Watchlist!N:N,0)),0) | J22: =IFERROR(INDEX(Watchlist!Y:Y,MATCH(LARGE(Watchlist!N5:N202,16),Watchlist!N:N,0)),0) | K22: =IFERROR(INDEX(Watchlist!Z:Z,MATCH(LARGE(Watchlist!N5:N202,16),Watchlist!N:N,0)),"")
B23: =IFERROR(INDEX(Watchlist!A:A,MATCH(LARGE(Watchlist!N5:N202,17),Watchlist!N:N,0)),"") | C23: =IFERROR(INDEX(Watchlist!D:D,MATCH(LARGE(Watchlist!N5:N202,17),Watchlist!N:N,0)),"") | D23: =IFERROR(INDEX(Watchlist!E:E,MATCH(LARGE(Watchlist!N5:N202,17),Watchlist!N:N,0)),"") | E23: =IFERROR(INDEX(Watchlist!H:H,MATCH(LARGE(Watchlist!N5:N202,17),Watchlist!N:N,0)),0) | F23: =IFERROR(INDEX(Watchlist!G:G,MATCH(LARGE(Watchlist!N5:N202,17),Watchlist!N:N,0)),"") | G23: =IFERROR(INDEX(Watchlist!M:M,MATCH(LARGE(Watchlist!N5:N202,17),Watchlist!N:N,0)),0) | H23: =IFERROR(LARGE(Watchlist!N5:N202,17),0) | I23: =IFERROR(INDEX(Watchlist!O:O,MATCH(LARGE(Watchlist!N5:N202,17),Watchlist!N:N,0)),0) | J23: =IFERROR(INDEX(Watchlist!Y:Y,MATCH(LARGE(Watchlist!N5:N202,17),Watchlist!N:N,0)),0) | K23: =IFERROR(INDEX(Watchlist!Z:Z,MATCH(LARGE(Watchlist!N5:N202,17),Watchlist!N:N,0)),"")
B24: =IFERROR(INDEX(Watchlist!A:A,MATCH(LARGE(Watchlist!N5:N202,18),Watchlist!N:N,0)),"") | C24: =IFERROR(INDEX(Watchlist!D:D,MATCH(LARGE(Watchlist!N5:N202,18),Watchlist!N:N,0)),"") | D24: =IFERROR(INDEX(Watchlist!E:E,MATCH(LARGE(Watchlist!N5:N202,18),Watchlist!N:N,0)),"") | E24: =IFERROR(INDEX(Watchlist!H:H,MATCH(LARGE(Watchlist!N5:N202,18),Watchlist!N:N,0)),0) | F24: =IFERROR(INDEX(Watchlist!G:G,MATCH(LARGE(Watchlist!N5:N202,18),Watchlist!N:N,0)),"") | G24: =IFERROR(INDEX(Watchlist!M:M,MATCH(LARGE(Watchlist!N5:N202,18),Watchlist!N:N,0)),0) | H24: =IFERROR(LARGE(Watchlist!N5:N202,18),0) | I24: =IFERROR(INDEX(Watchlist!O:O,MATCH(LARGE(Watchlist!N5:N202,18),Watchlist!N:N,0)),0) | J24: =IFERROR(INDEX(Watchlist!Y:Y,MATCH(LARGE(Watchlist!N5:N202,18),Watchlist!N:N,0)),0) | K24: =IFERROR(INDEX(Watchlist!Z:Z,MATCH(LARGE(Watchlist!N5:N202,18),Watchlist!N:N,0)),"")
B25: =IFERROR(INDEX(Watchlist!A:A,MATCH(LARGE(Watchlist!N5:N202,19),Watchlist!N:N,0)),"") | C25: =IFERROR(INDEX(Watchlist!D:D,MATCH(LARGE(Watchlist!N5:N202,19),Watchlist!N:N,0)),"") | D25: =IFERROR(INDEX(Watchlist!E:E,MATCH(LARGE(Watchlist!N5:N202,19),Watchlist!N:N,0)),"") | E25: =IFERROR(INDEX(Watchlist!H:H,MATCH(LARGE(Watchlist!N5:N202,19),Watchlist!N:N,0)),0) | F25: =IFERROR(INDEX(Watchlist!G:G,MATCH(LARGE(Watchlist!N5:N202,19),Watchlist!N:N,0)),"") | G25: =IFERROR(INDEX(Watchlist!M:M,MATCH(LARGE(Watchlist!N5:N202,19),Watchlist!N:N,0)),0) | H25: =IFERROR(LARGE(Watchlist!N5:N202,19),0) | I25: =IFERROR(INDEX(Watchlist!O:O,MATCH(LARGE(Watchlist!N5:N202,19),Watchlist!N:N,0)),0) | J25: =IFERROR(INDEX(Watchlist!Y:Y,MATCH(LARGE(Watchlist!N5:N202,19),Watchlist!N:N,0)),0) | K25: =IFERROR(INDEX(Watchlist!Z:Z,MATCH(LARGE(Watchlist!N5:N202,19),Watchlist!N:N,0)),"")
B26: =IFERROR(INDEX(Watchlist!A:A,MATCH(LARGE(Watchlist!N5:N202,20),Watchlist!N:N,0)),"") | C26: =IFERROR(INDEX(Watchlist!D:D,MATCH(LARGE(Watchlist!N5:N202,20),Watchlist!N:N,0)),"") | D26: =IFERROR(INDEX(Watchlist!E:E,MATCH(LARGE(Watchlist!N5:N202,20),Watchlist!N:N,0)),"") | E26: =IFERROR(INDEX(Watchlist!H:H,MATCH(LARGE(Watchlist!N5:N202,20),Watchlist!N:N,0)),0) | F26: =IFERROR(INDEX(Watchlist!G:G,MATCH(LARGE(Watchlist!N5:N202,20),Watchlist!N:N,0)),"") | G26: =IFERROR(INDEX(Watchlist!M:M,MATCH(LARGE(Watchlist!N5:N202,20),Watchlist!N:N,0)),0) | H26: =IFERROR(LARGE(Watchlist!N5:N202,20),0) | I26: =IFERROR(INDEX(Watchlist!O:O,MATCH(LARGE(Watchlist!N5:N202,20),Watchlist!N:N,0)),0) | J26: =IFERROR(INDEX(Watchlist!Y:Y,MATCH(LARGE(Watchlist!N5:N202,20),Watchlist!N:N,0)),0) | K26: =IFERROR(INDEX(Watchlist!Z:Z,MATCH(LARGE(Watchlist!N5:N202,20),Watchlist!N:N,0)),"")
B28: OVERSOLD / TURNAROUND CANDIDATES (Bottom 10 by 30D %)
B29: CardID | C29: Card Name | D29: Set | E29: Current Price | F29: Variant | G29: 7D % | H29: 30D % | I29: 90D % | J29: Score | K29: Signal
B30: =IFERROR(INDEX(Watchlist!A:A,MATCH(SMALL(Watchlist!N5:N202,1),Watchlist!N:N,0)),"") | C30: =IFERROR(INDEX(Watchlist!D:D,MATCH(SMALL(Watchlist!N5:N202,1),Watchlist!N:N,0)),"") | D30: =IFERROR(INDEX(Watchlist!E:E,MATCH(SMALL(Watchlist!N5:N202,1),Watchlist!N:N,0)),"") | E30: =IFERROR(INDEX(Watchlist!H:H,MATCH(SMALL(Watchlist!N5:N202,1),Watchlist!N:N,0)),0) | F30: =IFERROR(INDEX(Watchlist!G:G,MATCH(SMALL(Watchlist!N5:N202,1),Watchlist!N:N,0)),"") | G30: =IFERROR(INDEX(Watchlist!M:M,MATCH(SMALL(Watchlist!N5:N202,1),Watchlist!N:N,0)),0) | H30: =IFERROR(SMALL(Watchlist!N5:N202,1),0) | I30: =IFERROR(INDEX(Watchlist!O:O,MATCH(SMALL(Watchlist!N5:N202,1),Watchlist!N:N,0)),0) | J30: =IFERROR(INDEX(Watchlist!Y:Y,MATCH(SMALL(Watchlist!N5:N202,1),Watchlist!N:N,0)),0) | K30: =IFERROR(INDEX(Watchlist!Z:Z,MATCH(SMALL(Watchlist!N5:N202,1),Watchlist!N:N,0)),"")
B31: =IFERROR(INDEX(Watchlist!A:A,MATCH(SMALL(Watchlist!N5:N202,2),Watchlist!N:N,0)),"") | C31: =IFERROR(INDEX(Watchlist!D:D,MATCH(SMALL(Watchlist!N5:N202,2),Watchlist!N:N,0)),"") | D31: =IFERROR(INDEX(Watchlist!E:E,MATCH(SMALL(Watchlist!N5:N202,2),Watchlist!N:N,0)),"") | E31: =IFERROR(INDEX(Watchlist!H:H,MATCH(SMALL(Watchlist!N5:N202,2),Watchlist!N:N,0)),0) | F31: =IFERROR(INDEX(Watchlist!G:G,MATCH(SMALL(Watchlist!N5:N202,2),Watchlist!N:N,0)),"") | G31: =IFERROR(INDEX(Watchlist!M:M,MATCH(SMALL(Watchlist!N5:N202,2),Watchlist!N:N,0)),0) | H31: =IFERROR(SMALL(Watchlist!N5:N202,2),0) | I31: =IFERROR(INDEX(Watchlist!O:O,MATCH(SMALL(Watchlist!N5:N202,2),Watchlist!N:N,0)),0) | J31: =IFERROR(INDEX(Watchlist!Y:Y,MATCH(SMALL(Watchlist!N5:N202,2),Watchlist!N:N,0)),0) | K31: =IFERROR(INDEX(Watchlist!Z:Z,MATCH(SMALL(Watchlist!N5:N202,2),Watchlist!N:N,0)),"")
B32: =IFERROR(INDEX(Watchlist!A:A,MATCH(SMALL(Watchlist!N5:N202,3),Watchlist!N:N,0)),"") | C32: =IFERROR(INDEX(Watchlist!D:D,MATCH(SMALL(Watchlist!N5:N202,3),Watchlist!N:N,0)),"") | D32: =IFERROR(INDEX(Watchlist!E:E,MATCH(SMALL(Watchlist!N5:N202,3),Watchlist!N:N,0)),"") | E32: =IFERROR(INDEX(Watchlist!H:H,MATCH(SMALL(Watchlist!N5:N202,3),Watchlist!N:N,0)),0) | F32: =IFERROR(INDEX(Watchlist!G:G,MATCH(SMALL(Watchlist!N5:N202,3),Watchlist!N:N,0)),"") | G32: =IFERROR(INDEX(Watchlist!M:M,MATCH(SMALL(Watchlist!N5:N202,3),Watchlist!N:N,0)),0) | H32: =IFERROR(SMALL(Watchlist!N5:N202,3),0) | I32: =IFERROR(INDEX(Watchlist!O:O,MATCH(SMALL(Watchlist!N5:N202,3),Watchlist!N:N,0)),0) | J32: =IFERROR(INDEX(Watchlist!Y:Y,MATCH(SMALL(Watchlist!N5:N202,3),Watchlist!N:N,0)),0) | K32: =IFERROR(INDEX(Watchlist!Z:Z,MATCH(SMALL(Watchlist!N5:N202,3),Watchlist!N:N,0)),"")
B33: =IFERROR(INDEX(Watchlist!A:A,MATCH(SMALL(Watchlist!N5:N202,4),Watchlist!N:N,0)),"") | C33: =IFERROR(INDEX(Watchlist!D:D,MATCH(SMALL(Watchlist!N5:N202,4),Watchlist!N:N,0)),"") | D33: =IFERROR(INDEX(Watchlist!E:E,MATCH(SMALL(Watchlist!N5:N202,4),Watchlist!N:N,0)),"") | E33: =IFERROR(INDEX(Watchlist!H:H,MATCH(SMALL(Watchlist!N5:N202,4),Watchlist!N:N,0)),0) | F33: =IFERROR(INDEX(Watchlist!G:G,MATCH(SMALL(Watchlist!N5:N202,4),Watchlist!N:N,0)),"") | G33: =IFERROR(INDEX(Watchlist!M:M,MATCH(SMALL(Watchlist!N5:N202,4),Watchlist!N:N,0)),0) | H33: =IFERROR(SMALL(Watchlist!N5:N202,4),0) | I33: =IFERROR(INDEX(Watchlist!O:O,MATCH(SMALL(Watchlist!N5:N202,4),Watchlist!N:N,0)),0) | J33: =IFERROR(INDEX(Watchlist!Y:Y,MATCH(SMALL(Watchlist!N5:N202,4),Watchlist!N:N,0)),0) | K33: =IFERROR(INDEX(Watchlist!Z:Z,MATCH(SMALL(Watchlist!N5:N202,4),Watchlist!N:N,0)),"")
B34: =IFERROR(INDEX(Watchlist!A:A,MATCH(SMALL(Watchlist!N5:N202,5),Watchlist!N:N,0)),"") | C34: =IFERROR(INDEX(Watchlist!D:D,MATCH(SMALL(Watchlist!N5:N202,5),Watchlist!N:N,0)),"") | D34: =IFERROR(INDEX(Watchlist!E:E,MATCH(SMALL(Watchlist!N5:N202,5),Watchlist!N:N,0)),"") | E34: =IFERROR(INDEX(Watchlist!H:H,MATCH(SMALL(Watchlist!N5:N202,5),Watchlist!N:N,0)),0) | F34: =IFERROR(INDEX(Watchlist!G:G,MATCH(SMALL(Watchlist!N5:N202,5),Watchlist!N:N,0)),"") | G34: =IFERROR(INDEX(Watchlist!M:M,MATCH(SMALL(Watchlist!N5:N202,5),Watchlist!N:N,0)),0) | H34: =IFERROR(SMALL(Watchlist!N5:N202,5),0) | I34: =IFERROR(INDEX(Watchlist!O:O,MATCH(SMALL(Watchlist!N5:N202,5),Watchlist!N:N,0)),0) | J34: =IFERROR(INDEX(Watchlist!Y:Y,MATCH(SMALL(Watchlist!N5:N202,5),Watchlist!N:N,0)),0) | K34: =IFERROR(INDEX(Watchlist!Z:Z,MATCH(SMALL(Watchlist!N5:N202,5),Watchlist!N:N,0)),"")
B35: =IFERROR(INDEX(Watchlist!A:A,MATCH(SMALL(Watchlist!N5:N202,6),Watchlist!N:N,0)),"") | C35: =IFERROR(INDEX(Watchlist!D:D,MATCH(SMALL(Watchlist!N5:N202,6),Watchlist!N:N,0)),"") | D35: =IFERROR(INDEX(Watchlist!E:E,MATCH(SMALL(Watchlist!N5:N202,6),Watchlist!N:N,0)),"") | E35: =IFERROR(INDEX(Watchlist!H:H,MATCH(SMALL(Watchlist!N5:N202,6),Watchlist!N:N,0)),0) | F35: =IFERROR(INDEX(Watchlist!G:G,MATCH(SMALL(Watchlist!N5:N202,6),Watchlist!N:N,0)),"") | G35: =IFERROR(INDEX(Watchlist!M:M,MATCH(SMALL(Watchlist!N5:N202,6),Watchlist!N:N,0)),0) | H35: =IFERROR(SMALL(Watchlist!N5:N202,6),0) | I35: =IFERROR(INDEX(Watchlist!O:O,MATCH(SMALL(Watchlist!N5:N202,6),Watchlist!N:N,0)),0) | J35: =IFERROR(INDEX(Watchlist!Y:Y,MATCH(SMALL(Watchlist!N5:N202,6),Watchlist!N:N,0)),0) | K35: =IFERROR(INDEX(Watchlist!Z:Z,MATCH(SMALL(Watchlist!N5:N202,6),Watchlist!N:N,0)),"")
B36: =IFERROR(INDEX(Watchlist!A:A,MATCH(SMALL(Watchlist!N5:N202,7),Watchlist!N:N,0)),"") | C36: =IFERROR(INDEX(Watchlist!D:D,MATCH(SMALL(Watchlist!N5:N202,7),Watchlist!N:N,0)),"") | D36: =IFERROR(INDEX(Watchlist!E:E,MATCH(SMALL(Watchlist!N5:N202,7),Watchlist!N:N,0)),"") | E36: =IFERROR(INDEX(Watchlist!H:H,MATCH(SMALL(Watchlist!N5:N202,7),Watchlist!N:N,0)),0) | F36: =IFERROR(INDEX(Watchlist!G:G,MATCH(SMALL(Watchlist!N5:N202,7),Watchlist!N:N,0)),"") | G36: =IFERROR(INDEX(Watchlist!M:M,MATCH(SMALL(Watchlist!N5:N202,7),Watchlist!N:N,0)),0) | H36: =IFERROR(SMALL(Watchlist!N5:N202,7),0) | I36: =IFERROR(INDEX(Watchlist!O:O,MATCH(SMALL(Watchlist!N5:N202,7),Watchlist!N:N,0)),0) | J36: =IFERROR(INDEX(Watchlist!Y:Y,MATCH(SMALL(Watchlist!N5:N202,7),Watchlist!N:N,0)),0) | K36: =IFERROR(INDEX(Watchlist!Z:Z,MATCH(SMALL(Watchlist!N5:N202,7),Watchlist!N:N,0)),"")
B37: =IFERROR(INDEX(Watchlist!A:A,MATCH(SMALL(Watchlist!N5:N202,8),Watchlist!N:N,0)),"") | C37: =IFERROR(INDEX(Watchlist!D:D,MATCH(SMALL(Watchlist!N5:N202,8),Watchlist!N:N,0)),"") | D37: =IFERROR(INDEX(Watchlist!E:E,MATCH(SMALL(Watchlist!N5:N202,8),Watchlist!N:N,0)),"") | E37: =IFERROR(INDEX(Watchlist!H:H,MATCH(SMALL(Watchlist!N5:N202,8),Watchlist!N:N,0)),0) | F37: =IFERROR(INDEX(Watchlist!G:G,MATCH(SMALL(Watchlist!N5:N202,8),Watchlist!N:N,0)),"") | G37: =IFERROR(INDEX(Watchlist!M:M,MATCH(SMALL(Watchlist!N5:N202,8),Watchlist!N:N,0)),0) | H37: =IFERROR(SMALL(Watchlist!N5:N202,8),0) | I37: =IFERROR(INDEX(Watchlist!O:O,MATCH(SMALL(Watchlist!N5:N202,8),Watchlist!N:N,0)),0) | J37: =IFERROR(INDEX(Watchlist!Y:Y,MATCH(SMALL(Watchlist!N5:N202,8),Watchlist!N:N,0)),0) | K37: =IFERROR(INDEX(Watchlist!Z:Z,MATCH(SMALL(Watchlist!N5:N202,8),Watchlist!N:N,0)),"")
B38: =IFERROR(INDEX(Watchlist!A:A,MATCH(SMALL(Watchlist!N5:N202,9),Watchlist!N:N,0)),"") | C38: =IFERROR(INDEX(Watchlist!D:D,MATCH(SMALL(Watchlist!N5:N202,9),Watchlist!N:N,0)),"") | D38: =IFERROR(INDEX(Watchlist!E:E,MATCH(SMALL(Watchlist!N5:N202,9),Watchlist!N:N,0)),"") | E38: =IFERROR(INDEX(Watchlist!H:H,MATCH(SMALL(Watchlist!N5:N202,9),Watchlist!N:N,0)),0) | F38: =IFERROR(INDEX(Watchlist!G:G,MATCH(SMALL(Watchlist!N5:N202,9),Watchlist!N:N,0)),"") | G38: =IFERROR(INDEX(Watchlist!M:M,MATCH(SMALL(Watchlist!N5:N202,9),Watchlist!N:N,0)),0) | H38: =IFERROR(SMALL(Watchlist!N5:N202,9),0) | I38: =IFERROR(INDEX(Watchlist!O:O,MATCH(SMALL(Watchlist!N5:N202,9),Watchlist!N:N,0)),0) | J38: =IFERROR(INDEX(Watchlist!Y:Y,MATCH(SMALL(Watchlist!N5:N202,9),Watchlist!N:N,0)),0) | K38: =IFERROR(INDEX(Watchlist!Z:Z,MATCH(SMALL(Watchlist!N5:N202,9),Watchlist!N:N,0)),"")
B39: =IFERROR(INDEX(Watchlist!A:A,MATCH(SMALL(Watchlist!N5:N202,10),Watchlist!N:N,0)),"") | C39: =IFERROR(INDEX(Watchlist!D:D,MATCH(SMALL(Watchlist!N5:N202,10),Watchlist!N:N,0)),"") | D39: =IFERROR(INDEX(Watchlist!E:E,MATCH(SMALL(Watchlist!N5:N202,10),Watchlist!N:N,0)),"") | E39: =IFERROR(INDEX(Watchlist!H:H,MATCH(SMALL(Watchlist!N5:N202,10),Watchlist!N:N,0)),0) | F39: =IFERROR(INDEX(Watchlist!G:G,MATCH(SMALL(Watchlist!N5:N202,10),Watchlist!N:N,0)),"") | G39: =IFERROR(INDEX(Watchlist!M:M,MATCH(SMALL(Watchlist!N5:N202,10),Watchlist!N:N,0)),0) | H39: =IFERROR(SMALL(Watchlist!N5:N202,10),0) | I39: =IFERROR(INDEX(Watchlist!O:O,MATCH(SMALL(Watchlist!N5:N202,10),Watchlist!N:N,0)),0) | J39: =IFERROR(INDEX(Watchlist!Y:Y,MATCH(SMALL(Watchlist!N5:N202,10),Watchlist!N:N,0)),0) | K39: =IFERROR(INDEX(Watchlist!Z:Z,MATCH(SMALL(Watchlist!N5:N202,10),Watchlist!N:N,0)),"")

Sheet Watchlist
A1: WATCHLIST — 674 Cards with Quant Scoring (May 12, 2026)
A2: Composite Score = 0.4×Momentum + 0.25×Value + 0.2×Scarcity + 0.15×Liquidity. Signals refresh automatically when prices update.
A4: CardID | B4: Category | C4: Tier | D4: Card Name | E4: Set | F4: Card # | G4: Variant / Grade | H4: Current Price | I4: Last Updated | J4: Price 7D Ago | K4: Price 30D Ago | L4: Price 90D Ago | M4: 7D % | N4: 30D % | O4: 90D % | P4: Target Buy | Q4: Target Sell | R4: Horizon | S4: Conf | T4: Pop PSA10 | U4: Momentum | V4: Value | W4: Scarcity | X4: Liquidity | Y4: Composite | Z4: Signal | AA4: Source URL | AB4: Notes
A5: V001 | B5: Vintage Graded Singles | C5: T1 | D5: Charizard | E5: Base Set 1st Edition Shadowless | F5: 4/102 | G5: PSA 9 | H5: 32000 | I5: 46153 | J5: 32360.48 | K5: 31986.85 | L5: 30646.16 | M5: =IFERROR((H5-J5)/J5,0) | N5: =IFERROR((H5-K5)/K5,0) | O5: =IFERROR((H5-L5)/L5,0) | P5: 25000 | Q5: 45000 | R5: 5-10yr | S5: 5 | T5: 121 | U5: =MAX(0,MIN(100,50+((M5*0.6)+(N5*0.4))*200)) | V5: =MAX(20,MIN(100,50+(P5-H5)/P5*100)) | W5: =IFERROR(MAX(0,MIN(100,100-LOG10(T5)*16)),60) | X5: =IF(C5="T2",85,IF(C5="T4",70,IF(C5="T1",65,IF(C5="T3",55,45)))) | Y5: =U5*0.55+W5*0.20+V5*0.15+X5*0.10+ROW()/1000000 | Z5: =IF(Y5>=75,"STRONG BUY",IF(Y5>=60,"BUY",IF(Y5>=40,"HOLD",IF(Y5>=25,"TRIM","SELL")))) | AA5: https://www.pricecharting.com/game/pokemon-base-set/charizard-1st-edition-4 | AB5: Crown jewel. PSA 10 is $200K+. Pop ~121 PSA 9 = institutional grade.
A6: V002 | B6: Vintage Graded Singles | C6: T1 | D6: Charizard | E6: Base Set 1st Edition Shadowless | F6: 4/102 | G6: PSA 8 | H6: 9500 | I6: 46153 | J6: 9551.49 | K6: 9278.6 | L6: 8882.26 | M6: =IFERROR((H6-J6)/J6,0) | N6: =IFERROR((H6-K6)/K6,0) | O6: =IFERROR((H6-L6)/L6,0) | P6: 7500 | Q6: 13000 | R6: 5-10yr | S6: 5 | T6: 980 | U6: =MAX(0,MIN(100,50+((M6*0.6)+(N6*0.4))*200)) | V6: =MAX(20,MIN(100,50+(P6-H6)/P6*100)) | W6: =IFERROR(MAX(0,MIN(100,100-LOG10(T6)*16)),60) | X6: =IF(C6="T2",85,IF(C6="T4",70,IF(C6="T1",65,IF(C6="T3",55,45)))) | Y6: =U6*0.55+W6*0.20+V6*0.15+X6*0.10+ROW()/1000000 | Z6: =IF(Y6>=75,"STRONG BUY",IF(Y6>=60,"BUY",IF(Y6>=40,"HOLD",IF(Y6>=25,"TRIM","SELL")))) | AA6: https://www.pricecharting.com/game/pokemon-base-set/charizard-1st-edition-4 | AB6: PSA 8 entry-tier to 1st Ed Charizard. More liquid.
A7: V003 | B7: Vintage Graded Singles | C7: T1 | D7: Charizard | E7: Base Set Shadowless | F7: 4/102 | G7: PSA 9 | H7: 9500 | I7: 46153 | J7: 9491.39 | K7: 9142.94 | L7: 8803.62 | M7: =IFERROR((H7-J7)/J7,0) | N7: =IFERROR((H7-K7)/K7,0) | O7: =IFERROR((H7-L7)/L7,0) | P7: 7500 | Q7: 13000 | R7: 5-10yr | S7: 5 | T7: 600 | U7: =MAX(0,MIN(100,50+((M7*0.6)+(N7*0.4))*200)) | V7: =MAX(20,MIN(100,50+(P7-H7)/P7*100)) | W7: =IFERROR(MAX(0,MIN(100,100-LOG10(T7)*16)),60) | X7: =IF(C7="T2",85,IF(C7="T4",70,IF(C7="T1",65,IF(C7="T3",55,45)))) | Y7: =U7*0.55+W7*0.20+V7*0.15+X7*0.10+ROW()/1000000 | Z7: =IF(Y7>=75,"STRONG BUY",IF(Y7>=60,"BUY",IF(Y7>=40,"HOLD",IF(Y7>=25,"TRIM","SELL")))) | AA7: https://www.pricecharting.com/game/pokemon-base-set/charizard-shadowless-4 | AB7: Shadowless (no 1st Ed stamp). Affordable Charizard institutional play.
A8: V004 | B8: Vintage Graded Singles | C8: T1 | D8: Charizard | E8: Base Set Unlimited | F8: 4/102 | G8: PSA 10 | H8: 8000 | I8: 46153 | J8: 8057.48 | K8: 7499.61 | L8: 7235.96 | M8: =IFERROR((H8-J8)/J8,0) | N8: =IFERROR((H8-K8)/K8,0) | O8: =IFERROR((H8-L8)/L8,0) | P8: 6000 | Q8: 11000 | R8: 5-10yr | S8: 4 | T8: 1800 | U8: =MAX(0,MIN(100,50+((M8*0.6)+(N8*0.4))*200)) | V8: =MAX(20,MIN(100,50+(P8-H8)/P8*100)) | W8: =IFERROR(MAX(0,MIN(100,100-LOG10(T8)*16)),60) | X8: =IF(C8="T2",85,IF(C8="T4",70,IF(C8="T1",65,IF(C8="T3",55,45)))) | Y8: =U8*0.55+W8*0.20+V8*0.15+X8*0.10+ROW()/1000000 | Z8: =IF(Y8>=75,"STRONG BUY",IF(Y8>=60,"BUY",IF(Y8>=40,"HOLD",IF(Y8>=25,"TRIM","SELL")))) | AA8: https://www.pricecharting.com/game/pokemon-base-set/charizard-4 | AB8: Unlimited PSA 10 ceiling. Recent climb on Mega Charizard reintroduction.
A9: V005 | B9: Vintage Graded Singles | C9: T1 | D9: Charizard | E9: Base Set Unlimited | F9: 4/102 | G9: PSA 9 | H9: 3126 | I9: 46153 | J9: 1776.57 | K9: 1697.73 | L9: 1558.03 | M9: =IFERROR((H9-J9)/J9,0) | N9: =IFERROR((H9-K9)/K9,0) | O9: =IFERROR((H9-L9)/L9,0) | P9: 2300 | Q9: 4700 | R9: 5-10yr | S9: 4 | T9: 4500 | U9: =MAX(0,MIN(100,50+((M9*0.6)+(N9*0.4))*200)) | V9: =MAX(20,MIN(100,50+(P9-H9)/P9*100)) | W9: =IFERROR(MAX(0,MIN(100,100-LOG10(T9)*16)),60) | X9: =IF(C9="T2",85,IF(C9="T4",70,IF(C9="T1",65,IF(C9="T3",55,45)))) | Y9: =U9*0.55+W9*0.20+V9*0.15+X9*0.10+ROW()/1000000 | Z9: =IF(Y9>=75,"STRONG BUY",IF(Y9>=60,"BUY",IF(Y9>=40,"HOLD",IF(Y9>=25,"TRIM","SELL")))) | AA9: https://www.pricecharting.com/game/pokemon-base-set/charizard-4 | AB9: Most accessible holo Charizard. Rides Charizard tide.
A10: V006 | B10: Vintage Graded Singles | C10: T1 | D10: Blastoise | E10: Base Set 1st Edition Shadowless | F10: 2/102 | G10: PSA 9 | H10: 6500 | I10: 46153 | J10: 6519.85 | K10: 6394.47 | L10: 6079.81 | M10: =IFERROR((H10-J10)/J10,0) | N10: =IFERROR((H10-K10)/K10,0) | O10: =IFERROR((H10-L10)/L10,0) | P10: 5000 | Q10: 9000 | R10: 5-10yr | S10: 4 | T10: 280 | U10: =MAX(0,MIN(100,50+((M10*0.6)+(N10*0.4))*200)) | V10: =MAX(20,MIN(100,50+(P10-H10)/P10*100)) | W10: =IFERROR(MAX(0,MIN(100,100-LOG10(T10)*16)),60) | X10: =IF(C10="T2",85,IF(C10="T4",70,IF(C10="T1",65,IF(C10="T3",55,45)))) | Y10: =U10*0.55+W10*0.20+V10*0.15+X10*0.10+ROW()/1000000 | Z10: =IF(Y10>=75,"STRONG BUY",IF(Y10>=60,"BUY",IF(Y10>=40,"HOLD",IF(Y10>=25,"TRIM","SELL")))) | AA10: https://www.pricecharting.com/game/pokemon-base-set/blastoise-1st-edition-2 | AB10: Original starter holo. Less Charizard correlation = portfolio diversifier.
A11: V007 | B11: Vintage Graded Singles | C11: T1 | D11: Venusaur | E11: Base Set 1st Edition Shadowless | F11: 15/102 | G11: PSA 9 | H11: 4800 | I11: 46153 | J11: 4820.96 | K11: 4704.15 | L11: 4655.21 | M11: =IFERROR((H11-J11)/J11,0) | N11: =IFERROR((H11-K11)/K11,0) | O11: =IFERROR((H11-L11)/L11,0) | P11: 3800 | Q11: 6800 | R11: 5-10yr | S11: 4 | T11: 320 | U11: =MAX(0,MIN(100,50+((M11*0.6)+(N11*0.4))*200)) | V11: =MAX(20,MIN(100,50+(P11-H11)/P11*100)) | W11: =IFERROR(MAX(0,MIN(100,100-LOG10(T11)*16)),60) | X11: =IF(C11="T2",85,IF(C11="T4",70,IF(C11="T1",65,IF(C11="T3",55,45)))) | Y11: =U11*0.55+W11*0.20+V11*0.15+X11*0.10+ROW()/1000000 | Z11: =IF(Y11>=75,"STRONG BUY",IF(Y11>=60,"BUY",IF(Y11>=40,"HOLD",IF(Y11>=25,"TRIM","SELL")))) | AA11: https://www.pricecharting.com/game/pokemon-base-set/venusaur-1st-edition-15 | AB11: Cheapest of the 3 1st Ed starter holos. Symmetry play with V001/V006.
A12: V008 | B12: Vintage Graded Singles | C12: T1 | D12: Chansey | E12: Base Set 1st Edition | F12: 3/102 | G12: PSA 9 | H12: 1100 | I12: 46153 | J12: 1072.31 | K12: 1076.04 | L12: 980.57 | M12: =IFERROR((H12-J12)/J12,0) | N12: =IFERROR((H12-K12)/K12,0) | O12: =IFERROR((H12-L12)/L12,0) | P12: 850 | Q12: 1500 | R12: 5-10yr | S12: 3 | T12: 850 | U12: =MAX(0,MIN(100,50+((M12*0.6)+(N12*0.4))*200)) | V12: =MAX(20,MIN(100,50+(P12-H12)/P12*100)) | W12: =IFERROR(MAX(0,MIN(100,100-LOG10(T12)*16)),60) | X12: =IF(C12="T2",85,IF(C12="T4",70,IF(C12="T1",65,IF(C12="T3",55,45)))) | Y12: =U12*0.55+W12*0.20+V12*0.15+X12*0.10+ROW()/1000000 | Z12: =IF(Y12>=75,"STRONG BUY",IF(Y12>=60,"BUY",IF(Y12>=40,"HOLD",IF(Y12>=25,"TRIM","SELL")))) | AA12: https://www.pricecharting.com/game/pokemon-base-set/chansey-1st-edition-3 | AB12: Trophy run-up potential. Cheap 1st Ed PSA 9.
A13: V009 | B13: Vintage Graded Singles | C13: T1 | D13: Mewtwo | E13: Base Set 1st Edition | F13: 10/102 | G13: PSA 9 | H13: 1400 | I13: 46153 | J13: 1371.66 | K13: 1323.46 | L13: 1195 | M13: =IFERROR((H13-J13)/J13,0) | N13: =IFERROR((H13-K13)/K13,0) | O13: =IFERROR((H13-L13)/L13,0) | P13: 1100 | Q13: 2000 | R13: 5-10yr | S13: 4 | T13: 700 | U13: =MAX(0,MIN(100,50+((M13*0.6)+(N13*0.4))*200)) | V13: =MAX(20,MIN(100,50+(P13-H13)/P13*100)) | W13: =IFERROR(MAX(0,MIN(100,100-LOG10(T13)*16)),60) | X13: =IF(C13="T2",85,IF(C13="T4",70,IF(C13="T1",65,IF(C13="T3",55,45)))) | Y13: =U13*0.55+W13*0.20+V13*0.15+X13*0.10+ROW()/1000000 | Z13: =IF(Y13>=75,"STRONG BUY",IF(Y13>=60,"BUY",IF(Y13>=40,"HOLD",IF(Y13>=25,"TRIM","SELL")))) | AA13: https://www.pricecharting.com/game/pokemon-base-set/mewtwo-1st-edition-10 | AB13: Mewtwo brand strength; Genesis/Detective Pikachu/Mega exposure.
A14: V010 | B14: Vintage Graded Singles | C14: T1 | D14: Alakazam | E14: Base Set 1st Edition | F14: 1/102 | G14: PSA 9 | H14: 950 | I14: 46153 | J14: 961.58 | K14: 920.9 | L14: 890.98 | M14: =IFERROR((H14-J14)/J14,0) | N14: =IFERROR((H14-K14)/K14,0) | O14: =IFERROR((H14-L14)/L14,0) | P14: 750 | Q14: 1300 | R14: 5-10yr | S14: 3 | T14: 600 | U14: =MAX(0,MIN(100,50+((M14*0.6)+(N14*0.4))*200)) | V14: =MAX(20,MIN(100,50+(P14-H14)/P14*100)) | W14: =IFERROR(MAX(0,MIN(100,100-LOG10(T14)*16)),60) | X14: =IF(C14="T2",85,IF(C14="T4",70,IF(C14="T1",65,IF(C14="T3",55,45)))) | Y14: =U14*0.55+W14*0.20+V14*0.15+X14*0.10+ROW()/1000000 | Z14: =IF(Y14>=75,"STRONG BUY",IF(Y14>=60,"BUY",IF(Y14>=40,"HOLD",IF(Y14>=25,"TRIM","SELL")))) | AA14: https://www.pricecharting.com/game/pokemon-base-set/alakazam-1st-edition-1 | AB14: Card #1/102 collector premium. Cheap entry.
A15: V011 | B15: Vintage Graded Singles | C15: T1 | D15: Ninetales | E15: Base Set 1st Edition | F15: 12/102 | G15: PSA 9 | H15: 1100 | I15: 46153 | J15: 1083.78 | K15: 1035.94 | L15: 977.65 | M15: =IFERROR((H15-J15)/J15,0) | N15: =IFERROR((H15-K15)/K15,0) | O15: =IFERROR((H15-L15)/L15,0) | P15: 850 | Q15: 1500 | R15: 5-10yr | S15: 3 | T15: 500 | U15: =MAX(0,MIN(100,50+((M15*0.6)+(N15*0.4))*200)) | V15: =MAX(20,MIN(100,50+(P15-H15)/P15*100)) | W15: =IFERROR(MAX(0,MIN(100,100-LOG10(T15)*16)),60) | X15: =IF(C15="T2",85,IF(C15="T4",70,IF(C15="T1",65,IF(C15="T3",55,45)))) | Y15: =U15*0.55+W15*0.20+V15*0.15+X15*0.10+ROW()/1000000 | Z15: =IF(Y15>=75,"STRONG BUY",IF(Y15>=60,"BUY",IF(Y15>=40,"HOLD",IF(Y15>=25,"TRIM","SELL")))) | AA15: https://www.pricecharting.com/game/pokemon-base-set/ninetales-1st-edition-12 | AB15: Underrated 1st Ed holo. Strong fox IP.
A16: V012 | B16: Vintage Graded Singles | C16: T1 | D16: Zapdos | E16: Base Set 1st Edition | F16: 16/102 | G16: PSA 9 | H16: 1050 | I16: 46153 | J16: 1037.08 | K16: 992.39 | L16: 961.64 | M16: =IFERROR((H16-J16)/J16,0) | N16: =IFERROR((H16-K16)/K16,0) | O16: =IFERROR((H16-L16)/L16,0) | P16: 800 | Q16: 1400 | R16: 5-10yr | S16: 3 | T16: 540 | U16: =MAX(0,MIN(100,50+((M16*0.6)+(N16*0.4))*200)) | V16: =MAX(20,MIN(100,50+(P16-H16)/P16*100)) | W16: =IFERROR(MAX(0,MIN(100,100-LOG10(T16)*16)),60) | X16: =IF(C16="T2",85,IF(C16="T4",70,IF(C16="T1",65,IF(C16="T3",55,45)))) | Y16: =U16*0.55+W16*0.20+V16*0.15+X16*0.10+ROW()/1000000 | Z16: =IF(Y16>=75,"STRONG BUY",IF(Y16>=60,"BUY",IF(Y16>=40,"HOLD",IF(Y16>=25,"TRIM","SELL")))) | AA16: https://www.pricecharting.com/game/pokemon-base-set/zapdos-1st-edition-16 | AB16: Legendary bird 1st Ed. Cheaper than Articuno/Moltres.
... A40: M001 | B40: Modern Chase PSA 10 | C40: T2 | D40: Umbreon VMAX (Moonbreon) | E40: Evolving Skies | F40: 215/203 | G40: PSA 10 | H40: 4480 | I40: 46153 | J40: 1551.29 | K40: 1650.35 | L40: 1882.05 | M40: =IFERROR((H40-J40)/J40,0) | N40: =IFERROR((H40-K40)/K40,0) | O40: =IFERROR((H40-L40)/L40,0) | P40: 3500 | Q40: 6000 | R40: 5-10yr | S40: 5 | T40: 3500 | U40: =MAX(0,MIN(100,50+((M40*0.6)+(N40*0.4))*200)) | V40: =MAX(20,MIN(100,50+(P40-H40)/P40*100)) | W40: =IFERROR(MAX(0,MIN(100,100-LOG10(T40)*16)),60) | X40: =IF(C40="T2",85,IF(C40="T4",70,IF(C40="T1",65,IF(C40="T3",55,45)))) | Y40: =U40*0.55+W40*0.20+V40*0.15+X40*0.10+ROW()/1000000 | Z40: =IF(Y40>=75,"STRONG BUY",IF(Y40>=60,"BUY",IF(Y40>=40,"HOLD",IF(Y40>=25,"TRIM","SELL")))) | AA40: https://www.tcgplayer.com/product/246723 | AB40: Most-traded modern card. Retraced from $2,300 Oct'25 peak. Re-entry zone.
A41: M002 | B41: Modern Chase PSA 10 | C41: T4 | D41: Umbreon VMAX (Moonbreon) | E41: Evolving Skies | F41: 215/203 | G41: Raw NM | H41: 2100 | I41: 46153 | J41: 559.13 | K41: 629.84 | L41: 775.75 | M41: =IFERROR((H41-J41)/J41,0) | N41: =IFERROR((H41-K41)/K41,0) | O41: =IFERROR((H41-L41)/L41,0) | P41: 1600 | Q41: 3200 | R41: 1-3yr | S41: 4 | U41: =MAX(0,MIN(100,50+((M41*0.6)+(N41*0.4))*200)) | V41: =MAX(20,MIN(100,50+(P41-H41)/P41*100)) | W41: =IFERROR(MAX(0,MIN(100,100-LOG10(T41)*16)),60) | X41: =IF(C41="T2",85,IF(C41="T4",70,IF(C41="T1",65,IF(C41="T3",55,45)))) | Y41: =U41*0.55+W41*0.20+V41*0.15+X41*0.10+ROW()/1000000 | Z41: =IF(Y41>=75,"STRONG BUY",IF(Y41>=60,"BUY",IF(Y41>=40,"HOLD",IF(Y41>=25,"TRIM","SELL")))) | AA41: https://www.tcgplayer.com/product/246723 | AB41: Raw grading play. PSA 10 rate ~42%. Math: $575 cost vs $1,500 = +160% upside.
A42: M003 | B42: Modern Chase PSA 10 | C42: T2 | D42: Rayquaza VMAX Alt Art | E42: Evolving Skies | F42: 218/203 | G42: PSA 10 | H42: 1480 | I42: 46153 | J42: 969.21 | K42: 1009.54 | L42: 1075.11 | M42: =IFERROR((H42-J42)/J42,0) | N42: =IFERROR((H42-K42)/K42,0) | O42: =IFERROR((H42-L42)/L42,0) | P42: 1100 | Q42: 2100 | R42: 5-10yr | S42: 4 | T42: 2800 | U42: =MAX(0,MIN(100,50+((M42*0.6)+(N42*0.4))*200)) | V42: =MAX(20,MIN(100,50+(P42-H42)/P42*100)) | W42: =IFERROR(MAX(0,MIN(100,100-LOG10(T42)*16)),60) | X42: =IF(C42="T2",85,IF(C42="T4",70,IF(C42="T1",65,IF(C42="T3",55,45)))) | Y42: =U42*0.55+W42*0.20+V42*0.15+X42*0.10+ROW()/1000000 | Z42: =IF(Y42>=75,"STRONG BUY",IF(Y42>=60,"BUY",IF(Y42>=40,"HOLD",IF(Y42>=25,"TRIM","SELL")))) | AA42: https://www.tcgplayer.com/product/246726 | AB42: Second-best ES alt art. Dragon legendary tier.
A43: M004 | B43: Modern Chase PSA 10 | C43: T2 | D43: Sylveon VMAX Alt Art | E43: Evolving Skies | F43: 212/203 | G43: PSA 10 | H43: 1200 | I43: 46153 | J43: 701.67 | K43: 655.76 | L43: 592.35 | M43: =IFERROR((H43-J43)/J43,0) | N43: =IFERROR((H43-K43)/K43,0) | O43: =IFERROR((H43-L43)/L43,0) | P43: 900 | Q43: 1800 | R43: 5-10yr | S43: 4 | T43: 2400 | U43: =MAX(0,MIN(100,50+((M43*0.6)+(N43*0.4))*200)) | V43: =MAX(20,MIN(100,50+(P43-H43)/P43*100)) | W43: =IFERROR(MAX(0,MIN(100,100-LOG10(T43)*16)),60) | X43: =IF(C43="T2",85,IF(C43="T4",70,IF(C43="T1",65,IF(C43="T3",55,45)))) | Y43: =U43*0.55+W43*0.20+V43*0.15+X43*0.10+ROW()/1000000 | Z43: =IF(Y43>=75,"STRONG BUY",IF(Y43>=60,"BUY",IF(Y43>=40,"HOLD",IF(Y43>=25,"TRIM","SELL")))) | AA43: https://www.tcgplayer.com/product/246720 | AB43: Eeveelution sister to Moonbreon. Tracks at 50% discount.
A44: M005 | B44: Modern Chase PSA 10 | C44: T2 | D44: Espeon VMAX Alt Art | E44: Evolving Skies | F44: 208/203 | G44: PSA 10 | H44: 1100 | I44: 46153 | J44: 680.13 | K44: 641.61 | L44: 582.01 | M44: =IFERROR((H44-J44)/J44,0) | N44: =IFERROR((H44-K44)/K44,0) | O44: =IFERROR((H44-L44)/L44,0) | P44: 850 | Q44: 1600 | R44: 5-10yr | S44: 4 | T44: 2200 | U44: =MAX(0,MIN(100,50+((M44*0.6)+(N44*0.4))*200)) | V44: =MAX(20,MIN(100,50+(P44-H44)/P44*100)) | W44: =IFERROR(MAX(0,MIN(100,100-LOG10(T44)*16)),60) | X44: =IF(C44="T2",85,IF(C44="T4",70,IF(C44="T1",65,IF(C44="T3",55,45)))) | Y44: =U44*0.55+W44*0.20+V44*0.15+X44*0.10+ROW()/1000000 | Z44: =IF(Y44>=75,"STRONG BUY",IF(Y44>=60,"BUY",IF(Y44>=40,"HOLD",IF(Y44>=25,"TRIM","SELL")))) | AA44: https://www.tcgplayer.com/product/246716 | AB44: Sun Eeveelution. Buy on dips below $550.
A45: M006 | B45: Modern Chase PSA 10 | C45: T2 | D45: Leafeon VMAX Alt Art | E45: Evolving Skies | F45: 205/203 | G45: PSA 10 | H45: 900 | I45: 46153 | J45: 572.17 | K45: 558.52 | L45: 532.32 | M45: =IFERROR((H45-J45)/J45,0) | N45: =IFERROR((H45-K45)/K45,0) | O45: =IFERROR((H45-L45)/L45,0) | P45: 700 | Q45: 1300 | R45: 3-5yr | S45: 3 | T45: 1900 | U45: =MAX(0,MIN(100,50+((M45*0.6)+(N45*0.4))*200)) | V45: =MAX(20,MIN(100,50+(P45-H45)/P45*100)) | W45: =IFERROR(MAX(0,MIN(100,100-LOG10(T45)*16)),60) | X45: =IF(C45="T2",85,IF(C45="T4",70,IF(C45="T1",65,IF(C45="T3",55,45)))) | Y45: =U45*0.55+W45*0.20+V45*0.15+X45*0.10+ROW()/1000000 | Z45: =IF(Y45>=75,"STRONG BUY",IF(Y45>=60,"BUY",IF(Y45>=40,"HOLD",IF(Y45>=25,"TRIM","SELL")))) | AA45: https://www.tcgplayer.com/product/246713 | AB45: Grass Eeveelution. Cheapest of the Eevee alts.
A46: M007 | B46: Modern Chase PSA 10 | C46: T2 | D46: Glaceon VMAX Alt Art | E46: Evolving Skies | F46: 210/203 | G46: PSA 10 | H46: 1000 | I46: 46153 | J46: 618.71 | K46: 571.19 | L46: 518.03 | M46: =IFERROR((H46-J46)/J46,0) | N46: =IFERROR((H46-K46)/K46,0) | O46: =IFERROR((H46-L46)/L46,0) | P46: 750 | Q46: 1450 | R46: 3-5yr | S46: 4 | T46: 1700 | U46: =MAX(0,MIN(100,50+((M46*0.6)+(N46*0.4))*200)) | V46: =MAX(20,MIN(100,50+(P46-H46)/P46*100)) | W46: =IFERROR(MAX(0,MIN(100,100-LOG10(T46)*16)),60) | X46: =IF(C46="T2",85,IF(C46="T4",70,IF(C46="T1",65,IF(C46="T3",55,45)))) | Y46: =U46*0.55+W46*0.20+V46*0.15+X46*0.10+ROW()/1000000 | Z46: =IF(Y46>=75,"STRONG BUY",IF(Y46>=60,"BUY",IF(Y46>=40,"HOLD",IF(Y46>=25,"TRIM","SELL")))) | AA46: https://www.tcgplayer.com/product/246718 | AB46: Ice Eeveelution. Underrated relative to peers.
A47: M008 | B47: Modern Chase PSA 10 | C47: T2 | D47: Jolteon VMAX Alt Art | E47: Evolving Skies | F47: 203/203 | G47: PSA 10 | H47: 980 | I47: 46153 | J47: 629.58 | K47: 615.21 | L47: 568.01 | M47: =IFERROR((H47-J47)/J47,0) | N47: =IFERROR((H47-K47)/K47,0) | O47: =IFERROR((H47-L47)/L47,0) | P47: 750 | Q47: 1400 | R47: 3-5yr | S47: 3 | T47: 1600 | U47: =MAX(0,MIN(100,50+((M47*0.6)+(N47*0.4))*200)) | V47: =MAX(20,MIN(100,50+(P47-H47)/P47*100)) | W47: =IFERROR(MAX(0,MIN(100,100-LOG10(T47)*16)),60) | X47: =IF(C47="T2",85,IF(C47="T4",70,IF(C47="T1",65,IF(C47="T3",55,45)))) | Y47: =U47*0.55+W47*0.20+V47*0.15+X47*0.10+ROW()/1000000 | Z47: =IF(Y47>=75,"STRONG BUY",IF(Y47>=60,"BUY",IF(Y47>=40,"HOLD",IF(Y47>=25,"TRIM","SELL")))) | AA47: https://www.tcgplayer.com/product/246711 | AB47: Electric Eeveelution. Card #203/203 - last in set.
A48: M009 | B48: Modern Chase PSA 10 | C48: T2 | D48: Umbreon V Alt Art | E48: Evolving Skies | F48: 189/203 | G48: PSA 10 | H48: 480 | I48: 46153 | J48: 220 | K48: 218.86 | L48: 213.55 | M48: =IFERROR((H48-J48)/J48,0) | N48: =IFERROR((H48-K48)/K48,0) | O48: =IFERROR((H48-L48)/L48,0) | P48: 360 | Q48: 700 | R48: 2-5yr | S48: 3 | T48: 4500 | U48: =MAX(0,MIN(100,50+((M48*0.6)+(N48*0.4))*200)) | V48: =MAX(20,MIN(100,50+(P48-H48)/P48*100)) | W48: =IFERROR(MAX(0,MIN(100,100-LOG10(T48)*16)),60) | X48: =IF(C48="T2",85,IF(C48="T4",70,IF(C48="T1",65,IF(C48="T3",55,45)))) | Y48: =U48*0.55+W48*0.20+V48*0.15+X48*0.10+ROW()/1000000 | Z48: =IF(Y48>=75,"STRONG BUY",IF(Y48>=60,"BUY",IF(Y48>=40,"HOLD",IF(Y48>=25,"TRIM","SELL")))) | AA48: https://www.tcgplayer.com/product/246697 | AB48: V (not VMAX) Umbreon. Lower entry to Moonbreon adjacency.
A49: M010 | B49: Modern Chase PSA 10 | C49: T2 | D49: Dragonite V Alt Art | E49: Evolving Skies | F49: 192/203 | G49: PSA 10 | H49: 540 | I49: 46153 | J49: 281.04 | K49: 268.16 | L49: 257.88 | M49: =IFERROR((H49-J49)/J49,0) | N49: =IFERROR((H49-K49)/K49,0) | O49: =IFERROR((H49-L49)/L49,0) | P49: 410 | Q49: 800 | R49: 2-5yr | S49: 3 | T49: 3800 | U49: =MAX(0,MIN(100,50+((M49*0.6)+(N49*0.4))*200)) | V49: =MAX(20,MIN(100,50+(P49-H49)/P49*100)) | W49: =IFERROR(MAX(0,MIN(100,100-LOG10(T49)*16)),60) | X49: =IF(C49="T2",85,IF(C49="T4",70,IF(C49="T1",65,IF(C49="T3",55,45)))) | Y49: =U49*0.55+W49*0.20+V49*0.15+X49*0.10+ROW()/1000000 | Z49: =IF(Y49>=75,"STRONG BUY",IF(Y49>=60,"BUY",IF(Y49>=40,"HOLD",IF(Y49>=25,"TRIM","SELL")))) | AA49: https://www.tcgplayer.com/product/246700 | AB49: Pseudo-legendary V alt. Dragon collector cross-buy.
A50: M011 | B50: Modern Chase PSA 10 | C50: T2 | D50: Duraludon VMAX Alt Art | E50: Evolving Skies | F50: 217/203 | G50: PSA 10 | H50: 520 | I50: 46153 | J50: 320.06 | K50: 305.62 | L50: 298.86 | M50: =IFERROR((H50-J50)/J50,0) | N50: =IFERROR((H50-K50)/K50,0) | O50: =IFERROR((H50-L50)/L50,0) | P50: 390 | Q50: 760 | R50: 2-5yr | S50: 3 | T50: 2100 | U50: =MAX(0,MIN(100,50+((M50*0.6)+(N50*0.4))*200)) | V50: =MAX(20,MIN(100,50+(P50-H50)/P50*100)) | W50: =IFERROR(MAX(0,MIN(100,100-LOG10(T50)*16)),60) | X50: =IF(C50="T2",85,IF(C50="T4",70,IF(C50="T1",65,IF(C50="T3",55,45)))) | Y50: =U50*0.55+W50*0.20+V50*0.15+X50*0.10+ROW()/1000000 | Z50: =IF(Y50>=75,"STRONG BUY",IF(Y50>=60,"BUY",IF(Y50>=40,"HOLD",IF(Y50>=25,"TRIM","SELL")))) | AA50: https://www.tcgplayer.com/product/246725 | AB50: Tower mode artwork. Underrated alt.
A51: M012 | B51: Modern Chase PSA 10 | C51: T2 | D51: Rayquaza V Alt Art | E51: Evolving Skies | F51: 194/203 | G51: PSA 10 | H51: 620 | I51: 46153 | J51: 344.11 | K51: 334.16 | L51: 311.02 | M51: =IFERROR((H51-J51)/J51,0) | N51: =IFERROR((H51-K51)/K51,0) | O51: =IFERROR((H51-L51)/L51,0) | P51: 470 | Q51: 920 | R51: 2-5yr | S51: 3 | T51: 3200 | U51: =MAX(0,MIN(100,50+((M51*0.6)+(N51*0.4))*200)) | V51: =MAX(20,MIN(100,50+(P51-H51)/P51*100)) | W51: =IFERROR(MAX(0,MIN(100,100-LOG10(T51)*16)),60) | X51: =IF(C51="T2",85,IF(C51="T4",70,IF(C51="T1",65,IF(C51="T3",55,45)))) | Y51: =U51*0.55+W51*0.20+V51*0.15+X51*0.10+ROW()/1000000 | Z51: =IF(Y51>=75,"STRONG BUY",IF(Y51>=60,"BUY",IF(Y51>=40,"HOLD",IF(Y51>=25,"TRIM","SELL")))) | AA51: https://www.tcgplayer.com/product/246702 | AB51: V version of Rayquaza alt. Cheaper Rayquaza play.
A52: M013 | B52: Modern Chase PSA 10 | C52: T2 | D52: Charizard VMAX Rainbow | E52: Champion's Path | F52: 74/73 | G52: PSA 10 | H52: 1100 | I52: 46153 | J52: 797.77 | K52: 804.19 | L52: 788.64 | M52: =IFERROR((H52-J52)/J52,0) | N52: =IFERROR((H52-K52)/K52,0) | O52: =IFERROR((H52-L52)/L52,0) | P52: 850 | Q52: 1600 | R52: 5-10yr | S52: 4 | T52: 4000 | U52: =MAX(0,MIN(100,50+((M52*0.6)+(N52*0.4))*200)) | V52: =MAX(20,MIN(100,50+(P52-H52)/P52*100)) | W52: =IFERROR(MAX(0,MIN(100,100-LOG10(T52)*16)),60) | X52: =IF(C52="T2",85,IF(C52="T4",70,IF(C52="T1",65,IF(C52="T3",55,45)))) | Y52: =U52*0.55+W52*0.20+V52*0.15+X52*0.10+ROW()/1000000 | Z52: =IF(Y52>=75,"STRONG BUY",IF(Y52>=60,"BUY",IF(Y52>=40,"HOLD",IF(Y52>=25,"TRIM","SELL")))) | AA52: https://www.tcgplayer.com/product/223073 | AB52: Modern Charizard floor. CP sealed reprinted, this card was not.
A53: M014 | B53: Modern Chase PSA 10 | C53: T2 | D53: Charizard V Full Art | E53: Champion's Path | F53: 79/73 | G53: PSA 10 | H53: 580 | I53: 46153 | J53: 370.83 | K53: 372.86 | L53: 357.03 | M53: =IFERROR((H53-J53)/J53,0) | N53: =IFERROR((H53-K53)/K53,0) | O53: =IFERROR((H53-L53)/L53,0) | P53: 440 | Q53: 850 | R53: 3-5yr | S53: 3 | T53: 3500 | U53: =MAX(0,MIN(100,50+((M53*0.6)+(N53*0.4))*200)) | V53: =MAX(20,MIN(100,50+(P53-H53)/P53*100)) | W53: =IFERROR(MAX(0,MIN(100,100-LOG10(T53)*16)),60) | X53: =IF(C53="T2",85,IF(C53="T4",70,IF(C53="T1",65,IF(C53="T3",55,45)))) | Y53: =U53*0.55+W53*0.20+V53*0.15+X53*0.10+ROW()/1000000 | Z53: =IF(Y53>=75,"STRONG BUY",IF(Y53>=60,"BUY",IF(Y53>=40,"HOLD",IF(Y53>=25,"TRIM","SELL")))) | AA53: https://www.tcgplayer.com/product/223078 | AB53: V Full Art Charizard. Sister to Rainbow VMAX.
... A73: M034 | B73: Modern Chase PSA 10 | C73: T2 | D73: Charizard ex SIR | E73: Scarlet & Violet 151 | F73: 199/165 | G73: PSA 10 | H73: 1900 | I73: 46153 | J73: 1168.12 | K73: 1082.4 | L73: 969.66 | M73: =IFERROR((H73-J73)/J73,0) | N73: =IFERROR((H73-K73)/K73,0) | O73: =IFERROR((H73-L73)/L73,0) | P73: 1450 | Q73: 2850 | R73: 3-5yr | S73: 5 | T73: 1900 | U73: =MAX(0,MIN(100,50+((M73*0.6)+(N73*0.4))*200)) | V73: =MAX(20,MIN(100,50+(P73-H73)/P73*100)) | W73: =IFERROR(MAX(0,MIN(100,100-LOG10(T73)*16)),60) | X73: =IF(C73="T2",85,IF(C73="T4",70,IF(C73="T1",65,IF(C73="T3",55,45)))) | Y73: =U73*0.55+W73*0.20+V73*0.15+X73*0.10+ROW()/1000000 | Z73: =IF(Y73>=75,"STRONG BUY",IF(Y73>=60,"BUY",IF(Y73>=40,"HOLD",IF(Y73>=25,"TRIM","SELL")))) | AA73: https://www.tcgplayer.com/product/498100 | AB73: 151 Charizard SIR. Massive Gen 1 nostalgia. Most-flipped 151 card.
A74: M035 | B74: Modern Chase PSA 10 | C74: T4 | D74: Charizard ex SIR | E74: Scarlet & Violet 151 | F74: 199/165 | G74: Raw NM | H74: 350 | I74: 46153 | J74: 348.29 | K74: 337.7 | L74: 305.48 | M74: =IFERROR((H74-J74)/J74,0) | N74: =IFERROR((H74-K74)/K74,0) | O74: =IFERROR((H74-L74)/L74,0) | P74: 270 | Q74: 500 | R74: 1-3yr | S74: 4 | U74: =MAX(0,MIN(100,50+((M74*0.6)+(N74*0.4))*200)) | V74: =MAX(20,MIN(100,50+(P74-H74)/P74*100)) | W74: =IFERROR(MAX(0,MIN(100,100-LOG10(T74)*16)),60) | X74: =IF(C74="T2",85,IF(C74="T4",70,IF(C74="T1",65,IF(C74="T3",55,45)))) | Y74: =U74*0.55+W74*0.20+V74*0.15+X74*0.10+ROW()/1000000 | Z74: =IF(Y74>=75,"STRONG BUY",IF(Y74>=60,"BUY",IF(Y74>=40,"HOLD",IF(Y74>=25,"TRIM","SELL")))) | AA74: https://www.tcgplayer.com/product/498100 | AB74: Raw grading play. PSA 10 rate ~50%. EV $725 / cost $375 = +93%.
A75: M036 | B75: Modern Chase PSA 10 | C75: T2 | D75: Charizard ex Full Art | E75: Scarlet & Violet 151 | F75: 183/165 | G75: PSA 10 | H75: 640 | I75: 46153 | J75: 367.89 | K75: 364.45 | L75: 330.73 | M75: =IFERROR((H75-J75)/J75,0) | N75: =IFERROR((H75-K75)/K75,0) | O75: =IFERROR((H75-L75)/L75,0) | P75: 480 | Q75: 960 | R75: 2-5yr | S75: 4 | T75: 2800 | U75: =MAX(0,MIN(100,50+((M75*0.6)+(N75*0.4))*200)) | V75: =MAX(20,MIN(100,50+(P75-H75)/P75*100)) | W75: =IFERROR(MAX(0,MIN(100,100-LOG10(T75)*16)),60) | X75: =IF(C75="T2",85,IF(C75="T4",70,IF(C75="T1",65,IF(C75="T3",55,45)))) | Y75: =U75*0.55+W75*0.20+V75*0.15+X75*0.10+ROW()/1000000 | Z75: =IF(Y75>=75,"STRONG BUY",IF(Y75>=60,"BUY",IF(Y75>=40,"HOLD",IF(Y75>=25,"TRIM","SELL")))) | AA75: https://www.tcgplayer.com/product/498084 | AB75: Full Art (not SIR) Charizard. Cheaper Charizard exposure.
A76: M037 | B76: Modern Chase PSA 10 | C76: T2 | D76: Mew ex SIR | E76: Scarlet & Violet 151 | F76: 205/165 | G76: PSA 10 | H76: 640 | I76: 46153 | J76: 379.99 | K76: 346.87 | L76: 314.31 | M76: =IFERROR((H76-J76)/J76,0) | N76: =IFERROR((H76-K76)/K76,0) | O76: =IFERROR((H76-L76)/L76,0) | P76: 480 | Q76: 960 | R76: 2-5yr | S76: 4 | T76: 1700 | U76: =MAX(0,MIN(100,50+((M76*0.6)+(N76*0.4))*200)) | V76: =MAX(20,MIN(100,50+(P76-H76)/P76*100)) | W76: =IFERROR(MAX(0,MIN(100,100-LOG10(T76)*16)),60) | X76: =IF(C76="T2",85,IF(C76="T4",70,IF(C76="T1",65,IF(C76="T3",55,45)))) | Y76: =U76*0.55+W76*0.20+V76*0.15+X76*0.10+ROW()/1000000 | Z76: =IF(Y76>=75,"STRONG BUY",IF(Y76>=60,"BUY",IF(Y76>=40,"HOLD",IF(Y76>=25,"TRIM","SELL")))) | AA76: https://www.tcgplayer.com/product/498106 | AB76: Mew brand + SIR. Mythical pull.
A77: M038 | B77: Modern Chase PSA 10 | C77: T2 | D77: Zapdos ex SIR | E77: Scarlet & Violet 151 | F77: 202/165 | G77: PSA 10 | H77: 380 | I77: 46153 | J77: 219.82 | K77: 205.64 | L77: 178.84 | M77: =IFERROR((H77-J77)/J77,0) | N77: =IFERROR((H77-K77)/K77,0) | O77: =IFERROR((H77-L77)/L77,0) | P77: 290 | Q77: 570 | R77: 2-5yr | S77: 3 | T77: 1600 | U77: =MAX(0,MIN(100,50+((M77*0.6)+(N77*0.4))*200)) | V77: =MAX(20,MIN(100,50+(P77-H77)/P77*100)) | W77: =IFERROR(MAX(0,MIN(100,100-LOG10(T77)*16)),60) | X77: =IF(C77="T2",85,IF(C77="T4",70,IF(C77="T1",65,IF(C77="T3",55,45)))) | Y77: =U77*0.55+W77*0.20+V77*0.15+X77*0.10+ROW()/1000000 | Z77: =IF(Y77>=75,"STRONG BUY",IF(Y77>=60,"BUY",IF(Y77>=40,"HOLD",IF(Y77>=25,"TRIM","SELL")))) | AA77: https://www.tcgplayer.com/product/498103 | AB77: Legendary bird SIR. Underpriced vs Mew.
A78: M039 | B78: Modern Chase PSA 10 | C78: T2 | D78: Venusaur ex SIR | E78: Scarlet & Violet 151 | F78: 198/165 | G78: PSA 10 | H78: 480 | I78: 46153 | J78: 280.87 | K78: 256.92 | L78: 235.55 | M78: =IFERROR((H78-J78)/J78,0) | N78: =IFERROR((H78-K78)/K78,0) | O78: =IFERROR((H78-L78)/L78,0) | P78: 360 | Q78: 720 | R78: 2-5yr | S78: 4 | T78: 1500 | U78: =MAX(0,MIN(100,50+((M78*0.6)+(N78*0.4))*200)) | V78: =MAX(20,MIN(100,50+(P78-H78)/P78*100)) | W78: =IFERROR(MAX(0,MIN(100,100-LOG10(T78)*16)),60) | X78: =IF(C78="T2",85,IF(C78="T4",70,IF(C78="T1",65,IF(C78="T3",55,45)))) | Y78: =U78*0.55+W78*0.20+V78*0.15+X78*0.10+ROW()/1000000 | Z78: =IF(Y78>=75,"STRONG BUY",IF(Y78>=60,"BUY",IF(Y78>=40,"HOLD",IF(Y78>=25,"TRIM","SELL")))) | AA78: https://www.tcgplayer.com/product/498099 | AB78: Starter SIR. Trio play with Blastoise.
A79: M040 | B79: Modern Chase PSA 10 | C79: T2 | D79: Blastoise ex SIR | E79: Scarlet & Violet 151 | F79: 200/165 | G79: PSA 10 | H79: 440 | I79: 46153 | J79: 258.18 | K79: 245.16 | L79: 226.4 | M79: =IFERROR((H79-J79)/J79,0) | N79: =IFERROR((H79-K79)/K79,0) | O79: =IFERROR((H79-L79)/L79,0) | P79: 330 | Q79: 660 | R79: 2-5yr | S79: 4 | T79: 1500 | U79: =MAX(0,MIN(100,50+((M79*0.6)+(N79*0.4))*200)) | V79: =MAX(20,MIN(100,50+(P79-H79)/P79*100)) | W79: =IFERROR(MAX(0,MIN(100,100-LOG10(T79)*16)),60) | X79: =IF(C79="T2",85,IF(C79="T4",70,IF(C79="T1",65,IF(C79="T3",55,45)))) | Y79: =U79*0.55+W79*0.20+V79*0.15+X79*0.10+ROW()/1000000 | Z79: =IF(Y79>=75,"STRONG BUY",IF(Y79>=60,"BUY",IF(Y79>=40,"HOLD",IF(Y79>=25,"TRIM","SELL")))) | AA79: https://www.tcgplayer.com/product/498101 | AB79: Starter SIR trio play.
A80: M041 | B80: Modern Chase PSA 10 | C80: T2 | D80: Mewtwo ex SIR | E80: Scarlet & Violet 151 | F80: 201/165 | G80: PSA 10 | H80: 540 | I80: 46153 | J80: 314.6 | K80: 300.83 | L80: 275.56 | M80: =IFERROR((H80-J80)/J80,0) | N80: =IFERROR((H80-K80)/K80,0) | O80: =IFERROR((H80-L80)/L80,0) | P80: 410 | Q80: 810 | R80: 2-5yr | S80: 4 | T80: 1400 | U80: =MAX(0,MIN(100,50+((M80*0.6)+(N80*0.4))*200)) | V80: =MAX(20,MIN(100,50+(P80-H80)/P80*100)) | W80: =IFERROR(MAX(0,MIN(100,100-LOG10(T80)*16)),60) | X80: =IF(C80="T2",85,IF(C80="T4",70,IF(C80="T1",65,IF(C80="T3",55,45)))) | Y80: =U80*0.55+W80*0.20+V80*0.15+X80*0.10+ROW()/1000000 | Z80: =IF(Y80>=75,"STRONG BUY",IF(Y80>=60,"BUY",IF(Y80>=40,"HOLD",IF(Y80>=25,"TRIM","SELL")))) | AA80: https://www.tcgplayer.com/product/498102 | AB80: Mewtwo + SIR. Liquid like Charizard.
A81: M042 | B81: Modern Chase PSA 10 | C81: T2 | D81: Pikachu Master Ball Pattern | E81: Scarlet & Violet 151 | F81: 025/165 | G81: PSA 10 | H81: 380 | I81: 46153 | J81: 212.33 | K81: 197.43 | L81: 172.23 | M81: =IFERROR((H81-J81)/J81,0) | N81: =IFERROR((H81-K81)/K81,0) | O81: =IFERROR((H81-L81)/L81,0) | P81: 290 | Q81: 570 | R81: 2-5yr | S81: 4 | T81: 1800 | U81: =MAX(0,MIN(100,50+((M81*0.6)+(N81*0.4))*200)) | V81: =MAX(20,MIN(100,50+(P81-H81)/P81*100)) | W81: =IFERROR(MAX(0,MIN(100,100-LOG10(T81)*16)),60) | X81: =IF(C81="T2",85,IF(C81="T4",70,IF(C81="T1",65,IF(C81="T3",55,45)))) | Y81: =U81*0.55+W81*0.20+V81*0.15+X81*0.10+ROW()/1000000 | Z81: =IF(Y81>=75,"STRONG BUY",IF(Y81>=60,"BUY",IF(Y81>=40,"HOLD",IF(Y81>=25,"TRIM","SELL")))) | AA81: https://www.tcgplayer.com/product/498075 | AB81: Pokeball patterns are subset chase. Master Ball is the rarest.
A82: M043 | B82: Modern Chase PSA 10 | C82: T2 | D82: Alakazam ex SIR | E82: Scarlet & Violet 151 | F82: 203/165 | G82: PSA 10 | H82: 340 | I82: 46153 | J82: 197.84 | K82: 189.48 | L82: 171 | M82: =IFERROR((H82-J82)/J82,0) | N82: =IFERROR((H82-K82)/K82,0) | O82: =IFERROR((H82-L82)/L82,0) | P82: 260 | Q82: 510 | R82: 2-5yr | S82: 3 | T82: 1400 | U82: =MAX(0,MIN(100,50+((M82*0.6)+(N82*0.4))*200)) | V82: =MAX(20,MIN(100,50+(P82-H82)/P82*100)) | W82: =IFERROR(MAX(0,MIN(100,100-LOG10(T82)*16)),60) | X82: =IF(C82="T2",85,IF(C82="T4",70,IF(C82="T1",65,IF(C82="T3",55,45)))) | Y82: =U82*0.55+W82*0.20+V82*0.15+X82*0.10+ROW()/1000000 | Z82: =IF(Y82>=75,"STRONG BUY",IF(Y82>=60,"BUY",IF(Y82>=40,"HOLD",IF(Y82>=25,"TRIM","SELL")))) | AA82: https://www.tcgplayer.com/product/498104 | AB82: Underrated 151 SIR.
A83: M044 | B83: Modern Chase PSA 10 | C83: T2 | D83: Iono SIR | E83: Paldea Evolved | F83: 269/193 | G83: PSA 10 | H83: 700 | I83: 46153 | J83: 399.71 | K83: 395.94 | L83: 395.03 | M83: =IFERROR((H83-J83)/J83,0) | N83: =IFERROR((H83-K83)/K83,0) | O83: =IFERROR((H83-L83)/L83,0) | P83: 530 | Q83: 1050 | R83: 2-5yr | S83: 4 | T83: 2500 | U83: =MAX(0,MIN(100,50+((M83*0.6)+(N83*0.4))*200)) | V83: =MAX(20,MIN(100,50+(P83-H83)/P83*100)) | W83: =IFERROR(MAX(0,MIN(100,100-LOG10(T83)*16)),60) | X83: =IF(C83="T2",85,IF(C83="T4",70,IF(C83="T1",65,IF(C83="T3",55,45)))) | Y83: =U83*0.55+W83*0.20+V83*0.15+X83*0.10+ROW()/1000000 | Z83: =IF(Y83>=75,"STRONG BUY",IF(Y83>=60,"BUY",IF(Y83>=40,"HOLD",IF(Y83>=25,"TRIM","SELL")))) | AA83: https://www.pricecharting.com/game/pokemon-paldea-evolved/iono-237 | AB83: Trainer waifu classic. Iono pattern follows Marnie.
A84: M045 | B84: Modern Chase PSA 10 | C84: T2 | D84: Tinkaton ex SIR | E84: Paldea Evolved | F84: 265/193 | G84: PSA 10 | H84: 90 | I84: 46153 | J84: 88.33 | K84: 85.86 | L84: 80.33 | M84: =IFERROR((H84-J84)/J84,0) | N84: =IFERROR((H84-K84)/K84,0) | O84: =IFERROR((H84-L84)/L84,0) | P84: 70 | Q84: 140 | R84: 2-5yr | S84: 3 | T84: 1400 | U84: =MAX(0,MIN(100,50+((M84*0.6)+(N84*0.4))*200)) | V84: =MAX(20,MIN(100,50+(P84-H84)/P84*100)) | W84: =IFERROR(MAX(0,MIN(100,100-LOG10(T84)*16)),60) | X84: =IF(C84="T2",85,IF(C84="T4",70,IF(C84="T1",65,IF(C84="T3",55,45)))) | Y84: =U84*0.55+W84*0.20+V84*0.15+X84*0.10+ROW()/1000000 | Z84: =IF(Y84>=75,"STRONG BUY",IF(Y84>=60,"BUY",IF(Y84>=40,"HOLD",IF(Y84>=25,"TRIM","SELL")))) | AA84: https://www.tcgplayer.com/product/505420 | AB84: Newer Pokemon. Cult following.
A85: M046 | B85: Modern Chase PSA 10 | C85: T2 | D85: Charizard ex SIR | E85: Obsidian Flames | F85: 228/197 | G85: PSA 10 | H85: 1500 | I85: 46153 | J85: 928.14 | K85: 850.77 | L85: 765.87 | M85: =IFERROR((H85-J85)/J85,0) | N85: =IFERROR((H85-K85)/K85,0) | O85: =IFERROR((H85-L85)/L85,0) | P85: 1130 | Q85: 2250 | R85: 3-5yr | S85: 5 | T85: 2200 | U85: =MAX(0,MIN(100,50+((M85*0.6)+(N85*0.4))*200)) | V85: =MAX(20,MIN(100,50+(P85-H85)/P85*100)) | W85: =IFERROR(MAX(0,MIN(100,100-LOG10(T85)*16)),60) | X85: =IF(C85="T2",85,IF(C85="T4",70,IF(C85="T1",65,IF(C85="T3",55,45)))) | Y85: =U85*0.55+W85*0.20+V85*0.15+X85*0.10+ROW()/1000000 | Z85: =IF(Y85>=75,"STRONG BUY",IF(Y85>=60,"BUY",IF(Y85>=40,"HOLD",IF(Y85>=25,"TRIM","SELL")))) | AA85: https://www.tcgplayer.com/product/521988 | AB85: OF Charizard SIR. Up 10%/30D. Top momentum pick.
A86: M047 | B86: Modern Chase PSA 10 | C86: T4 | D86: Charizard ex SIR | E86: Obsidian Flames | F86: 228/197 | G86: Raw NM | H86: 280 | I86: 46153 | J86: 265.83 | K86: 233.24 | L86: 193.67 | M86: =IFERROR((H86-J86)/J86,0) | N86: =IFERROR((H86-K86)/K86,0) | O86: =IFERROR((H86-L86)/L86,0) | P86: 220 | Q86: 400 | R86: 1-2yr | S86: 4 | U86: =MAX(0,MIN(100,50+((M86*0.6)+(N86*0.4))*200)) | V86: =MAX(20,MIN(100,50+(P86-H86)/P86*100)) | W86: =IFERROR(MAX(0,MIN(100,100-LOG10(T86)*16)),60) | X86: =IF(C86="T2",85,IF(C86="T4",70,IF(C86="T1",65,IF(C86="T3",55,45)))) | Y86: =U86*0.55+W86*0.20+V86*0.15+X86*0.10+ROW()/1000000 | Z86: =IF(Y86>=75,"STRONG BUY",IF(Y86>=60,"BUY",IF(Y86>=40,"HOLD",IF(Y86>=25,"TRIM","SELL")))) | AA86: https://www.pricecharting.com/game/pokemon-obsidian-flames/charizard-ex-special-illustration-rare-215 | AB86: Top raw grading play this month. +18%/30D.
A87: M048 | B87: Modern Chase PSA 10 | C87: T2 | D87: Tyranitar ex SIR | E87: Obsidian Flames | F87: 230/197 | G87: PSA 10 | H87: 320 | I87: 46153 | J87: 175.1 | K87: 168.79 | L87: 156.24 | M87: =IFERROR((H87-J87)/J87,0) | N87: =IFERROR((H87-K87)/K87,0) | O87: =IFERROR((H87-L87)/L87,0) | P87: 240 | Q87: 480 | R87: 2-5yr | S87: 3 | T87: 1700 | U87: =MAX(0,MIN(100,50+((M87*0.6)+(N87*0.4))*200)) | V87: =MAX(20,MIN(100,50+(P87-H87)/P87*100)) | W87: =IFERROR(MAX(0,MIN(100,100-LOG10(T87)*16)),60) | X87: =IF(C87="T2",85,IF(C87="T4",70,IF(C87="T1",65,IF(C87="T3",55,45)))) | Y87: =U87*0.55+W87*0.20+V87*0.15+X87*0.10+ROW()/1000000 | Z87: =IF(Y87>=75,"STRONG BUY",IF(Y87>=60,"BUY",IF(Y87>=40,"HOLD",IF(Y87>=25,"TRIM","SELL")))) | AA87: https://www.tcgplayer.com/product/521990 | AB87: Underrated OF SIR. Tyranitar fanbase.
A88: M049 | B88: Modern Chase PSA 10 | C88: T2 | D88: Mela SIR | E88: Obsidian Flames | F88: 229/197 | G88: PSA 10 | H88: 480 | I88: 46153 | J88: 274.18 | K88: 259.62 | L88: 237.99 | M88: =IFERROR((H88-J88)/J88,0) | N88: =IFERROR((H88-K88)/K88,0) | O88: =IFERROR((H88-L88)/L88,0) | P88: 360 | Q88: 720 | R88: 2-5yr | S88: 4 | T88: 1900 | U88: =MAX(0,MIN(100,50+((M88*0.6)+(N88*0.4))*200)) | V88: =MAX(20,MIN(100,50+(P88-H88)/P88*100)) | W88: =IFERROR(MAX(0,MIN(100,100-LOG10(T88)*16)),60) | X88: =IF(C88="T2",85,IF(C88="T4",70,IF(C88="T1",65,IF(C88="T3",55,45)))) | Y88: =U88*0.55+W88*0.20+V88*0.15+X88*0.10+ROW()/1000000 | Z88: =IF(Y88>=75,"STRONG BUY",IF(Y88>=60,"BUY",IF(Y88>=40,"HOLD",IF(Y88>=25,"TRIM","SELL")))) | AA88: https://www.tcgplayer.com/product/521989 | AB88: Trainer SIR. Follow Iono playbook.
A89: M050 | B89: Modern Chase PSA 10 | C89: T2 | D89: Iron Hands ex Alt Art | E89: Paradox Rift | F89: 228/182 | G89: PSA 10 | H89: 280 | I89: 46153 | J89: 155.69 | K89: 152.15 | L89: 140.12 | M89: =IFERROR((H89-J89)/J89,0) | N89: =IFERROR((H89-K89)/K89,0) | O89: =IFERROR((H89-L89)/L89,0) | P89: 210 | Q89: 420 | R89: 2-5yr | S89: 3 | T89: 1500 | U89: =MAX(0,MIN(100,50+((M89*0.6)+(N89*0.4))*200)) | V89: =MAX(20,MIN(100,50+(P89-H89)/P89*100)) | W89: =IFERROR(MAX(0,MIN(100,100-LOG10(T89)*16)),60) | X89: =IF(C89="T2",85,IF(C89="T4",70,IF(C89="T1",65,IF(C89="T3",55,45)))) | Y89: =U89*0.55+W89*0.20+V89*0.15+X89*0.10+ROW()/1000000 | Z89: =IF(Y89>=75,"STRONG BUY",IF(Y89>=60,"BUY",IF(Y89>=40,"HOLD",IF(Y89>=25,"TRIM","SELL")))) | AA89: https://www.tcgplayer.com/product/536451 | AB89: Future paradox Pokemon. Niche but growing.
A90: M051 | B90: Modern Chase PSA 10 | C90: T2 | D90: Roaring Moon ex Alt Art | E90: Paradox Rift | F90: 229/182 | G90: PSA 10 | H90: 340 | I90: 46153 | J90: 194.84 | K90: 189.54 | L90: 169.25 | M90: =IFERROR((H90-J90)/J90,0) | N90: =IFERROR((H90-K90)/K90,0) | O90: =IFERROR((H90-L90)/L90,0) | P90: 260 | Q90: 510 | R90: 2-5yr | S90: 4 | T90: 1600 | U90: =MAX(0,MIN(100,50+((M90*0.6)+(N90*0.4))*200)) | V90: =MAX(20,MIN(100,50+(P90-H90)/P90*100)) | W90: =IFERROR(MAX(0,MIN(100,100-LOG10(T90)*16)),60) | X90: =IF(C90="T2",85,IF(C90="T4",70,IF(C90="T1",65,IF(C90="T3",55,45)))) | Y90: =U90*0.55+W90*0.20+V90*0.15+X90*0.10+ROW()/1000000 | Z90: =IF(Y90>=75,"STRONG BUY",IF(Y90>=60,"BUY",IF(Y90>=40,"HOLD",IF(Y90>=25,"TRIM","SELL")))) | AA90: https://www.tcgplayer.com/product/536452 | AB90: Past paradox. Strong art.
A91: M052 | B91: Modern Chase PSA 10 | C91: T2 | D91: Penny SIR | E91: Paradox Rift | F91: 238/182 | G91: PSA 10 | H91: 380 | I91: 46153 | J91: 211.56 | K91: 201.88 | L91: 178.69 | M91: =IFERROR((H91-J91)/J91,0) | N91: =IFERROR((H91-K91)/K91,0) | O91: =IFERROR((H91-L91)/L91,0) | P91: 290 | Q91: 570 | R91: 2-5yr | S91: 4 | T91: 1800 | U91: =MAX(0,MIN(100,50+((M91*0.6)+(N91*0.4))*200)) | V91: =MAX(20,MIN(100,50+(P91-H91)/P91*100)) | W91: =IFERROR(MAX(0,MIN(100,100-LOG10(T91)*16)),60) | X91: =IF(C91="T2",85,IF(C91="T4",70,IF(C91="T1",65,IF(C91="T3",55,45)))) | Y91: =U91*0.55+W91*0.20+V91*0.15+X91*0.10+ROW()/1000000 | Z91: =IF(Y91>=75,"STRONG BUY",IF(Y91>=60,"BUY",IF(Y91>=40,"HOLD",IF(Y91>=25,"TRIM","SELL")))) | AA91: https://www.tcgplayer.com/product/536461 | AB91: Penny trainer SIR. Younger trainer demographic.
A92: M053 | B92: Modern Chase PSA 10 | C92: T2 | D92: Garchomp ex Alt Art | E92: Paradox Rift | F92: 230/182 | G92: PSA 10 | H92: 240 | I92: 46153 | J92: 137.41 | K92: 136.93 | L92: 127.22 | M92: =IFERROR((H92-J92)/J92,0) | N92: =IFERROR((H92-K92)/K92,0) | O92: =IFERROR((H92-L92)/L92,0) | P92: 180 | Q92: 360 | R92: 2-5yr | S92: 3 | T92: 1700 | U92: =MAX(0,MIN(100,50+((M92*0.6)+(N92*0.4))*200)) | V92: =MAX(20,MIN(100,50+(P92-H92)/P92*100)) | W92: =IFERROR(MAX(0,MIN(100,100-LOG10(T92)*16)),60) | X92: =IF(C92="T2",85,IF(C92="T4",70,IF(C92="T1",65,IF(C92="T3",55,45)))) | Y92: =U92*0.55+W92*0.20+V92*0.15+X92*0.10+ROW()/1000000 | Z92: =IF(Y92>=75,"STRONG BUY",IF(Y92>=60,"BUY",IF(Y92>=40,"HOLD",IF(Y92>=25,"TRIM","SELL")))) | AA92: https://www.tcgplayer.com/product/536453 | AB92: Garchomp consistent fan favorite.
A93: M054 | B93: Modern Chase PSA 10 | C93: T2 | D93: Roaring Moon ex SIR | E93: Paradox Rift | F93: 251/182 | G93: PSA 10 | H93: 640 | I93: 46153 | J93: 372.63 | K93: 353.44 | L93: 315.12 | M93: =IFERROR((H93-J93)/J93,0) | N93: =IFERROR((H93-K93)/K93,0) | O93: =IFERROR((H93-L93)/L93,0) | P93: 480 | Q93: 960 | R93: 2-5yr | S93: 4 | T93: 1400 | U93: =MAX(0,MIN(100,50+((M93*0.6)+(N93*0.4))*200)) | V93: =MAX(20,MIN(100,50+(P93-H93)/P93*100)) | W93: =IFERROR(MAX(0,MIN(100,100-LOG10(T93)*16)),60) | X93: =IF(C93="T2",85,IF(C93="T4",70,IF(C93="T1",65,IF(C93="T3",55,45)))) | Y93: =U93*0.55+W93*0.20+V93*0.15+X93*0.10+ROW()/1000000 | Z93: =IF(Y93>=75,"STRONG BUY",IF(Y93>=60,"BUY",IF(Y93>=40,"HOLD",IF(Y93>=25,"TRIM","SELL")))) | AA93: https://www.tcgplayer.com/product/536474 | AB93: SIR version of M051. Better art, higher premium.
A94: M055 | B94: Modern Chase PSA 10 | C94: T2 | D94: Garchomp ex SIR | E94: Paradox Rift | F94: 252/182 | G94: PSA 10 | H94: 480 | I94: 46153 | J94: 279.11 | K94: 266.2 | L94: 248.24 | M94: =IFERROR((H94-J94)/J94,0) | N94: =IFERROR((H94-K94)/K94,0) | O94: =IFERROR((H94-L94)/L94,0) | P94: 360 | Q94: 720 | R94: 2-5yr | S94: 3 | T94: 1500 | U94: =MAX(0,MIN(100,50+((M94*0.6)+(N94*0.4))*200)) | V94: =MAX(20,MIN(100,50+(P94-H94)/P94*100)) | W94: =IFERROR(MAX(0,MIN(100,100-LOG10(T94)*16)),60) | X94: =IF(C94="T2",85,IF(C94="T4",70,IF(C94="T1",65,IF(C94="T3",55,45)))) | Y94: =U94*0.55+W94*0.20+V94*0.15+X94*0.10+ROW()/1000000 | Z94: =IF(Y94>=75,"STRONG BUY",IF(Y94>=60,"BUY",IF(Y94>=40,"HOLD",IF(Y94>=25,"TRIM","SELL")))) | AA94: https://www.tcgplayer.com/product/536475 | AB94: SIR Garchomp. Pseudo-legendary play.
A95: M056 | B95: Modern Chase PSA 10 | C95: T2 | D95: Charizard ex Shiny | E95: Paldean Fates | F95: 234/091 | G95: PSA 10 | H95: 740 | I95: 46153 | J95: 453.26 | K95: 439.01 | L95: 414.79 | M95: =IFERROR((H95-J95)/J95,0) | N95: =IFERROR((H95-K95)/K95,0) | O95: =IFERROR((H95-L95)/L95,0) | P95: 560 | Q95: 1110 | R95: 2-5yr | S95: 4 | T95: 2300 | U95: =MAX(0,MIN(100,50+((M95*0.6)+(N95*0.4))*200)) | V95: =MAX(20,MIN(100,50+(P95-H95)/P95*100)) | W95: =IFERROR(MAX(0,MIN(100,100-LOG10(T95)*16)),60) | X95: =IF(C95="T2",85,IF(C95="T4",70,IF(C95="T1",65,IF(C95="T3",55,45)))) | Y95: =U95*0.55+W95*0.20+V95*0.15+X95*0.10+ROW()/1000000 | Z95: =IF(Y95>=75,"STRONG BUY",IF(Y95>=60,"BUY",IF(Y95>=40,"HOLD",IF(Y95>=25,"TRIM","SELL")))) | AA95: https://www.tcgplayer.com/product/542687 | AB95: Shiny Charizard from PF. Already popular collector chase.
A96: M057 | B96: Modern Chase PSA 10 | C96: T2 | D96: Mewtwo ex Shiny | E96: Paldean Fates | F96: 235/091 | G96: PSA 10 | H96: 640 | I96: 46153 | J96: 377.88 | K96: 360.82 | L96: 337.62 | M96: =IFERROR((H96-J96)/J96,0) | N96: =IFERROR((H96-K96)/K96,0) | O96: =IFERROR((H96-L96)/L96,0) | P96: 480 | Q96: 960 | R96: 2-5yr | S96: 4 | T96: 2100 | U96: =MAX(0,MIN(100,50+((M96*0.6)+(N96*0.4))*200)) | V96: =MAX(20,MIN(100,50+(P96-H96)/P96*100)) | W96: =IFERROR(MAX(0,MIN(100,100-LOG10(T96)*16)),60) | X96: =IF(C96="T2",85,IF(C96="T4",70,IF(C96="T1",65,IF(C96="T3",55,45)))) | Y96: =U96*0.55+W96*0.20+V96*0.15+X96*0.10+ROW()/1000000 | Z96: =IF(Y96>=75,"STRONG BUY",IF(Y96>=60,"BUY",IF(Y96>=40,"HOLD",IF(Y96>=25,"TRIM","SELL")))) | AA96: https://www.tcgplayer.com/product/542688 | AB96: Shiny Mewtwo. Mewtwo brand.
A97: M058 | B97: Modern Chase PSA 10 | C97: T2 | D97: Pikachu Shiny | E97: Paldean Fates | F97: 232/091 | G97: PSA 10 | H97: 400 | I97: 46153 | J97: 239.93 | K97: 224.78 | L97: 208.09 | M97: =IFERROR((H97-J97)/J97,0) | N97: =IFERROR((H97-K97)/K97,0) | O97: =IFERROR((H97-L97)/L97,0) | P97: 300 | Q97: 600 | R97: 2-5yr | S97: 4 | T97: 2500 | U97: =MAX(0,MIN(100,50+((M97*0.6)+(N97*0.4))*200)) | V97: =MAX(20,MIN(100,50+(P97-H97)/P97*100)) | W97: =IFERROR(MAX(0,MIN(100,100-LOG10(T97)*16)),60) | X97: =IF(C97="T2",85,IF(C97="T4",70,IF(C97="T1",65,IF(C97="T3",55,45)))) | Y97: =U97*0.55+W97*0.20+V97*0.15+X97*0.10+ROW()/1000000 | Z97: =IF(Y97>=75,"STRONG BUY",IF(Y97>=60,"BUY",IF(Y97>=40,"HOLD",IF(Y97>=25,"TRIM","SELL")))) | AA97: https://www.tcgplayer.com/product/542685 | AB97: Shiny Pikachu - always strong demand.
A98: M059 | B98: Modern Chase PSA 10 | C98: T2 | D98: Greninja ex SIR | E98: Twilight Masquerade | F98: 232/167 | G98: PSA 10 | H98: 540 | I98: 46153 | J98: 307.82 | K98: 289.93 | L98: 258.35 | M98: =IFERROR((H98-J98)/J98,0) | N98: =IFERROR((H98-K98)/K98,0) | O98: =IFERROR((H98-L98)/L98,0) | P98: 410 | Q98: 810 | R98: 2-5yr | S98: 4 | T98: 1800 | U98: =MAX(0,MIN(100,50+((M98*0.6)+(N98*0.4))*200)) | V98: =MAX(20,MIN(100,50+(P98-H98)/P98*100)) | W98: =IFERROR(MAX(0,MIN(100,100-LOG10(T98)*16)),60) | X98: =IF(C98="T2",85,IF(C98="T4",70,IF(C98="T1",65,IF(C98="T3",55,45)))) | Y98: =U98*0.55+W98*0.20+V98*0.15+X98*0.10+ROW()/1000000 | Z98: =IF(Y98>=75,"STRONG BUY",IF(Y98>=60,"BUY",IF(Y98>=40,"HOLD",IF(Y98>=25,"TRIM","SELL")))) | AA98: https://www.tcgplayer.com/product/567103 | AB98: Greninja chase. Strong art.
... A108: M069 | B108: Modern Chase PSA 10 | C108: T2 | D108: Umbreon ex SIR | E108: Prismatic Evolutions | F108: 161/131 | G108: PSA 10 | H108: 5200 | I108: 46153 | J108: 4035.72 | K108: 3999.78 | L108: 3982.85 | M108: =IFERROR((H108-J108)/J108,0) | N108: =IFERROR((H108-K108)/K108,0) | O108: =IFERROR((H108-L108)/L108,0) | P108: 3900 | Q108: 7800 | R108: 5-10yr | S108: 5 | T108: 800 | U108: =MAX(0,MIN(100,50+((M108*0.6)+(N108*0.4))*200)) | V108: =MAX(20,MIN(100,50+(P108-H108)/P108*100)) | W108: =IFERROR(MAX(0,MIN(100,100-LOG10(T108)*16)),60) | X108: =IF(C108="T2",85,IF(C108="T4",70,IF(C108="T1",65,IF(C108="T3",55,45)))) | Y108: =U108*0.55+W108*0.20+V108*0.15+X108*0.10+ROW()/1000000 | Z108: =IF(Y108>=75,"STRONG BUY",IF(Y108>=60,"BUY",IF(Y108>=40,"HOLD",IF(Y108>=25,"TRIM","SELL")))) | AA108: https://www.pricecharting.com/game/pokemon-prismatic-evolutions/umbreon-ex-161 | AB108: PE Umbreon SIR. Most expensive S&V card. PSA 10 climbing.
A109: M070 | B109: Modern Chase PSA 10 | C109: T4 | D109: Umbreon ex SIR | E109: Prismatic Evolutions | F109: 161/131 | G109: Raw NM | H109: 1300 | I109: 46153 | J109: 986.57 | K109: 980.53 | L109: 1007.86 | M109: =IFERROR((H109-J109)/J109,0) | N109: =IFERROR((H109-K109)/K109,0) | O109: =IFERROR((H109-L109)/L109,0) | P109: 980 | Q109: 1950 | R109: 2-5yr | S109: 5 | U109: =MAX(0,MIN(100,50+((M109*0.6)+(N109*0.4))*200)) | V109: =MAX(20,MIN(100,50+(P109-H109)/P109*100)) | W109: =IFERROR(MAX(0,MIN(100,100-LOG10(T109)*16)),60) | X109: =IF(C109="T2",85,IF(C109="T4",70,IF(C109="T1",65,IF(C109="T3",55,45)))) | Y109: =U109*0.55+W109*0.20+V109*0.15+X109*0.10+ROW()/1000000 | Z109: =IF(Y109>=75,"STRONG BUY",IF(Y109>=60,"BUY",IF(Y109>=40,"HOLD",IF(Y109>=25,"TRIM","SELL")))) | AA109: https://www.tcgplayer.com/product/610516 | AB109: Raw PE Umbreon. Grade and flip - cleanest math in the game right now.
A110: M071 | B110: Modern Chase PSA 10 | C110: T2 | D110: Sylveon ex SIR | E110: Prismatic Evolutions | F110: 156/131 | G110: PSA 10 | H110: 1500 | I110: 46153 | J110: 1184.42 | K110: 1141.7 | L110: 1083.48 | M110: =IFERROR((H110-J110)/J110,0) | N110: =IFERROR((H110-K110)/K110,0) | O110: =IFERROR((H110-L110)/L110,0) | P110: 1130 | Q110: 2250 | R110: 2-5yr | S110: 4 | T110: 1200 | U110: =MAX(0,MIN(100,50+((M110*0.6)+(N110*0.4))*200)) | V110: =MAX(20,MIN(100,50+(P110-H110)/P110*100)) | W110: =IFERROR(MAX(0,MIN(100,100-LOG10(T110)*16)),60) | X110: =IF(C110="T2",85,IF(C110="T4",70,IF(C110="T1",65,IF(C110="T3",55,45)))) | Y110: =U110*0.55+W110*0.20+V110*0.15+X110*0.10+ROW()/1000000 | Z110: =IF(Y110>=75,"STRONG BUY",IF(Y110>=60,"BUY",IF(Y110>=40,"HOLD",IF(Y110>=25,"TRIM","SELL")))) | AA110: https://www.pricecharting.com/game/pokemon-prismatic-evolutions/sylveon-ex-156 | AB110: PE Sylveon SIR. 30-40% discount to Umbreon.
A111: M072 | B111: Modern Chase PSA 10 | C111: T2 | D111: Espeon ex SIR | E111: Prismatic Evolutions | F111: 155/131 | G111: PSA 10 | H111: 1400 | I111: 46153 | J111: 1089.15 | K111: 1031.86 | L111: 944.04 | M111: =IFERROR((H111-J111)/J111,0) | N111: =IFERROR((H111-K111)/K111,0) | O111: =IFERROR((H111-L111)/L111,0) | P111: 1050 | Q111: 2100 | R111: 2-5yr | S111: 4 | T111: 1300 | U111: =MAX(0,MIN(100,50+((M111*0.6)+(N111*0.4))*200)) | V111: =MAX(20,MIN(100,50+(P111-H111)/P111*100)) | W111: =IFERROR(MAX(0,MIN(100,100-LOG10(T111)*16)),60) | X111: =IF(C111="T2",85,IF(C111="T4",70,IF(C111="T1",65,IF(C111="T3",55,45)))) | Y111: =U111*0.55+W111*0.20+V111*0.15+X111*0.10+ROW()/1000000 | Z111: =IF(Y111>=75,"STRONG BUY",IF(Y111>=60,"BUY",IF(Y111>=40,"HOLD",IF(Y111>=25,"TRIM","SELL")))) | AA111: https://www.tcgplayer.com/product/610510 | AB111: Sun Eeveelution premium.
A112: M073 | B112: Modern Chase PSA 10 | C112: T2 | D112: Vaporeon ex SIR | E112: Prismatic Evolutions | F112: 159/131 | G112: PSA 10 | H112: 1080 | I112: 46153 | J112: 851.44 | K112: 794.61 | L112: 713.4 | M112: =IFERROR((H112-J112)/J112,0) | N112: =IFERROR((H112-K112)/K112,0) | O112: =IFERROR((H112-L112)/L112,0) | P112: 810 | Q112: 1620 | R112: 2-5yr | S112: 4 | T112: 1400 | U112: =MAX(0,MIN(100,50+((M112*0.6)+(N112*0.4))*200)) | V112: =MAX(20,MIN(100,50+(P112-H112)/P112*100)) | W112: =IFERROR(MAX(0,MIN(100,100-LOG10(T112)*16)),60) | X112: =IF(C112="T2",85,IF(C112="T4",70,IF(C112="T1",65,IF(C112="T3",55,45)))) | Y112: =U112*0.55+W112*0.20+V112*0.15+X112*0.10+ROW()/1000000 | Z112: =IF(Y112>=75,"STRONG BUY",IF(Y112>=60,"BUY",IF(Y112>=40,"HOLD",IF(Y112>=25,"TRIM","SELL")))) | AA112: https://www.tcgplayer.com/product/610514 | AB112: Water Eeveelution PE SIR.
A113: M074 | B113: Modern Chase PSA 10 | C113: T2 | D113: Glaceon ex SIR | E113: Prismatic Evolutions | F113: 158/131 | G113: PSA 10 | H113: 920 | I113: 46153 | J113: 698.11 | K113: 669.18 | L113: 624.39 | M113: =IFERROR((H113-J113)/J113,0) | N113: =IFERROR((H113-K113)/K113,0) | O113: =IFERROR((H113-L113)/L113,0) | P113: 690 | Q113: 1380 | R113: 2-5yr | S113: 4 | T113: 1500 | U113: =MAX(0,MIN(100,50+((M113*0.6)+(N113*0.4))*200)) | V113: =MAX(20,MIN(100,50+(P113-H113)/P113*100)) | W113: =IFERROR(MAX(0,MIN(100,100-LOG10(T113)*16)),60) | X113: =IF(C113="T2",85,IF(C113="T4",70,IF(C113="T1",65,IF(C113="T3",55,45)))) | Y113: =U113*0.55+W113*0.20+V113*0.15+X113*0.10+ROW()/1000000 | Z113: =IF(Y113>=75,"STRONG BUY",IF(Y113>=60,"BUY",IF(Y113>=40,"HOLD",IF(Y113>=25,"TRIM","SELL")))) | AA113: https://www.tcgplayer.com/product/610513 | AB113: Ice Eeveelution PE SIR.
A114: M075 | B114: Modern Chase PSA 10 | C114: T2 | D114: Leafeon ex SIR | E114: Prismatic Evolutions | F114: 144/131 | G114: PSA 10 | H114: 860 | I114: 46153 | J114: 677.91 | K114: 647.62 | L114: 614.68 | M114: =IFERROR((H114-J114)/J114,0) | N114: =IFERROR((H114-K114)/K114,0) | O114: =IFERROR((H114-L114)/L114,0) | P114: 650 | Q114: 1290 | R114: 2-5yr | S114: 3 | T114: 1600 | U114: =MAX(0,MIN(100,50+((M114*0.6)+(N114*0.4))*200)) | V114: =MAX(20,MIN(100,50+(P114-H114)/P114*100)) | W114: =IFERROR(MAX(0,MIN(100,100-LOG10(T114)*16)),60) | X114: =IF(C114="T2",85,IF(C114="T4",70,IF(C114="T1",65,IF(C114="T3",55,45)))) | Y114: =U114*0.55+W114*0.20+V114*0.15+X114*0.10+ROW()/1000000 | Z114: =IF(Y114>=75,"STRONG BUY",IF(Y114>=60,"BUY",IF(Y114>=40,"HOLD",IF(Y114>=25,"TRIM","SELL")))) | AA114: https://www.tcgplayer.com/product/610499 | AB114: Grass Eeveelution PE SIR. Cheapest entry to PE Eeveelution set.
A115: M076 | B115: Modern Chase PSA 10 | C115: T2 | D115: Marnie SIR | E115: Journey Together | F115: 180/159 | G115: PSA 10 | H115: 480 | I115: 46153 | J115: 370.04 | K115: 343.48 | L115: 304.63 | M115: =IFERROR((H115-J115)/J115,0) | N115: =IFERROR((H115-K115)/K115,0) | O115: =IFERROR((H115-L115)/L115,0) | P115: 360 | Q115: 720 | R115: 2-5yr | S115: 4 | T115: 1700 | U115: =MAX(0,MIN(100,50+((M115*0.6)+(N115*0.4))*200)) | V115: =MAX(20,MIN(100,50+(P115-H115)/P115*100)) | W115: =IFERROR(MAX(0,MIN(100,100-LOG10(T115)*16)),60) | X115: =IF(C115="T2",85,IF(C115="T4",70,IF(C115="T1",65,IF(C115="T3",55,45)))) | Y115: =U115*0.55+W115*0.20+V115*0.15+X115*0.10+ROW()/1000000 | Z115: =IF(Y115>=75,"STRONG BUY",IF(Y115>=60,"BUY",IF(Y115>=40,"HOLD",IF(Y115>=25,"TRIM","SELL")))) | AA115: https://www.tcgplayer.com/product/645321 | AB115: Marnie reprint chase from Journey Together. Up 10%/30D.
A116: M077 | B116: Modern Chase PSA 10 | C116: T2 | D116: N's Zoroark ex Alt | E116: Journey Together | F116: 175/159 | G116: PSA 10 | H116: 280 | I116: 46153 | J116: 214.7 | K116: 207.93 | L116: 187.23 | M116: =IFERROR((H116-J116)/J116,0) | N116: =IFERROR((H116-K116)/K116,0) | O116: =IFERROR((H116-L116)/L116,0) | P116: 210 | Q116: 420 | R116: 2-5yr | S116: 3 | T116: 1900 | U116: =MAX(0,MIN(100,50+((M116*0.6)+(N116*0.4))*200)) | V116: =MAX(20,MIN(100,50+(P116-H116)/P116*100)) | W116: =IFERROR(MAX(0,MIN(100,100-LOG10(T116)*16)),60) | X116: =IF(C116="T2",85,IF(C116="T4",70,IF(C116="T1",65,IF(C116="T3",55,45)))) | Y116: =U116*0.55+W116*0.20+V116*0.15+X116*0.10+ROW()/1000000 | Z116: =IF(Y116>=75,"STRONG BUY",IF(Y116>=60,"BUY",IF(Y116>=40,"HOLD",IF(Y116>=25,"TRIM","SELL")))) | AA116: https://www.tcgplayer.com/product/645316 | AB116: N + Zoroark = nostalgia + cult fav.
A117: M078 | B117: Modern Chase PSA 10 | C117: T2 | D117: Lillie's Determination SIR | E117: Mega Evolution (ME01) | F117: 184/132 | G117: PSA 10 | H117: 320 | I117: 46153 | J117: 189.27 | K117: 153.34 | L117: 112.18 | M117: =IFERROR((H117-J117)/J117,0) | N117: =IFERROR((H117-K117)/K117,0) | O117: =IFERROR((H117-L117)/L117,0) | P117: 240 | Q117: 480 | R117: 1-2yr | S117: 4 | T117: 1100 | U117: =MAX(0,MIN(100,50+((M117*0.6)+(N117*0.4))*200)) | V117: =MAX(20,MIN(100,50+(P117-H117)/P117*100)) | W117: =IFERROR(MAX(0,MIN(100,100-LOG10(T117)*16)),60) | X117: =IF(C117="T2",85,IF(C117="T4",70,IF(C117="T1",65,IF(C117="T3",55,45)))) | Y117: =U117*0.55+W117*0.20+V117*0.15+X117*0.10+ROW()/1000000 | Z117: =IF(Y117>=75,"STRONG BUY",IF(Y117>=60,"BUY",IF(Y117>=40,"HOLD",IF(Y117>=25,"TRIM","SELL")))) | AA117: https://www.tcgplayer.com/product/654523 | AB117: Trainer waifu pattern. Up 30%/30D - HOT mover.
A118: M079 | B118: Modern Chase PSA 10 | C118: T4 | D118: Lillie's Determination SIR | E118: Mega Evolution (ME01) | F118: 184/132 | G118: Raw NM | H118: 65 | I118: 46153 | J118: 61.68 | K118: 50.3 | L118: 36.59 | M118: =IFERROR((H118-J118)/J118,0) | N118: =IFERROR((H118-K118)/K118,0) | O118: =IFERROR((H118-L118)/L118,0) | P118: 50 | Q118: 100 | R118: 1-2yr | S118: 3 | U118: =MAX(0,MIN(100,50+((M118*0.6)+(N118*0.4))*200)) | V118: =MAX(20,MIN(100,50+(P118-H118)/P118*100)) | W118: =IFERROR(MAX(0,MIN(100,100-LOG10(T118)*16)),60) | X118: =IF(C118="T2",85,IF(C118="T4",70,IF(C118="T1",65,IF(C118="T3",55,45)))) | Y118: =U118*0.55+W118*0.20+V118*0.15+X118*0.10+ROW()/1000000 | Z118: =IF(Y118>=75,"STRONG BUY",IF(Y118>=60,"BUY",IF(Y118>=40,"HOLD",IF(Y118>=25,"TRIM","SELL")))) | AA118: https://www.tcgplayer.com/product/654523 | AB118: Cheapest raw flip play. Sub to PSA Bulk; 2x money.
A119: M080 | B119: Modern Chase PSA 10 | C119: T2 | D119: Mega Charizard X ex SIR | E119: Mega Evolution (ME01) | F119: 180/132 | G119: PSA 10 | H119: 1800 | I119: 46153 | J119: 1358.65 | K119: 1207.47 | L119: 957.35 | M119: =IFERROR((H119-J119)/J119,0) | N119: =IFERROR((H119-K119)/K119,0) | O119: =IFERROR((H119-L119)/L119,0) | P119: 1350 | Q119: 2700 | R119: 2-5yr | S119: 5 | T119: 900 | U119: =MAX(0,MIN(100,50+((M119*0.6)+(N119*0.4))*200)) | V119: =MAX(20,MIN(100,50+(P119-H119)/P119*100)) | W119: =IFERROR(MAX(0,MIN(100,100-LOG10(T119)*16)),60) | X119: =IF(C119="T2",85,IF(C119="T4",70,IF(C119="T1",65,IF(C119="T3",55,45)))) | Y119: =U119*0.55+W119*0.20+V119*0.15+X119*0.10+ROW()/1000000 | Z119: =IF(Y119>=75,"STRONG BUY",IF(Y119>=60,"BUY",IF(Y119>=40,"HOLD",IF(Y119>=25,"TRIM","SELL")))) | AA119: https://www.tcgplayer.com/product/654519 | AB119: Mega Charizard X reintro. Up 18%/30D. Top momentum.
A120: M081 | B120: Modern Chase PSA 10 | C120: T2 | D120: Mega Gengar ex SIR | E120: Ascended Heroes | F120: 284/217 | G120: PSA 10 | H120: 3000 | I120: 46153 | J120: 2131.38 | K120: 1778.54 | L120: 1411.24 | M120: =IFERROR((H120-J120)/J120,0) | N120: =IFERROR((H120-K120)/K120,0) | O120: =IFERROR((H120-L120)/L120,0) | P120: 2250 | Q120: 4500 | R120: 1-2yr | S120: 5 | T120: 400 | U120: =MAX(0,MIN(100,50+((M120*0.6)+(N120*0.4))*200)) | V120: =MAX(20,MIN(100,50+(P120-H120)/P120*100)) | W120: =IFERROR(MAX(0,MIN(100,100-LOG10(T120)*16)),60) | X120: =IF(C120="T2",85,IF(C120="T4",70,IF(C120="T1",65,IF(C120="T3",55,45)))) | Y120: =U120*0.55+W120*0.20+V120*0.15+X120*0.10+ROW()/1000000 | Z120: =IF(Y120>=75,"STRONG BUY",IF(Y120>=60,"BUY",IF(Y120>=40,"HOLD",IF(Y120>=25,"TRIM","SELL")))) | AA120: https://www.pricecharting.com/game/pokemon-ascended-heroes/mega-gengar-ex-284 | AB120: PSA 10 of the 2026 king card. Up 22%/30D. Pop building.
A121: M082 | B121: Modern Chase PSA 10 | C121: T4 | D121: Mega Gengar ex SIR | E121: Ascended Heroes | F121: 284/217 | G121: Raw NM | H121: 1480 | I121: 46153 | J121: 1122.41 | K121: 945.09 | L121: 749.72 | M121: =IFERROR((H121-J121)/J121,0) | N121: =IFERROR((H121-K121)/K121,0) | O121: =IFERROR((H121-L121)/L121,0) | P121: 1110 | Q121: 2220 | R121: 1-2yr | S121: 4 | U121: =MAX(0,MIN(100,50+((M121*0.6)+(N121*0.4))*200)) | V121: =MAX(20,MIN(100,50+(P121-H121)/P121*100)) | W121: =IFERROR(MAX(0,MIN(100,100-LOG10(T121)*16)),60) | X121: =IF(C121="T2",85,IF(C121="T4",70,IF(C121="T1",65,IF(C121="T3",55,45)))) | Y121: =U121*0.55+W121*0.20+V121*0.15+X121*0.10+ROW()/1000000 | Z121: =IF(Y121>=75,"STRONG BUY",IF(Y121>=60,"BUY",IF(Y121>=40,"HOLD",IF(Y121>=25,"TRIM","SELL")))) | AA121: https://www.tcgplayer.com/product/676096 | AB121: Raw Mega Gengar. Momentum trade - 30% trailing stop.
A122: M083 | B122: Modern Chase PSA 10 | C122: T2 | D122: Mega Gengar ex MAR | E122: Ascended Heroes | F122: 269/217 | G122: PSA 10 | H122: 480 | I122: 46153 | J122: 370.86 | K122: 331.59 | L122: 275.25 | M122: =IFERROR((H122-J122)/J122,0) | N122: =IFERROR((H122-K122)/K122,0) | O122: =IFERROR((H122-L122)/L122,0) | P122: 360 | Q122: 720 | R122: 1-2yr | S122: 4 | T122: 1200 | U122: =MAX(0,MIN(100,50+((M122*0.6)+(N122*0.4))*200)) | V122: =MAX(20,MIN(100,50+(P122-H122)/P122*100)) | W122: =IFERROR(MAX(0,MIN(100,100-LOG10(T122)*16)),60) | X122: =IF(C122="T2",85,IF(C122="T4",70,IF(C122="T1",65,IF(C122="T3",55,45)))) | Y122: =U122*0.55+W122*0.20+V122*0.15+X122*0.10+ROW()/1000000 | Z122: =IF(Y122>=75,"STRONG BUY",IF(Y122>=60,"BUY",IF(Y122>=40,"HOLD",IF(Y122>=25,"TRIM","SELL")))) | AA122: https://www.tcgplayer.com/product/676081 | AB122: Mega Attack Rare variant. Cheaper Mega Gengar exposure.
A123: M084 | B123: Modern Chase PSA 10 | C123: T2 | D123: Mega Rayquaza ex SIR | E123: Ascended Heroes | F123: 286/217 | G123: PSA 10 | H123: 1400 | I123: 46153 | J123: 1087.31 | K123: 951.53 | L123: 808.68 | M123: =IFERROR((H123-J123)/J123,0) | N123: =IFERROR((H123-K123)/K123,0) | O123: =IFERROR((H123-L123)/L123,0) | P123: 1050 | Q123: 2100 | R123: 2-5yr | S123: 5 | T123: 600 | U123: =MAX(0,MIN(100,50+((M123*0.6)+(N123*0.4))*200)) | V123: =MAX(20,MIN(100,50+(P123-H123)/P123*100)) | W123: =IFERROR(MAX(0,MIN(100,100-LOG10(T123)*16)),60) | X123: =IF(C123="T2",85,IF(C123="T4",70,IF(C123="T1",65,IF(C123="T3",55,45)))) | Y123: =U123*0.55+W123*0.20+V123*0.15+X123*0.10+ROW()/1000000 | Z123: =IF(Y123>=75,"STRONG BUY",IF(Y123>=60,"BUY",IF(Y123>=40,"HOLD",IF(Y123>=25,"TRIM","SELL")))) | AA123: https://www.tcgplayer.com/product/676098 | AB123: Mega Rayquaza in Ascended Heroes. Dragon collector pull.
A124: M085 | B124: Modern Chase PSA 10 | C124: T2 | D124: Mega Lucario ex SIR | E124: Ascended Heroes | F124: 285/217 | G124: PSA 10 | H124: 820 | I124: 46153 | J124: 627.23 | K124: 567.93 | L124: 484.12 | M124: =IFERROR((H124-J124)/J124,0) | N124: =IFERROR((H124-K124)/K124,0) | O124: =IFERROR((H124-L124)/L124,0) | P124: 620 | Q124: 1230 | R124: 2-5yr | S124: 4 | T124: 800 | U124: =MAX(0,MIN(100,50+((M124*0.6)+(N124*0.4))*200)) | V124: =MAX(20,MIN(100,50+(P124-H124)/P124*100)) | W124: =IFERROR(MAX(0,MIN(100,100-LOG10(T124)*16)),60) | X124: =IF(C124="T2",85,IF(C124="T4",70,IF(C124="T1",65,IF(C124="T3",55,45)))) | Y124: =U124*0.55+W124*0.20+V124*0.15+X124*0.10+ROW()/1000000 | Z124: =IF(Y124>=75,"STRONG BUY",IF(Y124>=60,"BUY",IF(Y124>=40,"HOLD",IF(Y124>=25,"TRIM","SELL")))) | AA124: https://www.tcgplayer.com/product/676097 | AB124: Lucario brand strength + Mega. Strong.
A125: M086 | B125: Modern Chase PSA 10 | C125: T2 | D125: Mega Lopunny ex SIR | E125: Ascended Heroes | F125: 283/217 | G125: PSA 10 | H125: 480 | I125: 46153 | J125: 376.01 | K125: 344.65 | L125: 295.73 | M125: =IFERROR((H125-J125)/J125,0) | N125: =IFERROR((H125-K125)/K125,0) | O125: =IFERROR((H125-L125)/L125,0) | P125: 360 | Q125: 720 | R125: 2-5yr | S125: 4 | T125: 1000 | U125: =MAX(0,MIN(100,50+((M125*0.6)+(N125*0.4))*200)) | V125: =MAX(20,MIN(100,50+(P125-H125)/P125*100)) | W125: =IFERROR(MAX(0,MIN(100,100-LOG10(T125)*16)),60) | X125: =IF(C125="T2",85,IF(C125="T4",70,IF(C125="T1",65,IF(C125="T3",55,45)))) | Y125: =U125*0.55+W125*0.20+V125*0.15+X125*0.10+ROW()/1000000 | Z125: =IF(Y125>=75,"STRONG BUY",IF(Y125>=60,"BUY",IF(Y125>=40,"HOLD",IF(Y125>=25,"TRIM","SELL")))) | AA125: https://www.tcgplayer.com/product/676095 | AB125: Sleeper Mega. Lopunny is uniquely popular in Japan.
A126: M087 | B126: Modern Chase PSA 10 | C126: T4 | D126: Mega Charizard Y ex SIR | E126: Ascended Heroes | F126: 288/217 | G126: Raw NM | H126: 280 | I126: 46153 | J126: 272.62 | K126: 231.82 | L126: 186.18 | M126: =IFERROR((H126-J126)/J126,0) | N126: =IFERROR((H126-K126)/K126,0) | O126: =IFERROR((H126-L126)/L126,0) | P126: 220 | Q126: 400 | R126: 1-2yr | S126: 4 | U126: =MAX(0,MIN(100,50+((M126*0.6)+(N126*0.4))*200)) | V126: =MAX(20,MIN(100,50+(P126-H126)/P126*100)) | W126: =IFERROR(MAX(0,MIN(100,100-LOG10(T126)*16)),60) | X126: =IF(C126="T2",85,IF(C126="T4",70,IF(C126="T1",65,IF(C126="T3",55,45)))) | Y126: =U126*0.55+W126*0.20+V126*0.15+X126*0.10+ROW()/1000000 | Z126: =IF(Y126>=75,"STRONG BUY",IF(Y126>=60,"BUY",IF(Y126>=40,"HOLD",IF(Y126>=25,"TRIM","SELL")))) | AA126: https://www.tcgplayer.com/product/676100 | AB126: Raw Mega Y Charizard. Submit for grade. +20%/30D momentum.
A127: M088 | B127: Modern Chase PSA 10 | C127: T2 | D127: Mega Charizard Y ex SIR | E127: Ascended Heroes | F127: 288/217 | G127: PSA 10 | H127: 1700 | I127: 46153 | J127: 1274.22 | K127: 1081.68 | L127: 883.2 | M127: =IFERROR((H127-J127)/J127,0) | N127: =IFERROR((H127-K127)/K127,0) | O127: =IFERROR((H127-L127)/L127,0) | P127: 1280 | Q127: 2550 | R127: 1-2yr | S127: 5 | T127: 700 | U127: =MAX(0,MIN(100,50+((M127*0.6)+(N127*0.4))*200)) | V127: =MAX(20,MIN(100,50+(P127-H127)/P127*100)) | W127: =IFERROR(MAX(0,MIN(100,100-LOG10(T127)*16)),60) | X127: =IF(C127="T2",85,IF(C127="T4",70,IF(C127="T1",65,IF(C127="T3",55,45)))) | Y127: =U127*0.55+W127*0.20+V127*0.15+X127*0.10+ROW()/1000000 | Z127: =IF(Y127>=75,"STRONG BUY",IF(Y127>=60,"BUY",IF(Y127>=40,"HOLD",IF(Y127>=25,"TRIM","SELL")))) | AA127: https://www.tcgplayer.com/product/676100 | AB127: Mega Y Charizard. Pairs with Mega X. Both surging.
A128: M089 | B128: Modern Chase PSA 10 | C128: T2 | D128: Van Gogh Pikachu | E128: Van Gogh Museum Promo | F128: 085 | G128: PSA 10 | H128: 2800 | I128: 46153 | J128: 2172.27 | K128: 2124.6 | L128: 1963.93 | M128: =IFERROR((H128-J128)/J128,0) | N128: =IFERROR((H128-K128)/K128,0) | O128: =IFERROR((H128-L128)/L128,0) | P128: 2100 | Q128: 4200 | R128: 2-5yr | S128: 4 | T128: 1400 | U128: =MAX(0,MIN(100,50+((M128*0.6)+(N128*0.4))*200)) | V128: =MAX(20,MIN(100,50+(P128-H128)/P128*100)) | W128: =IFERROR(MAX(0,MIN(100,100-LOG10(T128)*16)),60) | X128: =IF(C128="T2",85,IF(C128="T4",70,IF(C128="T1",65,IF(C128="T3",55,45)))) | Y128: =U128*0.55+W128*0.20+V128*0.15+X128*0.10+ROW()/1000000 | Z128: =IF(Y128>=75,"STRONG BUY",IF(Y128>=60,"BUY",IF(Y128>=40,"HOLD",IF(Y128>=25,"TRIM","SELL")))) | AA128: https://www.pricecharting.com/game/pokemon-promo/van-gogh-pikachu-085 | AB128: Cultural crossover. Authenticate carefully - many fakes.
A129: M090 | B129: Modern Chase PSA 10 | C129: T4 | D129: Van Gogh Pikachu | E129: Van Gogh Museum Promo | F129: 085 | G129: Raw NM | H129: 600 | I129: 46153 | J129: 600.61 | K129: 591.52 | L129: 589.69 | M129: =IFERROR((H129-J129)/J129,0) | N129: =IFERROR((H129-K129)/K129,0) | O129: =IFERROR((H129-L129)/L129,0) | P129: 450 | Q129: 850 | R129: 2-5yr | S129: 4 | U129: =MAX(0,MIN(100,50+((M129*0.6)+(N129*0.4))*200)) | V129: =MAX(20,MIN(100,50+(P129-H129)/P129*100)) | W129: =IFERROR(MAX(0,MIN(100,100-LOG10(T129)*16)),60) | X129: =IF(C129="T2",85,IF(C129="T4",70,IF(C129="T1",65,IF(C129="T3",55,45)))) | Y129: =U129*0.55+W129*0.20+V129*0.15+X129*0.10+ROW()/1000000 | Z129: =IF(Y129>=75,"STRONG BUY",IF(Y129>=60,"BUY",IF(Y129>=40,"HOLD",IF(Y129>=25,"TRIM","SELL")))) | AA129: https://www.pricecharting.com/game/pokemon-promo/van-gogh-pikachu-085 | AB129: Raw with provenance. Grade and flip.
A130: M091 | B130: Modern Chase PSA 10 | C130: T2 | D130: Pokemon Day 2026 Pikachu Promo | E130: 30th Anniversary Promo | F130: 001/030 | G130: PSA 10 | H130: 240 | I130: 46153 | J130: 175.76 | K130: 164.17 | L130: 142.72 | M130: =IFERROR((H130-J130)/J130,0) | N130: =IFERROR((H130-K130)/K130,0) | O130: =IFERROR((H130-L130)/L130,0) | P130: 180 | Q130: 360 | R130: 1-3yr | S130: 3 | T130: 1100 | U130: =MAX(0,MIN(100,50+((M130*0.6)+(N130*0.4))*200)) | V130: =MAX(20,MIN(100,50+(P130-H130)/P130*100)) | W130: =IFERROR(MAX(0,MIN(100,100-LOG10(T130)*16)),60) | X130: =IF(C130="T2",85,IF(C130="T4",70,IF(C130="T1",65,IF(C130="T3",55,45)))) | Y130: =U130*0.55+W130*0.20+V130*0.15+X130*0.10+ROW()/1000000 | Z130: =IF(Y130>=75,"STRONG BUY",IF(Y130>=60,"BUY",IF(Y130>=40,"HOLD",IF(Y130>=25,"TRIM","SELL")))) | AA130: https://www.pricecharting.com/game/pokemon-promo/pokemon-day-2026-pikachu | AB130: 30th anniversary stamped Pikachu. Sleeper.
A131: M092 | B131: Modern Chase PSA 10 | C131: T2 | D131: Birthday Pikachu Promo | E131: Black Star Promo #24 | F131: 24 | G131: PSA 10 | H131: 1100 | I131: 46153 | J131: 856.65 | K131: 807.48 | L131: 759.3 | M131: =IFERROR((H131-J131)/J131,0) | N131: =IFERROR((H131-K131)/K131,0) | O131: =IFERROR((H131-L131)/L131,0) | P131: 830 | Q131: 1650 | R131: 5-10yr | S131: 4 | T131: 350 | U131: =MAX(0,MIN(100,50+((M131*0.6)+(N131*0.4))*200)) | V131: =MAX(20,MIN(100,50+(P131-H131)/P131*100)) | W131: =IFERROR(MAX(0,MIN(100,100-LOG10(T131)*16)),60) | X131: =IF(C131="T2",85,IF(C131="T4",70,IF(C131="T1",65,IF(C131="T3",55,45)))) | Y131: =U131*0.55+W131*0.20+V131*0.15+X131*0.10+ROW()/1000000 | Z131: =IF(Y131>=75,"STRONG BUY",IF(Y131>=60,"BUY",IF(Y131>=40,"HOLD",IF(Y131>=25,"TRIM","SELL")))) | AA131: https://www.pricecharting.com/game/pokemon-promo/birthday-pikachu-24 | AB131: Classic 1999 Black Star promo. Birthday card meme.
A132: M093 | B132: Modern Chase PSA 10 | C132: T2 | D132: Tropical Wind Trainer | E132: WCS 2010 | F132: Promo | G132: PSA 10 | H132: 3200 | I132: 46153 | J132: 3152.4 | K132: 2991.92 | L132: 2743.7 | M132: =IFERROR((H132-J132)/J132,0) | N132: =IFERROR((H132-K132)/K132,0) | O132: =IFERROR((H132-L132)/L132,0) | P132: 2500 | Q132: 4700 | R132: 5-10yr | S132: 4 | T132: 180 | U132: =MAX(0,MIN(100,50+((M132*0.6)+(N132*0.4))*200)) | V132: =MAX(20,MIN(100,50+(P132-H132)/P132*100)) | W132: =IFERROR(MAX(0,MIN(100,100-LOG10(T132)*16)),60) | X132: =IF(C132="T2",85,IF(C132="T4",70,IF(C132="T1",65,IF(C132="T3",55,45)))) | Y132: =U132*0.55+W132*0.20+V132*0.15+X132*0.10+ROW()/1000000 | Z132: =IF(Y132>=75,"STRONG BUY",IF(Y132>=60,"BUY",IF(Y132>=40,"HOLD",IF(Y132>=25,"TRIM","SELL")))) | AA132: https://www.pricecharting.com/game/pokemon-promo/tropical-wind-2010 | AB132: WCS Trainer promo. Tiny pop in PSA 10.
A133: S001 | B133: Sealed Modern | C133: T3 | D133: Evolving Skies Booster Box | E133: Evolving Skies | F133: Box | G133: Sealed (36 packs) | H133: 290 | I133: 46153 | J133: 282.85 | K133: 273.99 | L133: 260.59 | M133: =IFERROR((H133-J133)/J133,0) | N133: =IFERROR((H133-K133)/K133,0) | O133: =IFERROR((H133-L133)/L133,0) | P133: 250 | Q133: 360 | R133: 5-10yr | S133: 5 | U133: =MAX(0,MIN(100,50+((M133*0.6)+(N133*0.4))*200)) | V133: =MAX(20,MIN(100,50+(P133-H133)/P133*100)) | W133: =IFERROR(MAX(0,MIN(100,100-LOG10(T133)*16)),60) | X133: =IF(C133="T2",85,IF(C133="T4",70,IF(C133="T1",65,IF(C133="T3",55,45)))) | Y133: =U133*0.55+W133*0.20+V133*0.15+X133*0.10+ROW()/1000000 | Z133: =IF(Y133>=75,"STRONG BUY",IF(Y133>=60,"BUY",IF(Y133>=40,"HOLD",IF(Y133>=25,"TRIM","SELL")))) | AA133: https://www.pricecharting.com/game/pokemon-evolving-skies/booster-box | AB133: OOP. $143 MSRP -> $290. Verify weight 545g ±5g.
A134: S002 | B134: Sealed Modern | C134: T3 | D134: Evolving Skies ETB | E134: Evolving Skies | F134: ETB | G134: Sealed | H134: 120 | I134: 46153 | J134: 118.29 | K134: 112.82 | L134: 98.44 | M134: =IFERROR((H134-J134)/J134,0) | N134: =IFERROR((H134-K134)/K134,0) | O134: =IFERROR((H134-L134)/L134,0) | P134: 95 | Q134: 170 | R134: 5-10yr | S134: 4 | U134: =MAX(0,MIN(100,50+((M134*0.6)+(N134*0.4))*200)) | V134: =MAX(20,MIN(100,50+(P134-H134)/P134*100)) | W134: =IFERROR(MAX(0,MIN(100,100-LOG10(T134)*16)),60) | X134: =IF(C134="T2",85,IF(C134="T4",70,IF(C134="T1",65,IF(C134="T3",55,45)))) | Y134: =U134*0.55+W134*0.20+V134*0.15+X134*0.10+ROW()/1000000 | Z134: =IF(Y134>=75,"STRONG BUY",IF(Y134>=60,"BUY",IF(Y134>=40,"HOLD",IF(Y134>=25,"TRIM","SELL")))) | AA134: https://www.pricecharting.com/game/pokemon-evolving-skies/elite-trainer-box | AB134: OOP ETB. Lower-ticket entry to ES sealed.
A135: S003 | B135: Sealed Modern | C135: T3 | D135: Evolving Skies Booster Bundle | E135: Evolving Skies | F135: Bundle | G135: Sealed (6 packs) | H135: 95 | I135: 46153 | J135: 94.29 | K135: 88.89 | L135: 84.01 | M135: =IFERROR((H135-J135)/J135,0) | N135: =IFERROR((H135-K135)/K135,0) | O135: =IFERROR((H135-L135)/L135,0) | P135: 75 | Q135: 140 | R135: 5-10yr | S135: 4 | U135: =MAX(0,MIN(100,50+((M135*0.6)+(N135*0.4))*200)) | V135: =MAX(20,MIN(100,50+(P135-H135)/P135*100)) | W135: =IFERROR(MAX(0,MIN(100,100-LOG10(T135)*16)),60) | X135: =IF(C135="T2",85,IF(C135="T4",70,IF(C135="T1",65,IF(C135="T3",55,45)))) | Y135: =U135*0.55+W135*0.20+V135*0.15+X135*0.10+ROW()/1000000 | Z135: =IF(Y135>=75,"STRONG BUY",IF(Y135>=60,"BUY",IF(Y135>=40,"HOLD",IF(Y135>=25,"TRIM","SELL")))) | AA135: https://www.pricecharting.com/game/pokemon-evolving-skies/booster-bundle | AB135: OOP. Smaller ticket = quick flip.
A136: S004 | B136: Sealed Modern | C136: T3 | D136: Crown Zenith ETB | E136: Crown Zenith | F136: ETB | G136: Sealed | H136: 75 | I136: 46153 | J136: 73.87 | K136: 72.59 | L136: 67.15 | M136: =IFERROR((H136-J136)/J136,0) | N136: =IFERROR((H136-K136)/K136,0) | O136: =IFERROR((H136-L136)/L136,0) | P136: 60 | Q136: 100 | R136: 3-5yr | S136: 4 | U136: =MAX(0,MIN(100,50+((M136*0.6)+(N136*0.4))*200)) | V136: =MAX(20,MIN(100,50+(P136-H136)/P136*100)) | W136: =IFERROR(MAX(0,MIN(100,100-LOG10(T136)*16)),60) | X136: =IF(C136="T2",85,IF(C136="T4",70,IF(C136="T1",65,IF(C136="T3",55,45)))) | Y136: =U136*0.55+W136*0.20+V136*0.15+X136*0.10+ROW()/1000000 | Z136: =IF(Y136>=75,"STRONG BUY",IF(Y136>=60,"BUY",IF(Y136>=40,"HOLD",IF(Y136>=25,"TRIM","SELL")))) | AA136: https://www.pricecharting.com/game/pokemon-crown-zenith/elite-trainer-box | AB136: Stable. Galarian Gallery sub-set drives long-term.
A137: S005 | B137: Sealed Modern | C137: T3 | D137: Crown Zenith Premium Playmat Collection | E137: Crown Zenith | F137: PPC | G137: Sealed | H137: 140 | I137: 46153 | J137: 136.9 | K137: 133.11 | L137: 123.09 | M137: =IFERROR((H137-J137)/J137,0) | N137: =IFERROR((H137-K137)/K137,0) | O137: =IFERROR((H137-L137)/L137,0) | P137: 110 | Q137: 200 | R137: 3-5yr | S137: 4 | U137: =MAX(0,MIN(100,50+((M137*0.6)+(N137*0.4))*200)) | V137: =MAX(20,MIN(100,50+(P137-H137)/P137*100)) | W137: =IFERROR(MAX(0,MIN(100,100-LOG10(T137)*16)),60) | X137: =IF(C137="T2",85,IF(C137="T4",70,IF(C137="T1",65,IF(C137="T3",55,45)))) | Y137: =U137*0.55+W137*0.20+V137*0.15+X137*0.10+ROW()/1000000 | Z137: =IF(Y137>=75,"STRONG BUY",IF(Y137>=60,"BUY",IF(Y137>=40,"HOLD",IF(Y137>=25,"TRIM","SELL")))) | AA137: https://www.pricecharting.com/game/pokemon-crown-zenith/premium-playmat | AB137: Limited PPC product. Better EV than ETB.
A138: S006 | B138: Sealed Modern | C138: T3 | D138: Brilliant Stars BB | E138: Brilliant Stars | F138: Box | G138: Sealed (36 packs) | H138: 220 | I138: 46153 | J138: 215.86 | K138: 208.13 | L138: 187.57 | M138: =IFERROR((H138-J138)/J138,0) | N138: =IFERROR((H138-K138)/K138,0) | O138: =IFERROR((H138-L138)/L138,0) | P138: 175 | Q138: 320 | R138: 3-5yr | S138: 4 | U138: =MAX(0,MIN(100,50+((M138*0.6)+(N138*0.4))*200)) | V138: =MAX(20,MIN(100,50+(P138-H138)/P138*100)) | W138: =IFERROR(MAX(0,MIN(100,100-LOG10(T138)*16)),60) | X138: =IF(C138="T2",85,IF(C138="T4",70,IF(C138="T1",65,IF(C138="T3",55,45)))) | Y138: =U138*0.55+W138*0.20+V138*0.15+X138*0.10+ROW()/1000000 | Z138: =IF(Y138>=75,"STRONG BUY",IF(Y138>=60,"BUY",IF(Y138>=40,"HOLD",IF(Y138>=25,"TRIM","SELL")))) | AA138: https://www.pricecharting.com/game/pokemon-brilliant-stars/booster-box | AB138: OOP. Charizard VSTAR + Trainer Gallery debut.
A139: S007 | B139: Sealed Modern | C139: T3 | D139: Astral Radiance BB | E139: Astral Radiance | F139: Box | G139: Sealed (36 packs) | H139: 180 | I139: 46153 | J139: 177.04 | K139: 168.27 | L139: 160.65 | M139: =IFERROR((H139-J139)/J139,0) | N139: =IFERROR((H139-K139)/K139,0) | O139: =IFERROR((H139-L139)/L139,0) | P139: 140 | Q139: 260 | R139: 3-5yr | S139: 3 | U139: =MAX(0,MIN(100,50+((M139*0.6)+(N139*0.4))*200)) | V139: =MAX(20,MIN(100,50+(P139-H139)/P139*100)) | W139: =IFERROR(MAX(0,MIN(100,100-LOG10(T139)*16)),60) | X139: =IF(C139="T2",85,IF(C139="T4",70,IF(C139="T1",65,IF(C139="T3",55,45)))) | Y139: =U139*0.55+W139*0.20+V139*0.15+X139*0.10+ROW()/1000000 | Z139: =IF(Y139>=75,"STRONG BUY",IF(Y139>=60,"BUY",IF(Y139>=40,"HOLD",IF(Y139>=25,"TRIM","SELL")))) | AA139: https://www.pricecharting.com/game/pokemon-astral-radiance/booster-box | AB139: OOP. Origin Forme chase cards.
A140: S008 | B140: Sealed Modern | C140: T3 | D140: Lost Origin BB | E140: Lost Origin | F140: Box | G140: Sealed (36 packs) | H140: 200 | I140: 46153 | J140: 197.94 | K140: 187.97 | L140: 172.33 | M140: =IFERROR((H140-J140)/J140,0) | N140: =IFERROR((H140-K140)/K140,0) | O140: =IFERROR((H140-L140)/L140,0) | P140: 160 | Q140: 290 | R140: 3-5yr | S140: 4 | U140: =MAX(0,MIN(100,50+((M140*0.6)+(N140*0.4))*200)) | V140: =MAX(20,MIN(100,50+(P140-H140)/P140*100)) | W140: =IFERROR(MAX(0,MIN(100,100-LOG10(T140)*16)),60) | X140: =IF(C140="T2",85,IF(C140="T4",70,IF(C140="T1",65,IF(C140="T3",55,45)))) | Y140: =U140*0.55+W140*0.20+V140*0.15+X140*0.10+ROW()/1000000 | Z140: =IF(Y140>=75,"STRONG BUY",IF(Y140>=60,"BUY",IF(Y140>=40,"HOLD",IF(Y140>=25,"TRIM","SELL")))) | AA140: https://www.pricecharting.com/game/pokemon-lost-origin/booster-box | AB140: OOP. Giratina alt art chase.
A141: S009 | B141: Sealed Modern | C141: T3 | D141: Silver Tempest BB | E141: Silver Tempest | F141: Box | G141: Sealed (36 packs) | H141: 190 | I141: 46153 | J141: 184.82 | K141: 178.47 | L141: 163.75 | M141: =IFERROR((H141-J141)/J141,0) | N141: =IFERROR((H141-K141)/K141,0) | O141: =IFERROR((H141-L141)/L141,0) | P141: 150 | Q141: 280 | R141: 3-5yr | S141: 4 | U141: =MAX(0,MIN(100,50+((M141*0.6)+(N141*0.4))*200)) | V141: =MAX(20,MIN(100,50+(P141-H141)/P141*100)) | W141: =IFERROR(MAX(0,MIN(100,100-LOG10(T141)*16)),60) | X141: =IF(C141="T2",85,IF(C141="T4",70,IF(C141="T1",65,IF(C141="T3",55,45)))) | Y141: =U141*0.55+W141*0.20+V141*0.15+X141*0.10+ROW()/1000000 | Z141: =IF(Y141>=75,"STRONG BUY",IF(Y141>=60,"BUY",IF(Y141>=40,"HOLD",IF(Y141>=25,"TRIM","SELL")))) | AA141: https://www.pricecharting.com/game/pokemon-silver-tempest/booster-box | AB141: OOP. Lugia VSTAR alt chase.
A142: S010 | B142: Sealed Modern | C142: T3 | D142: SV 151 Booster Bundle | E142: Scarlet & Violet 151 | F142: Bundle | G142: Sealed (6 packs) | H142: 175 | I142: 46153 | J142: 171.3 | K142: 160.18 | L142: 144.23 | M142: =IFERROR((H142-J142)/J142,0) | N142: =IFERROR((H142-K142)/K142,0) | O142: =IFERROR((H142-L142)/L142,0) | P142: 140 | Q142: 260 | R142: 3-5yr | S142: 4 | U142: =MAX(0,MIN(100,50+((M142*0.6)+(N142*0.4))*200)) | V142: =MAX(20,MIN(100,50+(P142-H142)/P142*100)) | W142: =IFERROR(MAX(0,MIN(100,100-LOG10(T142)*16)),60) | X142: =IF(C142="T2",85,IF(C142="T4",70,IF(C142="T1",65,IF(C142="T3",55,45)))) | Y142: =U142*0.55+W142*0.20+V142*0.15+X142*0.10+ROW()/1000000 | Z142: =IF(Y142>=75,"STRONG BUY",IF(Y142>=60,"BUY",IF(Y142>=40,"HOLD",IF(Y142>=25,"TRIM","SELL")))) | AA142: https://www.tcgplayer.com/product/502000 | AB142: $27 MSRP -> $175. Gen 1 nostalgia engine.
A143: S011 | B143: Sealed Modern | C143: T3 | D143: SV 151 ETB | E143: Scarlet & Violet 151 | F143: ETB | G143: Sealed | H143: 220 | I143: 46153 | J143: 218.92 | K143: 196.55 | L143: 174.71 | M143: =IFERROR((H143-J143)/J143,0) | N143: =IFERROR((H143-K143)/K143,0) | O143: =IFERROR((H143-L143)/L143,0) | P143: 170 | Q143: 330 | R143: 3-5yr | S143: 4 | U143: =MAX(0,MIN(100,50+((M143*0.6)+(N143*0.4))*200)) | V143: =MAX(20,MIN(100,50+(P143-H143)/P143*100)) | W143: =IFERROR(MAX(0,MIN(100,100-LOG10(T143)*16)),60) | X143: =IF(C143="T2",85,IF(C143="T4",70,IF(C143="T1",65,IF(C143="T3",55,45)))) | Y143: =U143*0.55+W143*0.20+V143*0.15+X143*0.10+ROW()/1000000 | Z143: =IF(Y143>=75,"STRONG BUY",IF(Y143>=60,"BUY",IF(Y143>=40,"HOLD",IF(Y143>=25,"TRIM","SELL")))) | AA143: https://www.pricecharting.com/game/pokemon-scarlet-&-violet-151/elite-trainer-box | AB143: 151 ETB - hardest to find at retail.
A144: S012 | B144: Sealed Modern | C144: T3 | D144: SV 151 Ultra-Premium Collection | E144: Scarlet & Violet 151 | F144: UPC | G144: Sealed | H144: 320 | I144: 46153 | J144: 307.56 | K144: 280.93 | L144: 241.63 | M144: =IFERROR((H144-J144)/J144,0) | N144: =IFERROR((H144-K144)/K144,0) | O144: =IFERROR((H144-L144)/L144,0) | P144: 250 | Q144: 480 | R144: 3-5yr | S144: 5 | U144: =MAX(0,MIN(100,50+((M144*0.6)+(N144*0.4))*200)) | V144: =MAX(20,MIN(100,50+(P144-H144)/P144*100)) | W144: =IFERROR(MAX(0,MIN(100,100-LOG10(T144)*16)),60) | X144: =IF(C144="T2",85,IF(C144="T4",70,IF(C144="T1",65,IF(C144="T3",55,45)))) | Y144: =U144*0.55+W144*0.20+V144*0.15+X144*0.10+ROW()/1000000 | Z144: =IF(Y144>=75,"STRONG BUY",IF(Y144>=60,"BUY",IF(Y144>=40,"HOLD",IF(Y144>=25,"TRIM","SELL")))) | AA144: https://www.pricecharting.com/game/pokemon-scarlet-&-violet-151/ultra-premium-collection | AB144: UPC = premium 151 sealed. Up 12%/30D.
... A165: X001 | B165: Modern Chase PSA 10 | C165: T5 | D165: Iono SIR | E165: Paldea Evolved | F165: 269/193 | G165: Raw NM | H165: 80 | I165: 46153 | J165: 78.18 | K165: 73.06 | L165: 67.67 | M165: =IFERROR((H165-J165)/J165,0) | N165: =IFERROR((H165-K165)/K165,0) | O165: =IFERROR((H165-L165)/L165,0) | P165: 60 | Q165: 130 | R165: 1-3yr | S165: 3 | U165: =MAX(0,MIN(100,50+((M165*0.6)+(N165*0.4))*200)) | V165: =MAX(20,MIN(100,50+(P165-H165)/P165*100)) | W165: =IFERROR(MAX(0,MIN(100,100-LOG10(T165)*16)),60) | X165: =IF(C165="T2",85,IF(C165="T4",70,IF(C165="T1",65,IF(C165="T3",55,45)))) | Y165: =U165*0.55+W165*0.20+V165*0.15+X165*0.10+ROW()/1000000 | Z165: =IF(Y165>=75,"STRONG BUY",IF(Y165>=60,"BUY",IF(Y165>=40,"HOLD",IF(Y165>=25,"TRIM","SELL")))) | AA165: https://www.pricecharting.com/game/pokemon-paldea-evolved/iono-237 | AB165: Raw Iono. Grade and flip.
A166: X002 | B166: Modern Chase PSA 10 | C166: T5 | D166: Pikachu V-Union Promo | E166: SWSH Promos | F166: SWSH212-215 | G166: PSA 10 set | H166: 220 | I166: 46153 | J166: 221.55 | K166: 208.42 | L166: 193.43 | M166: =IFERROR((H166-J166)/J166,0) | N166: =IFERROR((H166-K166)/K166,0) | O166: =IFERROR((H166-L166)/L166,0) | P166: 170 | Q166: 320 | R166: 2-5yr | S166: 3 | T166: 900 | U166: =MAX(0,MIN(100,50+((M166*0.6)+(N166*0.4))*200)) | V166: =MAX(20,MIN(100,50+(P166-H166)/P166*100)) | W166: =IFERROR(MAX(0,MIN(100,100-LOG10(T166)*16)),60) | X166: =IF(C166="T2",85,IF(C166="T4",70,IF(C166="T1",65,IF(C166="T3",55,45)))) | Y166: =U166*0.55+W166*0.20+V166*0.15+X166*0.10+ROW()/1000000 | Z166: =IF(Y166>=75,"STRONG BUY",IF(Y166>=60,"BUY",IF(Y166>=40,"HOLD",IF(Y166>=25,"TRIM","SELL")))) | AA166: https://www.pricecharting.com/game/pokemon-promo/pikachu-v-union | AB166: V-Union set = 4 cards. Whole-set play.
A167: X003 | B167: Modern Chase PSA 10 | C167: T5 | D167: Marnie Full Art | E167: Sword & Shield | F167: 200/202 | G167: PSA 10 | H167: 240 | I167: 46153 | J167: 233.23 | K167: 226.42 | L167: 209.33 | M167: =IFERROR((H167-J167)/J167,0) | N167: =IFERROR((H167-K167)/K167,0) | O167: =IFERROR((H167-L167)/L167,0) | P167: 180 | Q167: 350 | R167: 3-5yr | S167: 4 | T167: 1400 | U167: =MAX(0,MIN(100,50+((M167*0.6)+(N167*0.4))*200)) | V167: =MAX(20,MIN(100,50+(P167-H167)/P167*100)) | W167: =IFERROR(MAX(0,MIN(100,100-LOG10(T167)*16)),60) | X167: =IF(C167="T2",85,IF(C167="T4",70,IF(C167="T1",65,IF(C167="T3",55,45)))) | Y167: =U167*0.55+W167*0.20+V167*0.15+X167*0.10+ROW()/1000000 | Z167: =IF(Y167>=75,"STRONG BUY",IF(Y167>=60,"BUY",IF(Y167>=40,"HOLD",IF(Y167>=25,"TRIM","SELL")))) | AA167: https://www.pricecharting.com/game/pokemon-sword-and-shield/marnie-full-art-200 | AB167: OG Marnie - the prototype trainer waifu card.
A168: X004 | B168: Modern Chase PSA 10 | C168: T5 | D168: Cynthia Full Art | E168: Ultra Prism | F168: 148/156 | G168: PSA 10 | H168: 380 | I168: 46153 | J168: 381.02 | K168: 368.97 | L168: 340.4 | M168: =IFERROR((H168-J168)/J168,0) | N168: =IFERROR((H168-K168)/K168,0) | O168: =IFERROR((H168-L168)/L168,0) | P168: 290 | Q168: 560 | R168: 5-10yr | S168: 4 | T168: 800 | U168: =MAX(0,MIN(100,50+((M168*0.6)+(N168*0.4))*200)) | V168: =MAX(20,MIN(100,50+(P168-H168)/P168*100)) | W168: =IFERROR(MAX(0,MIN(100,100-LOG10(T168)*16)),60) | X168: =IF(C168="T2",85,IF(C168="T4",70,IF(C168="T1",65,IF(C168="T3",55,45)))) | Y168: =U168*0.55+W168*0.20+V168*0.15+X168*0.10+ROW()/1000000 | Z168: =IF(Y168>=75,"STRONG BUY",IF(Y168>=60,"BUY",IF(Y168>=40,"HOLD",IF(Y168>=25,"TRIM","SELL")))) | AA168: https://www.pricecharting.com/game/pokemon-ultra-prism/cynthia-full-art-148 | AB168: Sinnoh champion. Older sun-set demand.
A169: X005 | B169: Modern Chase PSA 10 | C169: T5 | D169: Erika's Invitation SIR | E169: 151 | F169: 203/165 | G169: PSA 10 | H169: 280 | I169: 46153 | J169: 276.81 | K169: 262.12 | L169: 233.6 | M169: =IFERROR((H169-J169)/J169,0) | N169: =IFERROR((H169-K169)/K169,0) | O169: =IFERROR((H169-L169)/L169,0) | P169: 220 | Q169: 410 | R169: 3-5yr | S169: 4 | T169: 1500 | U169: =MAX(0,MIN(100,50+((M169*0.6)+(N169*0.4))*200)) | V169: =MAX(20,MIN(100,50+(P169-H169)/P169*100)) | W169: =IFERROR(MAX(0,MIN(100,100-LOG10(T169)*16)),60) | X169: =IF(C169="T2",85,IF(C169="T4",70,IF(C169="T1",65,IF(C169="T3",55,45)))) | Y169: =U169*0.55+W169*0.20+V169*0.15+X169*0.10+ROW()/1000000 | Z169: =IF(Y169>=75,"STRONG BUY",IF(Y169>=60,"BUY",IF(Y169>=40,"HOLD",IF(Y169>=25,"TRIM","SELL")))) | AA169: https://www.tcgplayer.com/product/498104 | AB169: Gym leader SIR. Pairs with Charizard ex SIR.
A170: X006 | B170: Modern Chase PSA 10 | C170: T5 | D170: Misty's Determination SIR | E170: Mega Evolution ME01 | F170: Trainer SIR | G170: PSA 10 | H170: 140 | I170: 46153 | J170: 135.3 | K170: 125.56 | L170: 105.55 | M170: =IFERROR((H170-J170)/J170,0) | N170: =IFERROR((H170-K170)/K170,0) | O170: =IFERROR((H170-L170)/L170,0) | P170: 110 | Q170: 210 | R170: 1-2yr | S170: 3 | T170: 1300 | U170: =MAX(0,MIN(100,50+((M170*0.6)+(N170*0.4))*200)) | V170: =MAX(20,MIN(100,50+(P170-H170)/P170*100)) | W170: =IFERROR(MAX(0,MIN(100,100-LOG10(T170)*16)),60) | X170: =IF(C170="T2",85,IF(C170="T4",70,IF(C170="T1",65,IF(C170="T3",55,45)))) | Y170: =U170*0.55+W170*0.20+V170*0.15+X170*0.10+ROW()/1000000 | Z170: =IF(Y170>=75,"STRONG BUY",IF(Y170>=60,"BUY",IF(Y170>=40,"HOLD",IF(Y170>=25,"TRIM","SELL")))) | AA170: https://www.tcgplayer.com/product/654525 | AB170: Misty version of Lillie SIR. Up 12%/30D.
A171: X007 | B171: Modern Chase PSA 10 | C171: T5 | D171: Mewtwo Wave Holo Promo | E171: Black Star Promo | F171: 14 | G171: PSA 10 | H171: 320 | I171: 46153 | J171: 321.93 | K171: 308.66 | L171: 286.72 | M171: =IFERROR((H171-J171)/J171,0) | N171: =IFERROR((H171-K171)/K171,0) | O171: =IFERROR((H171-L171)/L171,0) | P171: 250 | Q171: 470 | R171: 5-10yr | S171: 4 | T171: 600 | U171: =MAX(0,MIN(100,50+((M171*0.6)+(N171*0.4))*200)) | V171: =MAX(20,MIN(100,50+(P171-H171)/P171*100)) | W171: =IFERROR(MAX(0,MIN(100,100-LOG10(T171)*16)),60) | X171: =IF(C171="T2",85,IF(C171="T4",70,IF(C171="T1",65,IF(C171="T3",55,45)))) | Y171: =U171*0.55+W171*0.20+V171*0.15+X171*0.10+ROW()/1000000 | Z171: =IF(Y171>=75,"STRONG BUY",IF(Y171>=60,"BUY",IF(Y171>=40,"HOLD",IF(Y171>=25,"TRIM","SELL")))) | AA171: https://www.pricecharting.com/game/pokemon-promo/mewtwo-wave-holo | AB171: Classic 1999 Mewtwo movie promo wave variant.
A172: X008 | B172: Modern Chase PSA 10 | C172: T5 | D172: Ancient Mew | E172: Movie Promo | F172: Promo | G172: PSA 10 | H172: 180 | I172: 46153 | J172: 179.48 | K172: 173.55 | L172: 165.24 | M172: =IFERROR((H172-J172)/J172,0) | N172: =IFERROR((H172-K172)/K172,0) | O172: =IFERROR((H172-L172)/L172,0) | P172: 140 | Q172: 270 | R172: 2-5yr | S172: 3 | T172: 2200 | U172: =MAX(0,MIN(100,50+((M172*0.6)+(N172*0.4))*200)) | V172: =MAX(20,MIN(100,50+(P172-H172)/P172*100)) | W172: =IFERROR(MAX(0,MIN(100,100-LOG10(T172)*16)),60) | X172: =IF(C172="T2",85,IF(C172="T4",70,IF(C172="T1",65,IF(C172="T3",55,45)))) | Y172: =U172*0.55+W172*0.20+V172*0.15+X172*0.10+ROW()/1000000 | Z172: =IF(Y172>=75,"STRONG BUY",IF(Y172>=60,"BUY",IF(Y172>=40,"HOLD",IF(Y172>=25,"TRIM","SELL")))) | AA172: https://www.pricecharting.com/game/pokemon-promo/ancient-mew | AB172: Ancient Mew - cultural classic, high pop but always demand.
...

Sheet Inventory
A1: INVENTORY — Active Positions
A2: Enter CardID Lookup (e.g., M001) - Category/Description/Current Price auto-populate from Watchlist.
A4: Item ID | B4: CardID Lookup | C4: Category | D4: Description | E4: Acquired | F4: Qty | G4: Cost / Unit | H4: Total Cost | I4: Current Price / Unit | J4: Last Updated | K4: Total Current Value | L4: Unrealized P&L $ | M4: Unrealized P&L % | N4: Days Held | O4: Tax Status | P4: Storage | Q4: Notes | R4: Buyer
A5: INV-001 | B5: S001 | C5: =IFERROR(VLOOKUP(B5,Watchlist!$A$5:$AB$202,2,FALSE()),"") | D5: =IFERROR(VLOOKUP(B5,Watchlist!$A$5:$AB$202,4,FALSE())&" — "&VLOOKUP(B5,Watchlist!$A$5:$AB$202,7,FALSE()),"") | E5: 46127 | F5: 2 | G5: 275 | H5: =F5*G5 | I5: =IFERROR(VLOOKUP(B5,Watchlist!$A$5:$AB$202,8,FALSE()),0) | J5: =IFERROR(VLOOKUP(B5,Watchlist!$A$5:$AB$202,9,FALSE()),"") | K5: =F5*I5 | L5: =K5-H5 | M5: =IFERROR(L5/H5,0) | N5: =IFERROR(TODAY()-E5,0) | O5: =IF(N5>365,"LT","ST") | P5: Vault Safe A | Q5: ES BB - case fresh, weighed 543g and 547g | R5: Brandon
A6: INV-002 | B6: M001 | C6: =IFERROR(VLOOKUP(B6,Watchlist!$A$5:$AB$202,2,FALSE()),"") | D6: =IFERROR(VLOOKUP(B6,Watchlist!$A$5:$AB$202,4,FALSE())&" — "&VLOOKUP(B6,Watchlist!$A$5:$AB$202,7,FALSE()),"") | E6: 46101 | F6: 1 | G6: 1450 | H6: =F6*G6 | I6: =IFERROR(VLOOKUP(B6,Watchlist!$A$5:$AB$202,8,FALSE()),0) | J6: =IFERROR(VLOOKUP(B6,Watchlist!$A$5:$AB$202,9,FALSE()),"") | K6: =F6*I6 | L6: =K6-H6 | M6: =IFERROR(L6/H6,0) | N6: =IFERROR(TODAY()-E6,0) | O6: =IF(N6>365,"LT","ST") | P6: Top Loader Binder | Q6: PSA 10 Moonbreon, strong centering from PWCC | R6: Brandon
A7: INV-003 | B7: S024 | C7: =IFERROR(VLOOKUP(B7,Watchlist!$A$5:$AB$202,2,FALSE()),"") | D7: =IFERROR(VLOOKUP(B7,Watchlist!$A$5:$AB$202,4,FALSE())&" — "&VLOOKUP(B7,Watchlist!$A$5:$AB$202,7,FALSE()),"") | E7: 46063 | F7: 3 | G7: 165 | H7: =F7*G7 | I7: =IFERROR(VLOOKUP(B7,Watchlist!$A$5:$AB$202,8,FALSE()),0) | J7: =IFERROR(VLOOKUP(B7,Watchlist!$A$5:$AB$202,9,FALSE()),"") | K7: =F7*I7 | L7: =K7-H7 | M7: =IFERROR(L7/H7,0) | N7: =IFERROR(TODAY()-E7,0) | O7: =IF(N7>365,"LT","ST") | P7: Vault Safe A | Q7: PE ETBs at preorder | R7: Joint
A8: INV-004 | B8: M047 | C8: =IFERROR(VLOOKUP(B8,Watchlist!$A$5:$AB$202,2,FALSE()),"") | D8: =IFERROR(VLOOKUP(B8,Watchlist!$A$5:$AB$202,4,FALSE())&" — "&VLOOKUP(B8,Watchlist!$A$5:$AB$202,7,FALSE()),"") | E8: 46140 | F8: 4 | G8: 265 | H8: =F8*G8 | I8: =IFERROR(VLOOKUP(B8,Watchlist!$A$5:$AB$202,8,FALSE()),0) | J8: =IFERROR(VLOOKUP(B8,Watchlist!$A$5:$AB$202,9,FALSE()),"") | K8: =F8*I8 | L8: =K8-H8 | M8: =IFERROR(L8/H8,0) | N8: =IFERROR(TODAY()-E8,0) | O8: =IF(N8>365,"LT","ST") | P8: Submission Box | Q8: Raw Char ex SIR OF for PSA Value | R8: Brandon
A9: P-001 | B9: PERSONAL | C9: =IFERROR(VLOOKUP(B9,Watchlist!$A$5:$AB$202,2,FALSE()),"") | D9: Pikachu VMAX Rainbow Rare PSA 10 | E9: 46113 | F9: 1 | G9: 375 | H9: 375 | I9: 375 | J9: =IFERROR(VLOOKUP(B9,Watchlist!$A$5:$AB$202,9,FALSE()),"") | K9: 375 | L9: 0 | M9: 0 | N9: =IF(ISNUMBER(E9),TODAY()-E9,0) | O9: =IF(ISNUMBER(E9),IF(N9>365,"LT","ST"),"") | P9: Graded Card · Existing · Anchor — hold | R9: Brandon
A10: P-002 | B10: PERSONAL | C10: =IFERROR(VLOOKUP(B10,Watchlist!$A$5:$AB$202,2,FALSE()),"") | D10: 1999 Unlimited Base Set Venusaur Pack | E10: 46113 | F10: 1 | G10: 1500 | H10: 1500 | I10: 1500 | J10: =IFERROR(VLOOKUP(B10,Watchlist!$A$5:$AB$202,9,FALSE()),"") | K10: 1500 | L10: 0 | M10: 0 | N10: =IF(ISNUMBER(E10),TODAY()-E10,0) | O10: =IF(ISNUMBER(E10),IF(N10>365,"LT","ST"),"") | P10: Sealed Vintage · Inherited · Submit PSA sealed ASAP | R10: Brandon
A11: P-003 | B11: PERSONAL | C11: =IFERROR(VLOOKUP(B11,Watchlist!$A$5:$AB$202,2,FALSE()),"") | D11: Vintage Duo Packs — held | E11: 46113 | F11: 1 | G11: 600 | H11: 600 | I11: 600 | J11: =IFERROR(VLOOKUP(B11,Watchlist!$A$5:$AB$202,9,FALSE()),"") | K11: 600 | L11: 0 | M11: 0 | N11: =IF(ISNUMBER(E11),TODAY()-E11,0) | O11: =IF(ISNUMBER(E11),IF(N11>365,"LT","ST"),"") | P11: Sealed Vintage · Inherited · $200-300 each — all held | R11: Brandon
C12: =IFERROR(VLOOKUP(B12,Watchlist!$A$5:$AB$202,2,FALSE()),"") | D12: =IFERROR(VLOOKUP(B12,Watchlist!$A$5:$AB$202,4,FALSE())&" — "&VLOOKUP(B12,Watchlist!$A$5:$AB$202,7,FALSE()),"") | H12: =IF(AND(ISNUMBER(F12),ISNUMBER(G12)),F12*G12,0) | I12: =IFERROR(VLOOKUP(B12,Watchlist!$A$5:$AB$202,8,FALSE()),0) | J12: =IFERROR(VLOOKUP(B12,Watchlist!$A$5:$AB$202,9,FALSE()),"") | K12: =IF(ISNUMBER(F12),F12*I12,0) | L12: =IF(H12=0,0,K12-H12) | M12: =IFERROR(L12/H12,0) | N12: =IF(ISNUMBER(E12),TODAY()-E12,0) | O12: =IF(ISNUMBER(E12),IF(N12>365,"LT","ST"),"")
C13: =IFERROR(VLOOKUP(B13,Watchlist!$A$5:$AB$202,2,FALSE()),"") | D13: =IFERROR(VLOOKUP(B13,Watchlist!$A$5:$AB$202,4,FALSE())&" — "&VLOOKUP(B13,Watchlist!$A$5:$AB$202,7,FALSE()),"") | H13: =IF(AND(ISNUMBER(F13),ISNUMBER(G13)),F13*G13,0) | I13: =IFERROR(VLOOKUP(B13,Watchlist!$A$5:$AB$202,8,FALSE()),0) | J13: =IFERROR(VLOOKUP(B13,Watchlist!$A$5:$AB$202,9,FALSE()),"") | K13: =IF(ISNUMBER(F13),F13*I13,0) | L13: =IF(H13=0,0,K13-H13) | M13: =IFERROR(L13/H13,0) | N13: =IF(ISNUMBER(E13),TODAY()-E13,0) | O13: =IF(ISNUMBER(E13),IF(N13>365,"LT","ST"),"")
C14: =IFERROR(VLOOKUP(B14,Watchlist!$A$5:$AB$202,2,FALSE()),"") | D14: =IFERROR(VLOOKUP(B14,Watchlist!$A$5:$AB$202,4,FALSE())&" — "&VLOOKUP(B14,Watchlist!$A$5:$AB$202,7,FALSE()),"") | H14: =IF(AND(ISNUMBER(F14),ISNUMBER(G14)),F14*G14,0) | I14: =IFERROR(VLOOKUP(B14,Watchlist!$A$5:$AB$202,8,FALSE()),0) | J14: =IFERROR(VLOOKUP(B14,Watchlist!$A$5:$AB$202,9,FALSE()),"") | K14: =IF(ISNUMBER(F14),F14*I14,0) | L14: =IF(H14=0,0,K14-H14) | M14: =IFERROR(L14/H14,0) | N14: =IF(ISNUMBER(E14),TODAY()-E14,0) | O14: =IF(ISNUMBER(E14),IF(N14>365,"LT","ST"),"")
C15: =IFERROR(VLOOKUP(B15,Watchlist!$A$5:$AB$202,2,FALSE()),"") | D15: =IFERROR(VLOOKUP(B15,Watchlist!$A$5:$AB$202,4,FALSE())&" — "&VLOOKUP(B15,Watchlist!$A$5:$AB$202,7,FALSE()),"") | H15: =IF(AND(ISNUMBER(F15),ISNUMBER(G15)),F15*G15,0) | I15: =IFERROR(VLOOKUP(B15,Watchlist!$A$5:$AB$202,8,FALSE()),0) | J15: =IFERROR(VLOOKUP(B15,Watchlist!$A$5:$AB$202,9,FALSE()),"") | K15: =IF(ISNUMBER(F15),F15*I15,0) | L15: =IF(H15=0,0,K15-H15) | M15: =IFERROR(L15/H15,0) | N15: =IF(ISNUMBER(E15),TODAY()-E15,0) | O15: =IF(ISNUMBER(E15),IF(N15>365,"LT","ST"),"")
C16: =IFERROR(VLOOKUP(B16,Watchlist!$A$5:$AB$202,2,FALSE()),"") | D16: =IFERROR(VLOOKUP(B16,Watchlist!$A$5:$AB$202,4,FALSE())&" — "&VLOOKUP(B16,Watchlist!$A$5:$AB$202,7,FALSE()),"") | H16: =IF(AND(ISNUMBER(F16),ISNUMBER(G16)),F16*G16,0) | I16: =IFERROR(VLOOKUP(B16,Watchlist!$A$5:$AB$202,8,FALSE()),0) | J16: =IFERROR(VLOOKUP(B16,Watchlist!$A$5:$AB$202,9,FALSE()),"") | K16: =IF(ISNUMBER(F16),F16*I16,0) | L16: =IF(H16=0,0,K16-H16) | M16: =IFERROR(L16/H16,0) | N16: =IF(ISNUMBER(E16),TODAY()-E16,0) | O16: =IF(ISNUMBER(E16),IF(N16>365,"LT","ST"),"")
C17: =IFERROR(VLOOKUP(B17,Watchlist!$A$5:$AB$202,2,FALSE()),"") | D17: =IFERROR(VLOOKUP(B17,Watchlist!$A$5:$AB$202,4,FALSE())&" — "&VLOOKUP(B17,Watchlist!$A$5:$AB$202,7,FALSE()),"") | H17: =IF(AND(ISNUMBER(F17),ISNUMBER(G17)),F17*G17,0) | I17: =IFERROR(VLOOKUP(B17,Watchlist!$A$5:$AB$202,8,FALSE()),0) | J17: =IFERROR(VLOOKUP(B17,Watchlist!$A$5:$AB$202,9,FALSE()),"") | K17: =IF(ISNUMBER(F17),F17*I17,0) | L17: =IF(H17=0,0,K17-H17) | M17: =IFERROR(L17/H17,0) | N17: =IF(ISNUMBER(E17),TODAY()-E17,0) | O17: =IF(ISNUMBER(E17),IF(N17>365,"LT","ST"),"")
C18: =IFERROR(VLOOKUP(B18,Watchlist!$A$5:$AB$202,2,FALSE()),"") | D18: =IFERROR(VLOOKUP(B18,Watchlist!$A$5:$AB$202,4,FALSE())&" — "&VLOOKUP(B18,Watchlist!$A$5:$AB$202,7,FALSE()),"") | H18: =IF(AND(ISNUMBER(F18),ISNUMBER(G18)),F18*G18,0) | I18: =IFERROR(VLOOKUP(B18,Watchlist!$A$5:$AB$202,8,FALSE()),0) | J18: =IFERROR(VLOOKUP(B18,Watchlist!$A$5:$AB$202,9,FALSE()),"") | K18: =IF(ISNUMBER(F18),F18*I18,0) | L18: =IF(H18=0,0,K18-H18) | M18: =IFERROR(L18/H18,0) | N18: =IF(ISNUMBER(E18),TODAY()-E18,0) | O18: =IF(ISNUMBER(E18),IF(N18>365,"LT","ST"),"")
C19: =IFERROR(VLOOKUP(B19,Watchlist!$A$5:$AB$202,2,FALSE()),"") | D19: =IFERROR(VLOOKUP(B19,Watchlist!$A$5:$AB$202,4,FALSE())&" — "&VLOOKUP(B19,Watchlist!$A$5:$AB$202,7,FALSE()),"") | H19: =IF(AND(ISNUMBER(F19),ISNUMBER(G19)),F19*G19,0) | I19: =IFERROR(VLOOKUP(B19,Watchlist!$A$5:$AB$202,8,FALSE()),0) | J19: =IFERROR(VLOOKUP(B19,Watchlist!$A$5:$AB$202,9,FALSE()),"") | K19: =IF(ISNUMBER(F19),F19*I19,0) | L19: =IF(H19=0,0,K19-H19) | M19: =IFERROR(L19/H19,0) | N19: =IF(ISNUMBER(E19),TODAY()-E19,0) | O19: =IF(ISNUMBER(E19),IF(N19>365,"LT","ST"),"")
C20: =IFERROR(VLOOKUP(B20,Watchlist!$A$5:$AB$202,2,FALSE()),"") | D20: =IFERROR(VLOOKUP(B20,Watchlist!$A$5:$AB$202,4,FALSE())&" — "&VLOOKUP(B20,Watchlist!$A$5:$AB$202,7,FALSE()),"") | H20: =IF(AND(ISNUMBER(F20),ISNUMBER(G20)),F20*G20,0) | I20: =IFERROR(VLOOKUP(B20,Watchlist!$A$5:$AB$202,8,FALSE()),0) | J20: =IFERROR(VLOOKUP(B20,Watchlist!$A$5:$AB$202,9,FALSE()),"") | K20: =IF(ISNUMBER(F20),F20*I20,0) | L20: =IF(H20=0,0,K20-H20) | M20: =IFERROR(L20/H20,0) | N20: =IF(ISNUMBER(E20),TODAY()-E20,0) | O20: =IF(ISNUMBER(E20),IF(N20>365,"LT","ST"),"")
C21: =IFERROR(VLOOKUP(B21,Watchlist!$A$5:$AB$202,2,FALSE()),"") | D21: =IFERROR(VLOOKUP(B21,Watchlist!$A$5:$AB$202,4,FALSE())&" — "&VLOOKUP(B21,Watchlist!$A$5:$AB$202,7,FALSE()),"") | H21: =IF(AND(ISNUMBER(F21),ISNUMBER(G21)),F21*G21,0) | I21: =IFERROR(VLOOKUP(B21,Watchlist!$A$5:$AB$202,8,FALSE()),0) | J21: =IFERROR(VLOOKUP(B21,Watchlist!$A$5:$AB$202,9,FALSE()),"") | K21: =IF(ISNUMBER(F21),F21*I21,0) | L21: =IF(H21=0,0,K21-H21) | M21: =IFERROR(L21/H21,0) | N21: =IF(ISNUMBER(E21),TODAY()-E21,0) | O21: =IF(ISNUMBER(E21),IF(N21>365,"LT","ST"),"")
C22: =IFERROR(VLOOKUP(B22,Watchlist!$A$5:$AB$202,2,FALSE()),"") | D22: =IFERROR(VLOOKUP(B22,Watchlist!$A$5:$AB$202,4,FALSE())&" — "&VLOOKUP(B22,Watchlist!$A$5:$AB$202,7,FALSE()),"") | H22: =IF(AND(ISNUMBER(F22),ISNUMBER(G22)),F22*G22,0) | I22: =IFERROR(VLOOKUP(B22,Watchlist!$A$5:$AB$202,8,FALSE()),0) | J22: =IFERROR(VLOOKUP(B22,Watchlist!$A$5:$AB$202,9,FALSE()),"") | K22: =IF(ISNUMBER(F22),F22*I22,0) | L22: =IF(H22=0,0,K22-H22) | M22: =IFERROR(L22/H22,0) | N22: =IF(ISNUMBER(E22),TODAY()-E22,0) | O22: =IF(ISNUMBER(E22),IF(N22>365,"LT","ST"),"")
C23: =IFERROR(VLOOKUP(B23,Watchlist!$A$5:$AB$202,2,FALSE()),"") | D23: =IFERROR(VLOOKUP(B23,Watchlist!$A$5:$AB$202,4,FALSE())&" — "&VLOOKUP(B23,Watchlist!$A$5:$AB$202,7,FALSE()),"") | H23: =IF(AND(ISNUMBER(F23),ISNUMBER(G23)),F23*G23,0) | I23: =IFERROR(VLOOKUP(B23,Watchlist!$A$5:$AB$202,8,FALSE()),0) | J23: =IFERROR(VLOOKUP(B23,Watchlist!$A$5:$AB$202,9,FALSE()),"") | K23: =IF(ISNUMBER(F23),F23*I23,0) | L23: =IF(H23=0,0,K23-H23) | M23: =IFERROR(L23/H23,0) | N23: =IF(ISNUMBER(E23),TODAY()-E23,0) | O23: =IF(ISNUMBER(E23),IF(N23>365,"LT","ST"),"")
... C58: =IFERROR(VLOOKUP(B58,Watchlist!$A$5:$AB$202,2,FALSE()),"") | D58: =IFERROR(VLOOKUP(B58,Watchlist!$A$5:$AB$202,4,FALSE())&" — "&VLOOKUP(B58,Watchlist!$A$5:$AB$202,7,FALSE()),"") | H58: =IF(AND(ISNUMBER(F58),ISNUMBER(G58)),F58*G58,0) | I58: =IFERROR(VLOOKUP(B58,Watchlist!$A$5:$AB$202,8,FALSE()),0) | J58: =IFERROR(VLOOKUP(B58,Watchlist!$A$5:$AB$202,9,FALSE()),"") | K58: =IF(ISNUMBER(F58),F58*I58,0) | L58: =IF(H58=0,0,K58-H58) | M58: =IFERROR(L58/H58,0) | N58: =IF(ISNUMBER(E58),TODAY()-E58,0) | O58: =IF(ISNUMBER(E58),IF(N58>365,"LT","ST"),"")

Sheet Grading Pipeline
A1: GRADING PIPELINE
A2: Submit only when EV/Cost > 1.5x. Math: (P10% × P10$) + (P9% × P9$) − fees
A4: Sub ID | B4: CardID | C4: Description | D4: Submitted | E4: Service | F4: PSA Fee | G4: Qty | H4: Est PSA10 % | I4: Est PSA10 $ | J4: Est PSA9 $ | K4: Total Fees | L4: Cost Basis | M4: Expected Value | N4: Expected ROI % | O4: Status | P4: Returned | Q4: Notes
A5: SUB-001 | B5: M047 | C5: =IFERROR(VLOOKUP(B5,Watchlist!$A$5:$AB$202,4,FALSE()),"") | D5: 46140 | E5: Value | F5: 24.99 | G5: 4 | H5: 0.5 | I5: 950 | J5: 350 | K5: =F5*G5 | L5: =IFERROR(SUMIFS(Inventory!H:H,Inventory!B:B,B5),0) | M5: =G5*(H5*I5+(1-H5)*J5)-K5 | N5: =IFERROR((M5-L5)/L5,0) | O5: Pending
A6: SUB-002 | B6: M002 | C6: =IFERROR(VLOOKUP(B6,Watchlist!$A$5:$AB$202,4,FALSE()),"") | D6: 46122 | E6: Value | F6: 24.99 | G6: 2 | H6: 0.42 | I6: 1500 | J6: 650 | K6: =F6*G6 | L6: =IFERROR(SUMIFS(Inventory!H:H,Inventory!B:B,B6),0) | M6: =G6*(H6*I6+(1-H6)*J6)-K6 | N6: =IFERROR((M6-L6)/L6,0) | O6: Pending
A7: SUB-003 | B7: M079 | C7: =IFERROR(VLOOKUP(B7,Watchlist!$A$5:$AB$202,4,FALSE()),"") | D7: 46103 | E7: Value | F7: 24.99 | G7: 5 | H7: 0.45 | I7: 200 | J7: 90 | K7: =F7*G7 | L7: =IFERROR(SUMIFS(Inventory!H:H,Inventory!B:B,B7),0) | M7: =G7*(H7*I7+(1-H7)*J7)-K7 | N7: =IFERROR((M7-L7)/L7,0) | O7: Pending
C8: =IFERROR(VLOOKUP(B8,Watchlist!$A$5:$AB$202,4,FALSE()),"") | K8: =IF(AND(ISNUMBER(F8),ISNUMBER(G8)),F8*G8,0) | L8: =IFERROR(SUMIFS(Inventory!H:H,Inventory!B:B,B8),0) | M8: =IF(ISNUMBER(G8),G8*(H8*I8+(1-H8)*J8)-K8,0) | N8: =IFERROR((M8-L8)/L8,0)
C9: =IFERROR(VLOOKUP(B9,Watchlist!$A$5:$AB$202,4,FALSE()),"") | K9: =IF(AND(ISNUMBER(F9),ISNUMBER(G9)),F9*G9,0) | L9: =IFERROR(SUMIFS(Inventory!H:H,Inventory!B:B,B9),0) | M9: =IF(ISNUMBER(G9),G9*(H9*I9+(1-H9)*J9)-K9,0) | N9: =IFERROR((M9-L9)/L9,0)
C10: =IFERROR(VLOOKUP(B10,Watchlist!$A$5:$AB$202,4,FALSE()),"") | K10: =IF(AND(ISNUMBER(F10),ISNUMBER(G10)),F10*G10,0) | L10: =IFERROR(SUMIFS(Inventory!H:H,Inventory!B:B,B10),0) | M10: =IF(ISNUMBER(G10),G10*(H10*I10+(1-H10)*J10)-K10,0) | N10: =IFERROR((M10-L10)/L10,0)
C11: =IFERROR(VLOOKUP(B11,Watchlist!$A$5:$AB$202,4,FALSE()),"") | K11: =IF(AND(ISNUMBER(F11),ISNUMBER(G11)),F11*G11,0) | L11: =IFERROR(SUMIFS(Inventory!H:H,Inventory!B:B,B11),0) | M11: =IF(ISNUMBER(G11),G11*(H11*I11+(1-H11)*J11)-K11,0) | N11: =IFERROR((M11-L11)/L11,0)
C12: =IFERROR(VLOOKUP(B12,Watchlist!$A$5:$AB$202,4,FALSE()),"") | K12: =IF(AND(ISNUMBER(F12),ISNUMBER(G12)),F12*G12,0) | L12: =IFERROR(SUMIFS(Inventory!H:H,Inventory!B:B,B12),0) | M12: =IF(ISNUMBER(G12),G12*(H12*I12+(1-H12)*J12)-K12,0) | N12: =IFERROR((M12-L12)/L12,0)
C13: =IFERROR(VLOOKUP(B13,Watchlist!$A$5:$AB$202,4,FALSE()),"") | K13: =IF(AND(ISNUMBER(F13),ISNUMBER(G13)),F13*G13,0) | L13: =IFERROR(SUMIFS(Inventory!H:H,Inventory!B:B,B13),0) | M13: =IF(ISNUMBER(G13),G13*(H13*I13+(1-H13)*J13)-K13,0) | N13: =IFERROR((M13-L13)/L13,0)
C14: =IFERROR(VLOOKUP(B14,Watchlist!$A$5:$AB$202,4,FALSE()),"") | K14: =IF(AND(ISNUMBER(F14),ISNUMBER(G14)),F14*G14,0) | L14: =IFERROR(SUMIFS(Inventory!H:H,Inventory!B:B,B14),0) | M14: =IF(ISNUMBER(G14),G14*(H14*I14+(1-H14)*J14)-K14,0) | N14: =IFERROR((M14-L14)/L14,0)
C15: =IFERROR(VLOOKUP(B15,Watchlist!$A$5:$AB$202,4,FALSE()),"") | K15: =IF(AND(ISNUMBER(F15),ISNUMBER(G15)),F15*G15,0) | L15: =IFERROR(SUMIFS(Inventory!H:H,Inventory!B:B,B15),0) | M15: =IF(ISNUMBER(G15),G15*(H15*I15+(1-H15)*J15)-K15,0) | N15: =IFERROR((M15-L15)/L15,0)
C16: =IFERROR(VLOOKUP(B16,Watchlist!$A$5:$AB$202,4,FALSE()),"") | K16: =IF(AND(ISNUMBER(F16),ISNUMBER(G16)),F16*G16,0) | L16: =IFERROR(SUMIFS(Inventory!H:H,Inventory!B:B,B16),0) | M16: =IF(ISNUMBER(G16),G16*(H16*I16+(1-H16)*J16)-K16,0) | N16: =IFERROR((M16-L16)/L16,0)
C17: =IFERROR(VLOOKUP(B17,Watchlist!$A$5:$AB$202,4,FALSE()),"") | K17: =IF(AND(ISNUMBER(F17),ISNUMBER(G17)),F17*G17,0) | L17: =IFERROR(SUMIFS(Inventory!H:H,Inventory!B:B,B17),0) | M17: =IF(ISNUMBER(G17),G17*(H17*I17+(1-H17)*J17)-K17,0) | N17: =IFERROR((M17-L17)/L17,0)
C18: =IFERROR(VLOOKUP(B18,Watchlist!$A$5:$AB$202,4,FALSE()),"") | K18: =IF(AND(ISNUMBER(F18),ISNUMBER(G18)),F18*G18,0) | L18: =IFERROR(SUMIFS(Inventory!H:H,Inventory!B:B,B18),0) | M18: =IF(ISNUMBER(G18),G18*(H18*I18+(1-H18)*J18)-K18,0) | N18: =IFERROR((M18-L18)/L18,0)
C19: =IFERROR(VLOOKUP(B19,Watchlist!$A$5:$AB$202,4,FALSE()),"") | K19: =IF(AND(ISNUMBER(F19),ISNUMBER(G19)),F19*G19,0) | L19: =IFERROR(SUMIFS(Inventory!H:H,Inventory!B:B,B19),0) | M19: =IF(ISNUMBER(G19),G19*(H19*I19+(1-H19)*J19)-K19,0) | N19: =IFERROR((M19-L19)/L19,0)
... C32: =IFERROR(VLOOKUP(B32,Watchlist!$A$5:$AB$202,4,FALSE()),"") | K32: =IF(AND(ISNUMBER(F32),ISNUMBER(G32)),F32*G32,0) | L32: =IFERROR(SUMIFS(Inventory!H:H,Inventory!B:B,B32),0) | M32: =IF(ISNUMBER(G32),G32*(H32*I32+(1-H32)*J32)-K32,0) | N32: =IFERROR((M32-L32)/L32,0)

Sheet Realized P&L
A1: REALIZED P&L
A2: Sales log. Auto-flags LT (>365 days) vs ST tax status.
A4: Sale ID | B4: CardID | C4: Description | D4: Buy Date | E4: Sell Date | F4: Qty | G4: Total Cost | H4: Gross Sale | I4: Fees % | J4: Net Proceeds | K4: Net P&L | L4: Holding Days | M4: Tax | N4: Channel | O4: Notes
A5: SALE-001 | B5: S028 | C5: =IFERROR(VLOOKUP(B5,Watchlist!$A$5:$AB$202,4,FALSE()),"") | D5: 46065 | E5: 46086 | F5: 5 | G5: 80 | H5: 175 | I5: 0.13 | J5: =H5*F5*(1-I5) | K5: =J5-G5 | L5: =E5-D5 | M5: =IF(L5>365,"LT","ST") | N5: eBay | O5: Pokemon Day flipped at peak hype
C6: =IFERROR(VLOOKUP(B6,Watchlist!$A$5:$AB$202,4,FALSE()),"") | J6: =IF(AND(ISNUMBER(H6),ISNUMBER(F6),ISNUMBER(I6)),H6*F6*(1-I6),0) | K6: =IF(ISNUMBER(G6),J6-G6,0) | L6: =IF(AND(ISNUMBER(E6),ISNUMBER(D6)),E6-D6,0) | M6: =IF(ISNUMBER(L6),IF(L6>365,"LT","ST"),"")
C7: =IFERROR(VLOOKUP(B7,Watchlist!$A$5:$AB$202,4,FALSE()),"") | J7: =IF(AND(ISNUMBER(H7),ISNUMBER(F7),ISNUMBER(I7)),H7*F7*(1-I7),0) | K7: =IF(ISNUMBER(G7),J7-G7,0) | L7: =IF(AND(ISNUMBER(E7),ISNUMBER(D7)),E7-D7,0) | M7: =IF(ISNUMBER(L7),IF(L7>365,"LT","ST"),"")
C8: =IFERROR(VLOOKUP(B8,Watchlist!$A$5:$AB$202,4,FALSE()),"") | J8: =IF(AND(ISNUMBER(H8),ISNUMBER(F8),ISNUMBER(I8)),H8*F8*(1-I8),0) | K8: =IF(ISNUMBER(G8),J8-G8,0) | L8: =IF(AND(ISNUMBER(E8),ISNUMBER(D8)),E8-D8,0) | M8: =IF(ISNUMBER(L8),IF(L8>365,"LT","ST"),"")
C9: =IFERROR(VLOOKUP(B9,Watchlist!$A$5:$AB$202,4,FALSE()),"") | J9: =IF(AND(ISNUMBER(H9),ISNUMBER(F9),ISNUMBER(I9)),H9*F9*(1-I9),0) | K9: =IF(ISNUMBER(G9),J9-G9,0) | L9: =IF(AND(ISNUMBER(E9),ISNUMBER(D9)),E9-D9,0) | M9: =IF(ISNUMBER(L9),IF(L9>365,"LT","ST"),"")
C10: =IFERROR(VLOOKUP(B10,Watchlist!$A$5:$AB$202,4,FALSE()),"") | J10: =IF(AND(ISNUMBER(H10),ISNUMBER(F10),ISNUMBER(I10)),H10*F10*(1-I10),0) | K10: =IF(ISNUMBER(G10),J10-G10,0) | L10: =IF(AND(ISNUMBER(E10),ISNUMBER(D10)),E10-D10,0) | M10: =IF(ISNUMBER(L10),IF(L10>365,"LT","ST"),"")
C11: =IFERROR(VLOOKUP(B11,Watchlist!$A$5:$AB$202,4,FALSE()),"") | J11: =IF(AND(ISNUMBER(H11),ISNUMBER(F11),ISNUMBER(I11)),H11*F11*(1-I11),0) | K11: =IF(ISNUMBER(G11),J11-G11,0) | L11: =IF(AND(ISNUMBER(E11),ISNUMBER(D11)),E11-D11,0) | M11: =IF(ISNUMBER(L11),IF(L11>365,"LT","ST"),"")
C12: =IFERROR(VLOOKUP(B12,Watchlist!$A$5:$AB$202,4,FALSE()),"") | J12: =IF(AND(ISNUMBER(H12),ISNUMBER(F12),ISNUMBER(I12)),H12*F12*(1-I12),0) | K12: =IF(ISNUMBER(G12),J12-G12,0) | L12: =IF(AND(ISNUMBER(E12),ISNUMBER(D12)),E12-D12,0) | M12: =IF(ISNUMBER(L12),IF(L12>365,"LT","ST"),"")
C13: =IFERROR(VLOOKUP(B13,Watchlist!$A$5:$AB$202,4,FALSE()),"") | J13: =IF(AND(ISNUMBER(H13),ISNUMBER(F13),ISNUMBER(I13)),H13*F13*(1-I13),0) | K13: =IF(ISNUMBER(G13),J13-G13,0) | L13: =IF(AND(ISNUMBER(E13),ISNUMBER(D13)),E13-D13,0) | M13: =IF(ISNUMBER(L13),IF(L13>365,"LT","ST"),"")
C14: =IFERROR(VLOOKUP(B14,Watchlist!$A$5:$AB$202,4,FALSE()),"") | J14: =IF(AND(ISNUMBER(H14),ISNUMBER(F14),ISNUMBER(I14)),H14*F14*(1-I14),0) | K14: =IF(ISNUMBER(G14),J14-G14,0) | L14: =IF(AND(ISNUMBER(E14),ISNUMBER(D14)),E14-D14,0) | M14: =IF(ISNUMBER(L14),IF(L14>365,"LT","ST"),"")
C15: =IFERROR(VLOOKUP(B15,Watchlist!$A$5:$AB$202,4,FALSE()),"") | J15: =IF(AND(ISNUMBER(H15),ISNUMBER(F15),ISNUMBER(I15)),H15*F15*(1-I15),0) | K15: =IF(ISNUMBER(G15),J15-G15,0) | L15: =IF(AND(ISNUMBER(E15),ISNUMBER(D15)),E15-D15,0) | M15: =IF(ISNUMBER(L15),IF(L15>365,"LT","ST"),"")
C16: =IFERROR(VLOOKUP(B16,Watchlist!$A$5:$AB$202,4,FALSE()),"") | J16: =IF(AND(ISNUMBER(H16),ISNUMBER(F16),ISNUMBER(I16)),H16*F16*(1-I16),0) | K16: =IF(ISNUMBER(G16),J16-G16,0) | L16: =IF(AND(ISNUMBER(E16),ISNUMBER(D16)),E16-D16,0) | M16: =IF(ISNUMBER(L16),IF(L16>365,"LT","ST"),"")
C17: =IFERROR(VLOOKUP(B17,Watchlist!$A$5:$AB$202,4,FALSE()),"") | J17: =IF(AND(ISNUMBER(H17),ISNUMBER(F17),ISNUMBER(I17)),H17*F17*(1-I17),0) | K17: =IF(ISNUMBER(G17),J17-G17,0) | L17: =IF(AND(ISNUMBER(E17),ISNUMBER(D17)),E17-D17,0) | M17: =IF(ISNUMBER(L17),IF(L17>365,"LT","ST"),"")
... C45: =IFERROR(VLOOKUP(B45,Watchlist!$A$5:$AB$202,4,FALSE()),"") | J45: =IF(AND(ISNUMBER(H45),ISNUMBER(F45),ISNUMBER(I45)),H45*F45*(1-I45),0) | K45: =IF(ISNUMBER(G45),J45-G45,0) | L45: =IF(AND(ISNUMBER(E45),ISNUMBER(D45)),E45-D45,0) | M45: =IF(ISNUMBER(L45),IF(L45>365,"LT","ST"),"")

Sheet Allocation
B2: ALLOCATION & REBALANCING
B3: Yellow cells are inputs. ADD/TRIM/HOLD signals fire on 5% target deviation.
B5: STARTING CAPITAL
B6: Initial Capital | C6: 5000
B7: Monthly Contribution | C7: 1500
B8: Months Active | C8: =MAX(0,DATEDIF(DATE(2026,5,1),TODAY(),"m"))
B9: Total Deployed Target | C9: =C6+C7*C8
B11: TARGET ALLOCATION (Momentum-Lean Strategy)
B12: Category | C12: Target % | D12: Target $ | E12: Current $ | F12: Current % | G12: Variance | H12: Action | I12: Strategy
B13: Modern Chase PSA 10 | C13: 0.4 | D13: =$C$9*C13 | E13: =SUMIFS(Inventory!K:K,Inventory!C:C,B13) | F13: =IFERROR(E13/SUM($E$13:$E$17),0) | G13: =F13-C13 | H13: =IF(G13>0.05,"TRIM",IF(G13<-0.05,"ADD","HOLD")) | I13: Hot singles, raw-to-grade flips. Highest turnover. Where signals concentrate.
B14: Sealed Modern | C14: 0.3 | D14: =$C$9*C14 | E14: =SUMIFS(Inventory!K:K,Inventory!C:C,B14) | F14: =IFERROR(E14/SUM($E$13:$E$17),0) | G14: =F14-C14 | H14: =IF(G14>0.05,"TRIM",IF(G14<-0.05,"ADD","HOLD")) | I14: OOP sealed appreciation. Anchor positions for compounding.
B15: Vintage Graded Singles | C15: 0.15 | D15: =$C$9*C15 | E15: =SUMIFS(Inventory!K:K,Inventory!C:C,B15) | F15: =IFERROR(E15/SUM($E$13:$E$17),0) | G15: =F15-C15 | H15: =IF(G15>0.05,"TRIM",IF(G15<-0.05,"ADD","HOLD")) | I15: Blue chip exposure. PSA 9 WOTC + Gold Stars.
B16: Grading Pipeline | C16: 0.1 | D16: =$C$9*C16 | E16: =SUMIFS(Inventory!K:K,Inventory!C:C,B16) | F16: =IFERROR(E16/SUM($E$13:$E$17),0) | G16: =F16-C16 | H16: =IF(G16>0.05,"TRIM",IF(G16<-0.05,"ADD","HOLD")) | I16: Working capital. Raw cards in transit for grading.
B17: Cash / Working Capital | C17: 0.05 | D17: =$C$9*C17 | E17: =SUMIFS(Inventory!K:K,Inventory!C:C,B17) | F17: =IFERROR(E17/SUM($E$13:$E$17),0) | G17: =F17-C17 | H17: =IF(G17>0.05,"TRIM",IF(G17<-0.05,"ADD","HOLD")) | I17: Dry powder for dislocations.

Sheet Coordination
B2: COORDINATION — Two-Person Operation
B3: Brandon + Brother shared workflow. Dibs system prevents bidding wars. Owner-level P&L splits.
B5: P&L SPLIT BY OWNER
B6: Owner | C6: # Positions | D6: Total Cost | E6: Current Value | F6: Unrealized P&L $ | G6: Unrealized P&L % | H6: Realized P&L | I6: Combined P&L
B7: Brandon | C7: =COUNTIF(Inventory!R5:R58,B7) | D7: =SUMIFS(Inventory!H5:H58,Inventory!R5:R58,B7) | E7: =SUMIFS(Inventory!K5:K58,Inventory!R5:R58,B7) | F7: =E7-D7 | G7: =IFERROR(F7/D7,0) | H7: 0 | I7: =F7+H7
B8: Brother | C8: =COUNTIF(Inventory!R5:R58,B8) | D8: =SUMIFS(Inventory!H5:H58,Inventory!R5:R58,B8) | E8: =SUMIFS(Inventory!K5:K58,Inventory!R5:R58,B8) | F8: =E8-D8 | G8: =IFERROR(F8/D8,0) | H8: 0 | I8: =F8+H8
B9: Joint | C9: =COUNTIF(Inventory!R5:R58,B9) | D9: =SUMIFS(Inventory!H5:H58,Inventory!R5:R58,B9) | E9: =SUMIFS(Inventory!K5:K58,Inventory!R5:R58,B9) | F9: =E9-D9 | G9: =IFERROR(F9/D9,0) | H9: 0 | I9: =F9+H9
B10: TOTAL | C10: =SUM(C7:C9) | D10: =SUM(D7:D9) | E10: =SUM(E7:E9) | F10: =SUM(F7:F9) | G10: =SUM(G7:G9) | H10: =SUM(H7:H9) | I10: =SUM(I7:I9)
B13: DIBS — Active Pursuits (claim before bidding to prevent overlap)
B14: CardID | C14: Card Name | D14: Claimed By | E14: Max Bid | F14: Source | G14: Auction Ends | H14: Status | I14: Notes
B15: M001 | C15: =IFERROR(VLOOKUP(B15,Watchlist!$A$5:$D$202,4,FALSE()),"") | D15: Brandon | E15: 1200 | F15: eBay | G15: 46156 | H15: ACTIVE | I15: Watching 3 PSA 10 listings
B16: S027 | C16: =IFERROR(VLOOKUP(B16,Watchlist!$A$5:$D$202,4,FALSE()),"") | D16: Brother | E16: 195 | F16: Whatnot | G16: 46155 | H16: ACTIVE | I16: Ascended Heroes BB live show 7PM
B17: M078 | C17: =IFERROR(VLOOKUP(B17,Watchlist!$A$5:$D$202,4,FALSE()),"") | D17: Brandon | E17: 180 | F17: TCGPlayer | G17: 46157 | H17: WATCHLIST | I17: Waiting for Lillie SIR PSA 10 dip
C18: =IFERROR(VLOOKUP(B18,Watchlist!$A$5:$D$202,4,FALSE()),"")
C19: =IFERROR(VLOOKUP(B19,Watchlist!$A$5:$D$202,4,FALSE()),"")
C20: =IFERROR(VLOOKUP(B20,Watchlist!$A$5:$D$202,4,FALSE()),"")
C21: =IFERROR(VLOOKUP(B21,Watchlist!$A$5:$D$202,4,FALSE()),"")
C22: =IFERROR(VLOOKUP(B22,Watchlist!$A$5:$D$202,4,FALSE()),"")
C23: =IFERROR(VLOOKUP(B23,Watchlist!$A$5:$D$202,4,FALSE()),"")
C24: =IFERROR(VLOOKUP(B24,Watchlist!$A$5:$D$202,4,FALSE()),"")
C25: =IFERROR(VLOOKUP(B25,Watchlist!$A$5:$D$202,4,FALSE()),"")
C26: =IFERROR(VLOOKUP(B26,Watchlist!$A$5:$D$202,4,FALSE()),"")
C27: =IFERROR(VLOOKUP(B27,Watchlist!$A$5:$D$202,4,FALSE()),"")
C28: =IFERROR(VLOOKUP(B28,Watchlist!$A$5:$D$202,4,FALSE()),"")
C29: =IFERROR(VLOOKUP(B29,Watchlist!$A$5:$D$202,4,FALSE()),"")
... C34: =IFERROR(VLOOKUP(B34,Watchlist!$A$5:$D$202,4,FALSE()),"")
B37: SOURCING LEADS — Card shops, meets, eBay sellers worth tracking
B38: Source Name | C38: Type | D38: Location | E38: Specialty | F38: Last Visit | G38: Best Deal Found | H38: Rating (1-5) | I38: Notes
B39: Frank & Son Collectibles | C39: Card Show | D39: City of Industry CA | E39: Vintage WOTC | F39: 46139 | G39: ES BB $260 | H39: 5 | I39: Sun 9AM-3PM. Best So Cal show. Cash deals.
B40: Trade-N-Games | C40: LCS | D40: Anaheim CA | E40: Modern sealed | F40: 46132 | G40: PE ETB $155 | H40: 4 | I40: Owner Jim runs Whatnot Wed. Pre-text first.
B41: Pokemon Card Hunters LA | C41: Meet | D41: Pasadena CA | E41: Singles/trades | H41: 4 | I41: Sat morning Pasadena Convention Center.
B42: PWCC Weekly Auctions | C42: Online | D42: — | E42: All tiers | H42: 5 | I42: Wed evening closes. Stack of vintage PSA 9s.
B43: Whatnot - PokeRippa | C43: Live stream | D43: Online | E43: PSA modern | H43: 4 | I43: Tue/Thu 8PM PT. Aggressive bid pacing.
B53: WEEKLY OPS MEETING TEMPLATE (15 min Sun evening)
B54: 1. Review Weekly Buy List — agree on top 3 deploys this week (split by buyer)
B55: 2. Check Dibs — confirm no overlap; reassign if conflict
B56: 3. Inventory check — any positions to TRIM or take profits this week?
B57: 4. Grading Pipeline — anything submitted? Anything coming back?
B58: 5. Card shops calendar — who's hitting Frank & Son / LCS Saturday?
B59: 6. Cash position — both contributed weekly $? Bank reconciliation?
B60: 7. Wins/losses last week — debrief any sales over $200 P&L
B61: 8. Next 7 days schedule — auctions, meets, shipments

Sheet Price History
A1: PRICE HISTORY — 90 Day Baseline + Refresh Append
A2: Each refresh appends a new row. Used by Watchlist trend formulas (7D / 30D / 90D % change).
A4: Date | B4: V001 | C4: V002 | D4: V003 | E4: V004 | F4: V005 | G4: V006 | H4: V007 | I4: V008 | J4: V009 | K4: V010 | L4: V011 | M4: V012 | N4: V013 | O4: V014 | P4: V015 | Q4: V016 | R4: V017 | S4: V018 | T4: V019 | U4: V020 | V4: V021 | W4: V022 | X4: V023 | Y4: V024 | Z4: V025 | AA4: V026 | AB4: V027 | AC4: V028 | AD4: V029 | AE4: V030 | AF4: V031 | AG4: V032 | AH4: V033 | AI4: V034 | AJ4: V035 | AK4: M001 | AL4: M002 | AM4: M003 | AN4: M004 | AO4: M005 | AP4: M006 | AQ4: M007 | AR4: M008 | AS4: M009 | AT4: M010 | AU4: M011 | AV4: M012 | AW4: M013 | AX4: M014 | AY4: M015 | AZ4: M016 | BA4: M017 | BB4: M018 | BC4: M019 | BD4: M020 | BE4: M021 | BF4: M022 | BG4: M023 | BH4: M024 | BI4: M025 | BJ4: M026 | BK4: M027 | BL4: M028 | BM4: M029 | BN4: M030 | BO4: M031 | BP4: M032 | BQ4: M033 | BR4: M034 | BS4: M035 | BT4: M036 | BU4: M037 | BV4: M038 | BW4: M039 | BX4: M040 | BY4: M041 | BZ4: M042 | CA4: M043 | CB4: M044 | CC4: M045 | CD4: M046 | CE4: M047 | CF4: M048 | CG4: M049 | CH4: M050 | CI4: M051 | CJ4: M052 | CK4: M053 | CL4: M054 | CM4: M055 | CN4: M056 | CO4: M057 | CP4: M058 | CQ4: M059 | CR4: M060 | CS4: M061 | CT4: M062 | CU4: M063 | CV4: M064 | CW4: M065 | CX4: M066 | CY4: M067 | CZ4: M068 | DA4: M069 | DB4: M070 | DC4: M071 | DD4: M072 | DE4: M073 | DF4: M074 | DG4: M075 | DH4: M076 | DI4: M077 | DJ4: M078 | DK4: M079 | DL4: M080 | DM4: M081 | DN4: M082 | DO4: M083 | DP4: M084 | DQ4: M085 | DR4: M086 | DS4: M087 | DT4: M088 | DU4: M089 | DV4: M090 | DW4: M091 | DX4: M092 | DY4: M093 | DZ4: S001 | EA4: S002 | EB4: S003 | EC4: S004 | ED4: S005 | EE4: S006 | EF4: S007 | EG4: S008 | EH4: S009 | EI4: S010 | EJ4: S011 | EK4: S012 | EL4: S013 | EM4: S014 | EN4: S015 | EO4: S016 | EP4: S017 | EQ4: S018 | ER4: S019 | ES4: S020 | ET4: S021 | EU4: S022 | EV4: S023 | EW4: S024 | EX4: S025 | EY4: S026 | EZ4: S027 | FA4: S028 | FB4: S029 | FC4: S030 | FD4: S031 | FE4: S032 | FF4: X001 | FG4: X002 | FH4: X003 | FI4: X004 | FJ4: X005 | FK4: X006 | FL4: X007 | FM4: X008 | FN4: X009 | FO4: X010 | FP4: X011 | FQ4: X012 | FR4: X013 | FS4: X014 | FT4: X015 | FU4: J001 | FV4: J002 | FW4: J003 | FX4: J004 | FY4: J005 | FZ4: J006 | GA4: J007 | GB4: J008 | GC4: J009 | GD4: J010 | GE4: V036 | GF4: V037 | GG4: V038 | GH4: V039 | GI4: V040 | GJ4: V041 | GK4: V042 | GL4: V043 | GM4: X016 | GN4: X017 | GO4: X018 | GP4: X019 | GQ4: X020 | GR4: P001 | GS4: P002 | GT4: P003 | GU4: P004 | GV4: P005 | GW4: P006 | GX4: P007 | GY4: P008 | GZ4: P009 | HA4: P010 | HB4: P011 | HC4: P012 | HD4: P013 | HE4: P014 | HF4: P015 | HG4: P016 | HH4: P017 | HI4: P018 | HJ4: P019 | HK4: P020 | HL4: P021 | HM4: P022 | HN4: P023 | HO4: P024 | HP4: P025 | HQ4: P026 | HR4: P027 | HS4: P028 | HT4: P029 | HU4: P030 | HV4: P031 | HW4: P032 | HX4: P033 | HY4: P034 | HZ4: P035 | IA4: P036 | IB4: P037 | IC4: P038 | ID4: P039 | IE4: P040 | IF4: P041 | IG4: P042 | IH4: P043 | II4: P044 | IJ4: P045 | IK4: P046 | IL4: P047 | IM4: P048 | IN4: P049 | IO4: P050 | IP4: P051 | IQ4: P052 | IR4: P053 | IS4: P054 | IT4: P055 | IU4: P056 | IV4: P057 | IW4: P058 | IX4: P059 | IY4: P060 | IZ4: B001 | JA4: B002 | JB4: B003 | JC4: B004 | JD4: B005 | JE4: B006 | JF4: B007 | JG4: B008 | JH4: B009 | JI4: B010 | JJ4: B011 | JK4: B012 | JL4: B013 | JM4: B014 | JN4: B015 | JO4: B016 | JP4: B017 | JQ4: B018 | JR4: B019 | JS4: B020 | JT4: M101 | JU4: M102 | JV4: M103 | JW4: M104 | JX4: M105 | JY4: M106 | JZ4: M107 | KA4: M108 | KB4: M109 | KC4: M110 | KD4: M111 | KE4: M112 | KF4: M113 | KG4: M114 | KH4: M115 | KI4: V801 | KJ4: V802 | KK4: V803 | KL4: V804 | KM4: V805 | KN4: V806 | KO4: V807 | KP4: V808 | KQ4: V809 | KR4: V810 | KS4: V811 | KT4: V812 | KU4: V813 | KV4: V814 | KW4: V815 | KX4: JB01 | KY4: JB02 | KZ4: JB03 | LA4: JB04 | LB4: JB05 | LC4: JB06 | LD4: JB07 | LE4: JB08 | LF4: S201 | LG4: S202 | LH4: S203 | LI4: S204 | LJ4: S205 | LK4: S206 | LL4: S207 | LM4: S208 | LN4: S209 | LO4: S210 | LP4: S211 | LQ4: S212 | LR4: S213 | LS4: S214 | LT4: S215 | LU4: D01 | LV4: D02 | LW4: D03 | LX4: D04 | LY4: D05 | LZ4: D06 | MA4: D07 | MB4: D08
A5: 46063 | B5: 30646.16 | C5: 8882.26 | D5: 8803.62 | E5: 7235.96 | F5: 1558.03 | G5: 6079.81 | H5: 4655.21 | I5: 980.57 | J5: 1195 | K5: 890.98 | L5: 977.65 | M5: 961.64 | N5: 2026.54 | O5: 896.51 | P5: 720.96 | Q5: 3347.08 | R5: 3658.46 | S5: 1650.23 | T5: 5200.2 | U5: 14802.31 | V5: 4267.94 | W5: 9627.92 | X5: 6861.35 | Y5: 2433.87 | Z5: 2123.87 | AA5: 2303.26 | AB5: 3527.92 | AC5: 1968.19 | AD5: 962.26 | AE5: 836.41 | AF5: 789593.68 | AG5: 5849.97 | AH5: 84659.29 | AI5: 1227.65 | AJ5: 996.93 | AK5: 1882.05 | AL5: 775.75 | AM5: 1075.11 | AN5: 592.35 | AO5: 582.01 | AP5: 532.32 | AQ5: 518.03 | AR5: 568.01 | AS5: 213.55 | AT5: 257.88 | AU5: 298.86 | AV5: 311.02 | AW5: 788.64 | AX5: 357.03 | AY5: 402.4 | AZ5: 283.21 | BA5: 150.61 | BB5: 193.77 | BC5: 202.07 | BD5: 199.03 | BE5: 189.85 | BF5: 80.57 | BG5: 54.17 | BH5: 433.1 | BI5: 120.01 | BJ5: 101.11 | BK5: 151.04 | BL5: 113.81 | BM5: 250.36 | BN5: 209.9 | BO5: 319.45 | BP5: 200.11 | BQ5: 158.6 | BR5: 969.66 | BS5: 305.48 | BT5: 330.73 | BU5: 314.31 | BV5: 178.84 | BW5: 235.55 | BX5: 226.4 | BY5: 275.56 | BZ5: 172.23 | CA5: 171 | CB5: 395.03 | CC5: 80.33 | CD5: 765.87 | CE5: 193.67 | CF5: 156.24 | CG5: 237.99 | CH5: 140.12 | CI5: 169.25 | CJ5: 178.69 | CK5: 127.22 | CL5: 315.12 | CM5: 248.24 | CN5: 414.79 | CO5: 337.62 | CP5: 208.09 | CQ5: 258.35 | CR5: 240.56 | CS5: 110.89 | CT5: 246.48 | CU5: 161.07 | CV5: 319.18 | CW5: 206.77 | CX5: 215.06 | CY5: 155.96 | CZ5: 134.75 | DA5: 3982.85 | DB5: 1007.86 | DC5: 1083.48 | DD5: 944.04 | DE5: 713.4 | DF5: 624.39 | DG5: 614.68 | DH5: 304.63 | DI5: 187.23 | DJ5: 112.18 | DK5: 36.59 | DL5: 957.35 | DM5: 1411.24 | DN5: 749.72 | DO5: 275.25 | DP5: 808.68 | DQ5: 484.12 | DR5: 295.73 | DS5: 186.18 | DT5: 883.2 | DU5: 1963.93 | DV5: 589.69 | DW5: 142.72 | DX5: 759.3 | DY5: 2743.7 | DZ5: 260.59 | EA5: 98.44 | EB5: 84.01 | EC5: 67.15 | ED5: 123.09 | EE5: 187.57 | EF5: 160.65 | EG5: 172.33 | EH5: 163.75 | EI5: 144.23 | EJ5: 174.71 | EK5: 241.63 | EL5: 145.02 | EM5: 141.96 | EN5: 74.28 | EO5: 88.13 | EP5: 62.49 | EQ5: 132.79 | ER5: 68.03 | ES5: 115.46 | ET5: 30.91 | EU5: 107.24 | EV5: 117.6 | EW5: 130.47 | EX5: 69.69 | EY5: 123.07 | EZ5: 134.93 | FA5: 23.82 | FB5: 51.64 | FC5: 57.56 | FD5: 311.59 | FE5: 35.78 | FF5: 67.67 | FG5: 193.43 | FH5: 209.33 | FI5: 340.4 | FJ5: 233.6 | FK5: 105.55 | FL5: 286.72 | FM5: 165.24 | FN5: 417.6 | FO5: 352.97 | FP5: 978.83 | FQ5: 79.79 | FR5: 247.2 | FS5: 479.52 | FT5: 8368.6 | FU5: 745.17 | FV5: 230.52 | FW5: 304.58 | FX5: 498.61 | FY5: 1189.38 | FZ5: 277.46 | GA5: 4029.15 | GB5: 1624.22 | GC5: 145.82 | GD5: 278.64 | GE5: 849.34 | GF5: 595.69 | GG5: 518.11 | GH5: 618.58 | GI5: 4256.12 | GJ5: 348.8 | GK5: 746.52 | GL5: 971.72 | GM5: 208.94 | GN5: 316.77 | GO5: 244.87 | GP5: 209.24 | GQ5: 282.97
A6: 46093 | B6: 31304.28 | C6: 9044.48 | D6: 8869.5 | E6: 7389.39 | F6: 1599.06 | G6: 6290.66 | H6: 4645.74 | I6: 1017.56 | J6: 1253.21 | K6: 912.4 | L6: 1025.85 | M6: 969.29 | N6: 2138 | O6: 897.58 | P6: 753.8 | Q6: 3505.24 | R6: 3795.97 | S6: 1692.98 | T6: 5322.93 | U6: 15973.25 | V6: 4456.77 | W6: 10364.87 | X6: 7411.71 | Y6: 2541.13 | Z6: 2172.58 | AA6: 2316.69 | AB6: 3762.9 | AC6: 2097.65 | AD6: 989.68 | AE6: 878.41 | AF6: 808933.77 | AG6: 6124.1 | AH6: 86064.56 | AI6: 1265.67 | AJ6: 1022.42 | AK6: 1785.46 | AL6: 700.18 | AM6: 1043.82 | AN6: 641.92 | AO6: 613.63 | AP6: 535.48 | AQ6: 547.52 | AR6: 598.11 | AS6: 214.45 | AT6: 263.51 | AU6: 298.97 | AV6: 321.85 | AW6: 786.04 | AX6: 370.56 | AY6: 426.47 | AZ6: 293.14 | BA6: 158.26 | BB6: 205.07 | BC6: 210.35 | BD6: 209.33 | BE6: 206.41 | BF6: 81.88 | BG6: 55.24 | BH6: 450.86 | BI6: 129.25 | BJ6: 104.55 | BK6: 161.2 | BL6: 117.77 | BM6: 253.19 | BN6: 221.67 | BO6: 345.88 | BP6: 206.19 | BQ6: 164.47 | BR6: 1033.06 | BS6: 328.18 | BT6: 342.57 | BU6: 330.22 | BV6: 188.05 | BW6: 253.84 | BX6: 233.81 | BY6: 284.05 | BZ6: 184.94 | CA6: 184.57 | CB6: 398.52 | CC6: 83.89 | CD6: 798 | CE6: 218.71 | CF6: 160.76 | CG6: 243.44 | CH6: 145.39 | CI6: 176.19 | CJ6: 190.27 | CK6: 129.66 | CL6: 332.33 | CM6: 253.82 | CN6: 424.7 | CO6: 350.11 | CP6: 213.24 | CQ6: 275.5 | CR6: 245.9 | CS6: 119.16 | CT6: 252.57 | CU6: 167 | CV6: 330.03 | CW6: 210.74 | CX6: 223.87 | CY6: 163.7 | CZ6: 140.07 | DA6: 4046.54 | DB6: 990.8 | DC6: 1094.43 | DD6: 972.88 | DE6: 741.78 | DF6: 651.83 | DG6: 634.36 | DH6: 320.75 | DI6: 195.85 | DJ6: 133.57 | DK6: 44.3 | DL6: 1065.78 | DM6: 1604.32 | DN6: 837.99 | DO6: 301.12 | DP6: 887.8 | DQ6: 534.9 | DR6: 316.33 | DS6: 211.13 | DT6: 966.3 | DU6: 1999.28 | DV6: 607.09 | DW6: 154.75 | DX6: 787.68 | DY6: 2890.39 | DZ6: 263.84 | EA6: 106.13 | EB6: 87.83 | EC6: 70.69 | ED6: 128.72 | EE6: 196.46 | EF6: 166.42 | EG6: 178.76 | EH6: 172.61 | EI6: 151.74 | EJ6: 188.24 | EK6: 261.52 | EL6: 148.37 | EM6: 150.03 | EN6: 78.46 | EO6: 95.2 | EP6: 66.65 | EQ6: 133.43 | ER6: 71.12 | ES6: 120.87 | ET6: 32.34 | EU6: 114.23 | EV6: 117.92 | EW6: 143.16 | EX6: 75.52 | EY6: 133.1 | EZ6: 152.27 | FA6: 25.76 | FB6: 56.56 | FC6: 60.36 | FD6: 330.93 | FE6: 37.8 | FF6: 69.91 | FG6: 202.99 | FH6: 216.64 | FI6: 355.7 | FJ6: 247.84 | FK6: 115.48 | FL6: 295.74 | FM6: 174.1 | FN6: 429.02 | FO6: 377.69 | FP6: 1017.3 | FQ6: 85.66 | FR6: 254.62 | FS6: 508.2 | FT6: 8669.56 | FU6: 761.23 | FV6: 243 | FW6: 332.23 | FX6: 524.67 | FY6: 1215.2 | FZ6: 286.28 | GA6: 4160.9 | GB6: 1713.45 | GC6: 153.63 | GD6: 300.89 | GE6: 891.86 | GF6: 637.09 | GG6: 536.92 | GH6: 652.02 | GI6: 4379.39 | GJ6: 359.02 | GK6: 775.3 | GL6: 1015.85 | GM6: 219.29 | GN6: 334.68 | GO6: 257.52 | GP6: 221.23 | GQ6: 300.07
A7: 46123 | B7: 31986.85 | C7: 9278.6 | D7: 9142.94 | E7: 7499.61 | F7: 1697.73 | G7: 6394.47 | H7: 4704.15 | I7: 1076.04 | J7: 1323.46 | K7: 920.9 | L7: 1035.94 | M7: 992.39 | N7: 2237.69 | O7: 920.56 | P7: 774.66 | Q7: 3614.72 | R7: 3973.98 | S7: 1753.29 | T7: 5386.49 | U7: 16504.3 | V7: 4655.22 | W7: 11099.96 | X7: 7760.94 | Y7: 2589.68 | Z7: 2274.81 | AA7: 2460.21 | AB7: 3848.23 | AC7: 2138.58 | AD7: 1042.2 | AE7: 895.9 | AF7: 815429.35 | AG7: 6204.72 | AH7: 90713.42 | AI7: 1346.79 | AJ7: 1054.17 | AK7: 1650.35 | AL7: 629.84 | AM7: 1009.54 | AN7: 655.76 | AO7: 641.61 | AP7: 558.52 | AQ7: 571.19 | AR7: 615.21 | AS7: 218.86 | AT7: 268.16 | AU7: 305.62 | AV7: 334.16 | AW7: 804.19 | AX7: 372.86 | AY7: 426.28 | AZ7: 300.14 | BA7: 163.7 | BB7: 209.72 | BC7: 224.45 | BD7: 215.93 | BE7: 222.23 | BF7: 85.6 | BG7: 57.47 | BH7: 485.85 | BI7: 130.93 | BJ7: 105.28 | BK7: 166.25 | BL7: 125.07 | BM7: 266.95 | BN7: 226.18 | BO7: 355.02 | BP7: 207.67 | BQ7: 173.75 | BR7: 1082.4 | BS7: 337.7 | BT7: 364.45 | BU7: 346.87 | BV7: 205.64 | BW7: 256.92 | BX7: 245.16 | BY7: 300.83 | BZ7: 197.43 | CA7: 189.48 | CB7: 395.94 | CC7: 85.86 | CD7: 850.77 | CE7: 233.24 | CF7: 168.79 | CG7: 259.62 | CH7: 152.15 | CI7: 189.54 | CJ7: 201.88 | CK7: 136.93 | CL7: 353.44 | CM7: 266.2 | CN7: 439.01 | CO7: 360.82 | CP7: 224.78 | CQ7: 289.93 | CR7: 262.22 | CS7: 127.81 | CT7: 262 | CU7: 173.62 | CV7: 352.75 | CW7: 222.17 | CX7: 231.9 | CY7: 168.96 | CZ7: 144.5 | DA7: 3999.78 | DB7: 980.53 | DC7: 1141.7 | DD7: 1031.86 | DE7: 794.61 | DF7: 669.18 | DG7: 647.62 | DH7: 343.48 | DI7: 207.93 | DJ7: 153.34 | DK7: 50.3 | DL7: 1207.47 | DM7: 1778.54 | DN7: 945.09 | DO7: 331.59 | DP7: 951.53 | DQ7: 567.93 | DR7: 344.65 | DS7: 231.82 | DT7: 1081.68 | DU7: 2124.6 | DV7: 591.52 | DW7: 164.17 | DX7: 807.48 | DY7: 2991.92 | DZ7: 273.99 | EA7: 112.82 | EB7: 88.89 | EC7: 72.59 | ED7: 133.11 | EE7: 208.13 | EF7: 168.27 | EG7: 187.97 | EH7: 178.47 | EI7: 160.18 | EJ7: 196.55 | EK7: 280.93 | EL7: 155.37 | EM7: 152.91 | EN7: 81.42 | EO7: 99.1 | EP7: 70.72 | EQ7: 137.18 | ER7: 71.02 | ES7: 125.65 | ET7: 33.54 | EU7: 117.82 | EV7: 123.83 | EW7: 159.36 | EX7: 79.02 | EY7: 146.45 | EZ7: 167.6 | FA7: 27.15 | FB7: 60.3 | FC7: 61.96 | FD7: 351.03 | FE7: 38.61 | FF7: 73.06 | FG7: 208.42 | FH7: 226.42 | FI7: 368.97 | FJ7: 262.12 | FK7: 125.56 | FL7: 308.66 | FM7: 173.55 | FN7: 446.82 | FO7: 397.51 | FP7: 1053.19 | FQ7: 90.41 | FR7: 265.6 | FS7: 540.97 | FT7: 8955.73 | FU7: 789.84 | FV7: 255.59 | FW7: 345.12 | FX7: 550 | FY7: 1264.13 | FZ7: 300.3 | GA7: 4236.05 | GB7: 1721.95 | GC7: 165.89 | GD7: 334.24 | GE7: 930.66 | GF7: 645.49 | GG7: 559.5 | GH7: 671.05 | GI7: 4460.77 | GJ7: 359.79 | GK7: 823.3 | GL7: 1054.8 | GM7: 226.34 | GN7: 352.82 | GO7: 266.2 | GP7: 226.97 | GQ7: 298.89
A8: 46146 | B8: 32360.48 | C8: 9551.49 | D8: 9491.39 | E8: 8057.48 | F8: 1776.57 | G8: 6519.85 | H8: 4820.96 | I8: 1072.31 | J8: 1371.66 | K8: 961.58 | L8: 1083.78 | M8: 1037.08 | N8: 2381.82 | O8: 943.72 | P8: 797.3 | Q8: 3751.42 | R8: 4174.69 | S8: 1770.47 | T8: 5371.18 | U8: 17956.63 | V8: 4841.33 | W8: 11854.23 | X8: 8447.4 | Y8: 2772.64 | Z8: 2407.46 | AA8: 2597.49 | AB8: 4181.4 | AC8: 2147.49 | AD8: 1088.44 | AE8: 934.66 | AF8: 844677.82 | AG8: 6358.21 | AH8: 93918.45 | AI8: 1391.1 | AJ8: 1099.05 | AK8: 1551.29 | AL8: 559.13 | AM8: 969.21 | AN8: 701.67 | AO8: 680.13 | AP8: 572.17 | AQ8: 618.71 | AR8: 629.58 | AS8: 220 | AT8: 281.04 | AU8: 320.06 | AV8: 344.11 | AW8: 797.77 | AX8: 370.83 | AY8: 444.46 | AZ8: 319.2 | BA8: 174.56 | BB8: 219.98 | BC8: 232.69 | BD8: 227.19 | BE8: 247.88 | BF8: 88.86 | BG8: 60.27 | BH8: 517.3 | BI8: 140.49 | BJ8: 110.27 | BK8: 178.38 | BL8: 128.04 | BM8: 277.12 | BN8: 240.96 | BO8: 369.16 | BP8: 220.02 | BQ8: 179.27 | BR8: 1168.12 | BS8: 348.29 | BT8: 367.89 | BU8: 379.99 | BV8: 219.82 | BW8: 280.87 | BX8: 258.18 | BY8: 314.6 | BZ8: 212.33 | CA8: 197.84 | CB8: 399.71 | CC8: 88.33 | CD8: 928.14 | CE8: 265.83 | CF8: 175.1 | CG8: 274.18 | CH8: 155.69 | CI8: 194.84 | CJ8: 211.56 | CK8: 137.41 | CL8: 372.63 | CM8: 279.11 | CN8: 453.26 | CO8: 377.88 | CP8: 239.93 | CQ8: 307.82 | CR8: 273.99 | CS8: 137.87 | CT8: 280.94 | CU8: 175 | CV8: 378.69 | CW8: 240.28 | CX8: 240.31 | CY8: 177.65 | CZ8: 148.63 | DA8: 4035.72 | DB8: 986.57 | DC8: 1184.42 | DD8: 1089.15 | DE8: 851.44 | DF8: 698.11 | DG8: 677.91 | DH8: 370.04 | DI8: 214.7 | DJ8: 189.27 | DK8: 61.68 | DL8: 1358.65 | DM8: 2131.38 | DN8: 1122.41 | DO8: 370.86 | DP8: 1087.31 | DQ8: 627.23 | DR8: 376.01 | DS8: 272.62 | DT8: 1274.22 | DU8: 2172.27 | DV8: 600.61 | DW8: 175.76 | DX8: 856.65 | DY8: 3152.4 | DZ8: 282.85 | EA8: 118.29 | EB8: 94.29 | EC8: 73.87 | ED8: 136.9 | EE8: 215.86 | EF8: 177.04 | EG8: 197.94 | EH8: 184.82 | EI8: 171.3 | EJ8: 218.92 | EK8: 307.56 | EL8: 156.07 | EM8: 162.32 | EN8: 84.33 | EO8: 109.62 | EP8: 79.53 | EQ8: 145.74 | ER8: 72.87 | ES8: 127.56 | ET8: 34.87 | EU8: 122.42 | EV8: 126.07 | EW8: 177.87 | EX8: 86.13 | EY8: 169.47 | EZ8: 193.43 | FA8: 29.18 | FB8: 67.02 | FC8: 63.98 | FD8: 368.46 | FE8: 40.21 | FF8: 78.18 | FG8: 221.55 | FH8: 233.23 | FI8: 381.02 | FJ8: 276.81 | FK8: 135.3 | FL8: 321.93 | FM8: 179.48 | FN8: 474.54 | FO8: 413.14 | FP8: 1088.44 | FQ8: 95.03 | FR8: 271.03 | FS8: 572.17 | FT8: 9400.78 | FU8: 849.85 | FV8: 275.94 | FW8: 373.17 | FX8: 580.98 | FY8: 1298.37 | FZ8: 321.39 | GA8: 4436.75 | GB8: 1750.66 | GC8: 173.64 | GD8: 362.41 | GE8: 959.09 | GF8: 673.81 | GG8: 567.59 | GH8: 716.09 | GI8: 4666.88 | GJ8: 371.28 | GK8: 836.68 | GL8: 1068.97 | GM8: 233.33 | GN8: 365.97 | GO8: 271.72 | GP8: 236.63 | GQ8: 318.5
A9: 46153 | B9: 32000 | C9: 9500 | D9: 9500 | E9: 8000 | F9: 1800 | G9: 6500 | H9: 4800 | I9: 1100 | J9: 1400 | K9: 950 | L9: 1100 | M9: 1050 | N9: 2400 | O9: 950 | P9: 800 | Q9: 3800 | R9: 4200 | S9: 1800 | T9: 5500 | U9: 18000 | V9: 5000 | W9: 12000 | X9: 8500 | Y9: 2800 | Z9: 2400 | AA9: 2600 | AB9: 4200 | AC9: 2200 | AD9: 1100 | AE9: 950 | AF9: 850000 | AG9: 6500 | AH9: 95000 | AI9: 1400 | AJ9: 1100 | AK9: 1500 | AL9: 550 | AM9: 950 | AN9: 720 | AO9: 680 | AP9: 580 | AQ9: 620 | AR9: 640 | AS9: 220 | AT9: 280 | AU9: 320 | AV9: 350 | AW9: 800 | AX9: 380 | AY9: 450 | AZ9: 320 | BA9: 180 | BB9: 220 | BC9: 240 | BD9: 230 | BE9: 250 | BF9: 90 | BG9: 60 | BH9: 520 | BI9: 140 | BJ9: 110 | BK9: 180 | BL9: 130 | BM9: 280 | BN9: 240 | BO9: 380 | BP9: 220 | BQ9: 180 | BR9: 1200 | BS9: 350 | BT9: 380 | BU9: 380 | BV9: 220 | BW9: 280 | BX9: 260 | BY9: 320 | BZ9: 220 | CA9: 200 | CB9: 400 | CC9: 90 | CD9: 950 | CE9: 280 | CF9: 180 | CG9: 280 | CH9: 160 | CI9: 200 | CJ9: 220 | CK9: 140 | CL9: 380 | CM9: 280 | CN9: 450 | CO9: 380 | CP9: 240 | CQ9: 320 | CR9: 280 | CS9: 140 | CT9: 280 | CU9: 180 | CV9: 380 | CW9: 240 | CX9: 240 | CY9: 180 | CZ9: 150 | DA9: 4000 | DB9: 1000 | DC9: 1200 | DD9: 1100 | DE9: 850 | DF9: 720 | DG9: 680 | DH9: 380 | DI9: 220 | DJ9: 200 | DK9: 65 | DL9: 1400 | DM9: 2200 | DN9: 1150 | DO9: 380 | DP9: 1100 | DQ9: 640 | DR9: 380 | DS9: 280 | DT9: 1300 | DU9: 2200 | DV9: 600 | DW9: 180 | DX9: 850 | DY9: 3200 | DZ9: 290 | EA9: 120 | EB9: 95 | EC9: 75 | ED9: 140 | EE9: 220 | EF9: 180 | EG9: 200 | EH9: 190 | EI9: 175 | EJ9: 220 | EK9: 320 | EL9: 160 | EM9: 165 | EN9: 85 | EO9: 110 | EP9: 80 | EQ9: 145 | ER9: 75 | ES9: 130 | ET9: 35 | EU9: 125 | EV9: 130 | EW9: 180 | EX9: 90 | EY9: 175 | EZ9: 200 | FA9: 30 | FB9: 70 | FC9: 65 | FD9: 380 | FE9: 40 | FF9: 80 | FG9: 220 | FH9: 240 | FI9: 380 | FJ9: 280 | FK9: 140 | FL9: 320 | FM9: 180 | FN9: 480 | FO9: 420 | FP9: 1100 | FQ9: 95 | FR9: 280 | FS9: 580 | FT9: 9500 | FU9: 850 | FV9: 280 | FW9: 380 | FX9: 580 | FY9: 1300 | FZ9: 320 | GA9: 4500 | GB9: 1800 | GC9: 180 | GD9: 380 | GE9: 950 | GF9: 680 | GG9: 580 | GH9: 720 | GI9: 4800 | GJ9: 380 | GK9: 850 | GL9: 1100 | GM9: 240 | GN9: 380 | GO9: 280 | GP9: 240 | GQ9: 320
A10: 46155 | B10: 32000 | C10: 9500 | D10: 9500 | E10: 8000 | F10: 3126 | G10: 6500 | H10: 4800 | I10: 1100 | J10: 1400 | K10: 950 | L10: 1100 | M10: 1050 | N10: 2400 | O10: 950 | P10: 800 | Q10: 3800 | R10: 4200 | S10: 1800 | T10: 5500 | U10: 18000 | V10: 5000 | W10: 12000 | X10: 8500 | Y10: 2800 | Z10: 2400 | AA10: 2600 | AB10: 4200 | AC10: 2200 | AD10: 1100 | AE10: 950 | AF10: 850000 | AG10: 6500 | AH10: 95000 | AI10: 1400 | AJ10: 1100 | AK10: 4480 | AL10: 2100 | AM10: 1480 | AN10: 1200 | AO10: 1100 | AP10: 900 | AQ10: 1000 | AR10: 980 | AS10: 480 | AT10: 540 | AU10: 520 | AV10: 620 | AW10: 1100 | AX10: 580 | AY10: 680 | AZ10: 520 | BA10: 320 | BB10: 380 | BC10: 390 | BD10: 380 | BE10: 440 | BF10: 160 | BG10: 110 | BH10: 820 | BI10: 240 | BJ10: 190 | BK10: 300 | BL10: 220 | BM10: 450 | BN10: 380 | BO10: 580 | BP10: 340 | BQ10: 280 | BR10: 1900 | BS10: 350 | BT10: 640 | BU10: 640 | BV10: 380 | BW10: 480 | BX10: 440 | BY10: 540 | BZ10: 380 | CA10: 340 | CB10: 700 | CC10: 90 | CD10: 1500 | CE10: 280 | CF10: 320 | CG10: 480 | CH10: 280 | CI10: 340 | CJ10: 380 | CK10: 240 | CL10: 640 | CM10: 480 | CN10: 740 | CO10: 640 | CP10: 400 | CQ10: 540 | CR10: 480 | CS10: 240 | CT10: 480 | CU10: 300 | CV10: 640 | CW10: 400 | CX10: 400 | CY10: 300 | CZ10: 260 | DA10: 5200 | DB10: 1300 | DC10: 1500 | DD10: 1400 | DE10: 1080 | DF10: 920 | DG10: 860 | DH10: 480 | DI10: 280 | DJ10: 320 | DK10: 65 | DL10: 1800 | DM10: 3000 | DN10: 1480 | DO10: 480 | DP10: 1400 | DQ10: 820 | DR10: 480 | DS10: 280 | DT10: 1700 | DU10: 2800 | DV10: 600 | DW10: 240 | DX10: 1100 | DY10: 3200 | DZ10: 290 | EA10: 120 | EB10: 95 | EC10: 75 | ED10: 140 | EE10: 220 | EF10: 180 | EG10: 200 | EH10: 190 | EI10: 175 | EJ10: 220 | EK10: 320 | EL10: 160 | EM10: 165 | EN10: 85 | EO10: 110 | EP10: 80 | EQ10: 145 | ER10: 75 | ES10: 130 | ET10: 35 | EU10: 125 | EV10: 130 | EW10: 180 | EX10: 90 | EY10: 175 | EZ10: 200 | FA10: 30 | FB10: 70 | FC10: 65 | FD10: 380 | FE10: 40 | FF10: 80 | FG10: 220 | FH10: 240 | FI10: 380 | FJ10: 280 | FK10: 140 | FL10: 320 | FM10: 180 | FN10: 480 | FO10: 420 | FP10: 1100 | FQ10: 95 | FR10: 280 | FS10: 580 | FT10: 9500 | FU10: 850 | FV10: 280 | FW10: 380 | FX10: 580 | FY10: 1300 | FZ10: 320 | GA10: 4500 | GB10: 1800 | GC10: 180 | GD10: 380 | GE10: 950 | GF10: 680 | GG10: 580 | GH10: 720 | GI10: 4800 | GJ10: 380 | GK10: 850 | GL10: 1100 | GM10: 240 | GN10: 380 | GO10: 360 | GP10: 320 | GQ10: 440 | GR10: 4 | GS10: 6 | GT10: 8 | GU10: 9 | GV10: 7 | GW10: 8 | GX10: 5 | GY10: 4 | GZ10: 6 | HA10: 5 | HB10: 5 | HC10: 4 | HD10: 4 | HE10: 5 | HF10: 6 | HG10: 4 | HH10: 7 | HI10: 8 | HJ10: 3 | HK10: 5 | HL10: 2 | HM10: 2 | HN10: 2 | HO10: 2 | HP10: 3 | HQ10: 6 | HR10: 5 | HS10: 4 | HT10: 5 | HU10: 9 | HV10: 8 | HW10: 8 | HX10: 7 | HY10: 9 | HZ10: 30 | IA10: 5 | IB10: 6 | IC10: 8 | ID10: 9 | IE10: 6 | IF10: 4 | IG10: 5 | IH10: 5 | II10: 6 | IJ10: 4 | IK10: 5 | IL10: 4 | IM10: 5 | IN10: 5 | IO10: 5 | IP10: 6 | IQ10: 8 | IR10: 5 | IS10: 5 | IT10: 6 | IU10: 7 | IV10: 9 | IW10: 8 | IX10: 6 | IY10: 8 | IZ10: 15 | JA10: 25 | JB10: 18 | JC10: 35 | JD10: 28 | JE10: 22 | JF10: 12 | JG10: 18 | JH10: 28 | JI10: 35 | JJ10: 28 | JK10: 18 | JL10: 22 | JM10: 35 | JN10: 20 | JO10: 25 | JP10: 25 | JQ10: 20 | JR10: 15 | JS10: 32 | JT10: 80 | JU10: 65 | JV10: 90 | JW10: 75 | JX10: 70 | JY10: 65 | JZ10: 120 | KA10: 85 | KB10: 95 | KC10: 130 | KD10: 70 | KE10: 95 | KF10: 60 | KG10: 85 | KH10: 55 | KI10: 700 | KJ10: 280 | KK10: 250 | KL10: 180 | KM10: 220 | KN10: 90 | KO10: 130 | KP10: 380 | KQ10: 180 | KR10: 110 | KS10: 280 | KT10: 2800 | KU10: 950 | KV10: 2200 | KW10: 880 | KX10: 18 | KY10: 14 | KZ10: 12 | LA10: 25 | LB10: 14 | LC10: 8 | LD10: 18 | LE10: 15 | LF10: 28 | LG10: 15 | LH10: 18 | LI10: 12 | LJ10: 18 | LK10: 80 | LL10: 22 | LM10: 45 | LN10: 55 | LO10: 50 | LP10: 60 | LQ10: 70 | LR10: 75 | LS10: 135 | LT10: 40 | LU10: 40 | LV10: 38 | LW10: 55 | LX10: 18 | LY10: 90 | LZ10: 55 | MA10: 65 | MB10: 50
A11: 46154 | B11: X101 | C11: Iono's Bellibolt ex IR | D11: Journey Together | E11: Raw NM | F11: 9
A12: 46154 | B12: X102 | C12: N's Zorua IR | D12: Journey Together | E12: Raw NM | F12: 6
A13: 46154 | B13: X103 | C13: N's Reshiram Full Art | D13: Journey Together | E13: Raw NM | F13: 12
A14: 46154 | B14: X104 | C14: N's Zekrom Full Art | D14: Journey Together | E14: Raw NM | F14: 12
A15: 46154 | B15: X105 | C15: Bianca's Devotion Full Art | D15: Journey Together | E15: Raw NM | F15: 9
A16: 46154 | B16: X106 | C16: Cilan & Chili & Cress IR | D16: Journey Together | E16: Raw NM | F16: 7
A17: 46154 | B17: X107 | C17: Hilbert FA Trainer | D17: Journey Together | E17: Raw NM | F17: 8
A18: 46154 | B18: X108 | C18: Iris's Haxorus IR | D18: Journey Together | E18: Raw NM | F18: 10
A19: 46154 | B19: X109 | C19: Bianca's Roserade IR | D19: Journey Together | E19: Raw NM | F19: 6
A20: 46154 | B20: X110 | C20: Cheren's Stoutland IR | D20: Journey Together | E20: Raw NM | F20: 5
A21: 46154 | B21: X111 | C21: Pikachu ex SIR (raw) | D21: Surging Sparks | E21: Raw NM | F21: 14
A22: 46154 | B22: X112 | C22: Latias ex SIR (raw) | D22: Surging Sparks | E22: Raw NM | F22: 10
... A345: 46154 | B345: V274 | C345: Gyarados PSA 10 | D345: Base Set Unlimited | E345: PSA 10 | F345: 850

Sheet eBay Sold Comps
B2: eBay SOLD COMPS — Real Transaction Prices
B3: Populated by ebay_solds.py companion script. Avg of last 30 days actual closed sales per CardID.
B5: CardID | C5: Card Name | D5: Avg Sold (30D) | E5: Min Sold | F5: Max Sold | G5: # Sales | H5: Last Updated | I5: eBay Search URL
B6: V001 | C6: Charizard | I6: https://www.ebay.com/sch/i.html?_nkw=Charizard+Base+Set+1st+Edition+Shadowless+4/102+PSA+9&LH_Sold=1&LH_Complete=1&_sop=13
B7: V002 | C7: Charizard | I7: https://www.ebay.com/sch/i.html?_nkw=Charizard+Base+Set+1st+Edition+Shadowless+4/102+PSA+8&LH_Sold=1&LH_Complete=1&_sop=13
B8: V003 | C8: Charizard | I8: https://www.ebay.com/sch/i.html?_nkw=Charizard+Base+Set+Shadowless+4/102+PSA+9&LH_Sold=1&LH_Complete=1&_sop=13
B9: V004 | C9: Charizard | I9: https://www.ebay.com/sch/i.html?_nkw=Charizard+Base+Set+Unlimited+4/102+PSA+10&LH_Sold=1&LH_Complete=1&_sop=13
B10: V005 | C10: Charizard | I10: https://www.ebay.com/sch/i.html?_nkw=Charizard+Base+Set+Unlimited+4/102+PSA+9&LH_Sold=1&LH_Complete=1&_sop=13
B11: V006 | C11: Blastoise | I11: https://www.ebay.com/sch/i.html?_nkw=Blastoise+Base+Set+1st+Edition+Shadowless+2/102+PSA+9&LH_Sold=1&LH_Complete=1&_sop=13
B12: V007 | C12: Venusaur | I12: https://www.ebay.com/sch/i.html?_nkw=Venusaur+Base+Set+1st+Edition+Shadowless+15/102+PSA+9&LH_Sold=1&LH_Complete=1&_sop=13
B13: V008 | C13: Chansey | I13: https://www.ebay.com/sch/i.html?_nkw=Chansey+Base+Set+1st+Edition+3/102+PSA+9&LH_Sold=1&LH_Complete=1&_sop=13
B14: V009 | C14: Mewtwo | I14: https://www.ebay.com/sch/i.html?_nkw=Mewtwo+Base+Set+1st+Edition+10/102+PSA+9&LH_Sold=1&LH_Complete=1&_sop=13
B15: V010 | C15: Alakazam | I15: https://www.ebay.com/sch/i.html?_nkw=Alakazam+Base+Set+1st+Edition+1/102+PSA+9&LH_Sold=1&LH_Complete=1&_sop=13
B16: V011 | C16: Ninetales | I16: https://www.ebay.com/sch/i.html?_nkw=Ninetales+Base+Set+1st+Edition+12/102+PSA+9&LH_Sold=1&LH_Complete=1&_sop=13
B17: V012 | C17: Zapdos | I17: https://www.ebay.com/sch/i.html?_nkw=Zapdos+Base+Set+1st+Edition+16/102+PSA+9&LH_Sold=1&LH_Complete=1&_sop=13
... B203: X020 | C203: Mewtwo and Mew GX Hidden Fates | I203: https://www.ebay.com/sch/i.html?_nkw=Mewtwo+and+Mew+GX+Hidden+Fates+Hidden+Fates+SM196+PSA+10&LH_Sold=1&LH_Complete=1&_sop=13

Sheet Refresh URLs
B2: REFRESH URLs
B3: Per-set URLs for Power Query / manual refresh. PriceCharting set pages expose 'Download Price List' CSV.
B5: Set | C5: PriceCharting URL | D5: Notes
B6: Base Set | C6: https://www.pricecharting.com/console/pokemon-base-set | D6: WOTC core
B7: Jungle | C7: https://www.pricecharting.com/console/pokemon-jungle
B8: Fossil | C8: https://www.pricecharting.com/console/pokemon-fossil
B9: Team Rocket | C9: https://www.pricecharting.com/console/pokemon-team-rocket
B10: Gym Heroes | C10: https://www.pricecharting.com/console/pokemon-gym-heroes
B11: Neo Genesis | C11: https://www.pricecharting.com/console/pokemon-neo-genesis
B12: Neo Destiny | C12: https://www.pricecharting.com/console/pokemon-neo-destiny
B13: Neo Revelation | C13: https://www.pricecharting.com/console/pokemon-neo-revelation
B14: EX Dragon Frontiers | C14: https://www.pricecharting.com/console/pokemon-dragon-frontiers | D14: Gold Stars
B15: EX Power Keepers | C15: https://www.pricecharting.com/console/pokemon-ex-power-keepers | D15: Eevee Gold Stars
B16: EX Crystal Guardians | C16: https://www.pricecharting.com/console/pokemon-ex-crystal-guardians | D16: Delta Species
B17: EX Holon Phantoms | C17: https://www.pricecharting.com/console/pokemon-ex-holon-phantoms | D17: Mew Gold Star
B18: EX Deoxys | C18: https://www.pricecharting.com/console/pokemon-ex-deoxys | D18: Rayquaza Gold Star
B19: POP Series 5 | C19: https://www.pricecharting.com/console/pokemon-pop-series-5 | D19: Umbreon/Espeon Gold Star
B20: Skyridge | C20: https://www.pricecharting.com/console/pokemon-skyridge | D20: Crystal Charizard
B21: Flashfire | C21: https://www.pricecharting.com/console/pokemon-flashfire | D21: M Charizard EX
B22: Roaring Skies | C22: https://www.pricecharting.com/console/pokemon-roaring-skies | D22: M Rayquaza EX
B23: Hidden Fates | C23: https://www.pricecharting.com/console/pokemon-hidden-fates | D23: Tag Team shinies
B24: Champion's Path | C24: https://www.pricecharting.com/console/pokemon-champion's-path | D24: Rainbow Char VMAX
B25: Brilliant Stars | C25: https://www.pricecharting.com/console/pokemon-brilliant-stars | D25: Char VSTAR
... B38: Stellar Crown | C38: https://www.pricecharting.com/console/pokemon-stellar-crown | D38: Terapagos
B39: Surging Sparks | C39: https://www.pricecharting.com/console/pokemon-surging-sparks
B40: Prismatic Evolutions | C40: https://www.pricecharting.com/console/pokemon-prismatic-evolutions | D40: PE Eevee SIRs
B41: Journey Together | C41: https://www.pricecharting.com/console/pokemon-journey-together | D41: Marnie
B42: Mega Evolution (ME01) | C42: https://www.pricecharting.com/console/pokemon-mega-evolution | D42: Lillie's SIR
B43: Ascended Heroes (ME2.5) | C43: https://www.pricecharting.com/console/pokemon-ascended-heroes | D43: Mega Gengar
B44: Pokemon Promos | C44: https://www.pricecharting.com/console/pokemon-promo | D44: Van Gogh, Pokemon Day, Birthday
B45: Japanese — Eevee Heroes | C45: https://www.pricecharting.com/console/pokemon-japanese-eevee-heroes | D45: JP Moonbreon
B46: Japanese — VMAX Climax | C46: https://www.pricecharting.com/console/pokemon-japanese-vmax-climax | D46: JP CHR/CSR
B47: Japanese — VSTAR Universe | C47: https://www.pricecharting.com/console/pokemon-japanese-vstar-universe | D47: JP high-class
B48: Japanese — Paradigm Trigger | C48: https://www.pricecharting.com/console/pokemon-japanese-paradigm-trigger | D48: JP Lugia
B50: TCGPlayer Pokemon Hub | C50: https://www.tcgplayer.com/categories/trading-and-collectible-card-games/pokemon/price-guides | D50: All set price guides
B51: PokemonPriceTracker API | C51: https://www.pokemonpricetracker.com/api | D51: Free tier: 100 calls/day
B52: PSA Pop Reports | C52: https://www.psacard.com/pop | D52: Population tracking
B53: 130point.com Sold Comps | C53: https://130point.com | D53: Real eBay solds

Sheet Research Notes
B2: RESEARCH NOTES & STRATEGY PLAYBOOK
B5: MOMENTUM-LEAN STRATEGY
B6: 40% Modern Chase / 30% Sealed Modern / 15% Vintage Graded / 10% Grading Pipeline / 5% Cash
B8: QUANT SIGNALS
B9: STRONG BUY (75+) | BUY (60-75) | HOLD (40-60) | TRIM (25-40) | SELL (<25)
B11: WEEKLY WORKFLOW
B12: Mon 7AM PT: run refresh_prices.py; check Weekly Buy List; bid at Target Buy
B13: Wed/Thu: PSA submissions, list outgoing
B14: Fri/Sat: monitor eBay closings; local card shop visits
B16: DO NOT BUY
B17: In-print modern at premium; CGC modern; resealed boxes; <25 score; JP without provenance
B19: OPERATIONAL
B20: CA LLC + Seller's Permit; biz checking; PSA Collector's Club; insurance rider; CPA

Sheet Sources
B2: RESEARCH SOURCES
B4: Source | C4: URL
B5: PokeTracker Investment Guide 2026 | C5: https://pokemoncardvalue.io/blog/best-pokemon-cards-to-invest-2026.html
B6: TCGrader Best 2026 | C6: https://www.tcgrader.com/blog/best-pokemon-cards-invest-2026
B7: Athlon Mega Evolution | C7: https://athlonsports.com/collectibles/pokemon-tcg-investing-2026-mega-evolution
B8: Hall of Cards Jan 2026 | C8: https://hallofcards.app/blog-posts/pokemon-card-market-report-january-2026
B9: Misprint ES Box 2026 | C9: https://www.misprint.com/posts/evolving-skies-booster-box-price-2026
B10: Cardrake Mega Gengar AH | C10: https://www.cardrake.com/cards/me2pt5-284
B11: PriceCharting PE Umbreon | C11: https://www.pricecharting.com/game/pokemon-prismatic-evolutions/umbreon-ex-161
B12: PPT PE Review 2026 | C12: https://www.pokemonpricetracker.com/blog/posts/prismatic-evolutions-set-review-2026-complete-guide
B13: CardsNPacks Char 1st Ed 2026 | C13: https://www.cardsnpacks.com/en/blog/evolution-prix-dracaufeu/
B14: PriceCharting API | C14: https://www.pricecharting.com/api-documentation
B15: PokemonPriceTracker API | C15: https://www.pokemonpricetracker.com/pokemon-card-price-api
... B17: 130point Sold Comps | C17: https://130point.com

Sheet Personal Trades
A1: 🔄 PERSONAL TRADE LOG
A3: Date | B3: Type | C3: Cards In | D3: Cards Out / Cash Paid | E3: Value In $ | F3: Value Out $ | G3: Net Gain $ | H3: Platform / Partner | I3: Condition | J3: Grade Result | K3: Strategy / Notes
B4: Slab | C4: 2016 X&Y Umbreon EX Fates Collide | E4: 100 | F4: 300 | G4: -200 | I4: 9 | J4: 9 | K4: 300
B5: Slab | C5: 2022 SWSH Charizard V Brilliant Stars | E5: 100 | F5: 340 | G5: -240 | I5: 9 | J5: 9 | K5: 340
B6: Slab | C6: 2024 SVP Pikachu Paldea Adventure Chest | E6: 25 | F6: 40 | G6: -15 | I6: 9 | J6: 9 | K6: 40
B7: Slab | C7: 2020 SM Black Star Umbreon/Darkrai GX Promo | E7: 100 | F7: 190 | G7: -90 | I7: 8 | J7: 8 | K7: 190
B8: Slab | C8: 2025 M2 JP Mega Charizard X Ex | E8: 25 | F8: 50 | G8: -25 | I8: 10 | J8: 10 | K8: 50
B9: Slab | C9: 2021 Celebratrions FA/Pikachu | E9: 25 | F9: 31 | G9: -6 | I9: 8 | J9: 8 | K9: 31
B10: Slab | C10: 2025 SV-P JP Pikachu Gym Event Campaign | E10: 25 | F10: 90 | G10: -65 | I10: 10 | J10: 10 | K10: 90
B11: Slab | C11: 1999 Fossil Muk-Holo 1st Edition | E11: 25 | F11: 65 | G11: -40 | I11: 7 | J11: 7 | K11: 65
B12: Slab | C12: 2020 SWSH FA/Pikachu VMAX Vivid Voltage - Secret | E12: 100 | F12: 370 | G12: -270 | I12: 10 | J12: 10 | K12: 370
B13: Slab | C13: 2022 CGC Electivire VSTAR Universe 180 | E13: 25 | F13: 30 | G13: -5 | I13: 9.5 | J13: 9.5 | K13: 30
B14: Slab | C14: Burger Pikachu Slab (eBay) | E14: 120 | F14: 108 | G14: -12 | K14: 108
B15: TOTAL SLAB | C15: TOTAL SLABS: | E15: 550 | F15: 1506 | G15: -956 | K15: 1614
B16: RAW - Full Art | C16: Phantasmal Flames Piplup | F16: 18 | G16: 18 | K16: 18
B17: RAW - Full Art | C17: Perfect Order Promo Tyrunt | F17: 5 | G17: 5 | K17: 5
B18: RAW - Full Art | C18: Perfect Order Jacinthe | F18: 6 | G18: 6 | K18: 6
B19: RAW - Full Art | C19: perfect Order Drapion | F19: 2 | G19: 2 | K19: 2
B20: RAW - Full Art | C20: Phantasmal Flames Yamper | F20: 4 | G20: 4 | K20: 4
B21: RAW - Full Art | C21: Phantasmal Flames Zacian | F21: 4 | G21: 4 | K21: 4
B22: RAW - Full Art | C22: Phantasmal Flames Firebreather | F22: 2 | G22: 2 | K22: 2
B23: RAW - Full Art | C23: Black Bolt Musharna | F23: 8 | G23: 8 | K23: 8
B24: RAW - Full Art | C24: Perfect Order Aurorus | F24: 5 | G24: 5 | K24: 5
B25: RAW - Full Art | C25: SV Cynthia's Garchomp EX | F25: 5 | G25: 5 | K25: 5
B26: RAW - Full Art | C26: Paradox Rift Toxtricity EX | F26: 3 | G26: 3 | K26: 3
B27: RAW - Full Art | C27: Perfect Order Rosa's Encouragmeent | F27: 15 | G27: 15 | K27: 15
... B49: TOTAL RAWS | C49: Brilliant Stars Raichu V | F49: 3 | G49: 3 | K49: 3
C50: TOTAL OF CARDS FROM RIPS | F50: 483 | G50: 483 | K50: 483
B51: SEALED | C51: Ascended Heroes ETB 1 | E51: 60 | F51: 180 | G51: 120 | K51: 120
B52: SEALED | C52: Ascended Heroes ETB 2 | E52: 60 | F52: 180 | G52: 120 | K52: 120
B53: SEALED | C53: Prismatic Evolutions ETB | E53: 60 | F53: 160 | G53: 100 | K53: 100
B54: SEALED | C54: Ascended Hereos Booster Bundle 1 | E54: 47 | F54: 86 | G54: 39 | K54: 39
B55: SEALED | C55: Ascended Heroes Booster Bundle 2 | E55: 47 | F55: 86 | G55: 39 | K55: 39
B56: SEALED | C56: Mega Fraligatr Ascended Heroes Bundle 1 | E56: 26 | F56: 55 | G56: 29 | K56: 29
B57: SEALED | C57: Mega Fraligatr Ascended Heroes Bundle 2 | E57: 26 | F57: 55 | G57: 29 | K57: 29
B58: SEALED | C58: Chaos Rising PTC ETB 1 | E58: 60 | F58: 200 | G58: 140 | K58: 140
B59: SEALED | C59: Chaos Rising PTC ETB 2 | E59: 60 | F59: 200 | G59: 140 | K59: 140
B60: SEALED | C60: Chaos Rising PTC ETB 3 | E60: 60 | F60: 200 | G60: 140 | K60: 140
B61: SEALED | C61: Chaos Rising PTC ETB 4 | E61: 60 | F61: 200 | G61: 140 | K61: 140
B62: SEALED | C62: Chaos Rising Booster Bundle 1 | E62: 25 | F62: 60 | G62: 35 | K62: 35
... B64: SEALED | C64: Chaos Rising Booster Box | E64: 164 | F64: 238 | G64: 74 | K64: 74
C65: TOTAL OF SEALED | E65: 780 | F65: 1960 | G65: 1180 | K65: 1180
B66: SINGLES | C66: SV: Scarlet & Violet Pikachu 173 | E66: 81 | F66: 71 | G66: -10 | K66: 71
B67: SINGLES | C67: Crown Zenith Regigigas | E67: 25 | F67: 25 | G67: 0 | K67: 25
B68: SINGLES | C68: Crown Zenith Mew | E68: 65 | F68: 71 | G68: 6 | K68: 71
B69: SINGLES | C69: Angry Charmander PROMO 044 | E69: 65 | F69: 72 | G69: 7 | K69: 72
B70: SINGLES | C70: Lost Origin Promo Pikachu + Dawn | E70: 55 | F70: 60 | G70: 5 | K70: 60
B71: SINGLES | C71: SWSH Arceus V Promo | E71: 20 | F71: 24 | G71: 4 | K71: 24
B72: SINGLES | C72: Crown Zenith Arceus Vstar | E72: 150 | F72: 165 | G72: 15 | K72: 165
B73: SINGLES | C73: 151 Charmander | E73: 110 | F73: 105 | G73: -5 | K73: 105
B74: SINGLES | C74: SV: Scarlet & Violet Pikachu Promo 027 | E74: 20 | F74: 22 | G74: 2 | K74: 22
C75: TOTAL OF SINGLES PURCHASED | E75: 591 | F75: 615 | G75: 24 | K75: 615
B76: RIP | C76: Ascended Hero ETB | E76: 120 | F76: 180 | G76: 60 | K76: 120
B77: RIP | C77: Black Bolt + White Flare box | E77: 90 | F77: 90 | G77: 0 | K77: 90
B78: RIP | C78: First illustration Box x2 | E78: 40.45 | F78: 102 | G78: 61.55 | K78: 40.45
B79: RIP | C79: First illustration Box x2 | E79: 40.45 | F79: 102 | G79: 61.55 | K79: 40.45
B80: RIP | C80: Ascended Heroes Pin Collection (Card Shop) | E80: 50 | F80: 58 | G80: 8 | K80: 50
B81: RIP | C81: Perfect Order ETB (Gamestop) | E81: 75 | F81: 60 | G81: -15 | K81: 75
B82: RIP | C82: Perfect Order Booster Box (Gamestop) | E82: 60 | F82: 40 | G82: -20 | K82: 60
B83: RIP | C83: Perfect Order Booster Box (brandon) | E83: 40 | F83: 40 | G83: 0 | K83: 40
B84: RIP | C84: Perfect Order Booster Packs x4 (Dicks) | E84: 24 | F84: 24 | G84: 0 | K84: 24
B85: RIP | C85: Perfect Order Booster Box (from Andy?) | E85: 40 | F85: 40 | G85: 0 | K85: 40
B86: RIP | C86: Destined Rivals Booster Bundle (Card Shop) | E86: 60 | F86: 70 | G86: 10 | K86: 60
B87: RIP | C87: Darkrai Tin (CVS) x2 | E87: 50 | F87: 50 | G87: 0 | K87: 50
... B93: RIP | C93: Phantasmal Flames ETB | E93: 110 | F93: 130 | G93: 20 | K93: 110
C94: ESTIMATE* TOTAL OF RIPS SPENT | E94: 1023.16 | F94: 1318 | G94: 274.84 | K94: 1023.16

Sheet Hunt List
A1: 🎯 HUNT LIST — Cards we want to acquire
A3: Card Name | B3: Set | C3: Year | D3: Card # | E3: Era / Type | F3: Raw NM ($) | G3: PSA 10 ($) | H3: PSA 9 ($) | I3: Notes
A4: ◆ 🔥 TIER S — $1,000+ Raw / $5,000+ PSA 10
A5: Charizard 1st Ed Holo #4 | B5: Base Set – 1st Edition | C5: 1999 | D5: 4/102 | E5: Vintage WOTC | F5: 7000 | G5: 25000 | H5: 8000 | I5: ⚠️ MARGINAL
A6: Charizard Shadowless Holo | B6: Base Set – Shadowless | C6: 1999 | D6: 4/102 | E6: Vintage WOTC | F6: 3000 | G6: 15000 | H6: 5000 | I6: ✅ GRADE IT
A7: Mega Gengar ex SIR #284 | B7: Ascended Heroes | C7: 2026 | D7: 284/217 | E7: Modern SIR | F7: 1000 | G7: 3000 | H7: 1100 | I7: ⚠️ MARGINAL
A8: Mega Charizard Y ex HR | B8: Ascended Heroes | C8: 2026 | D8: 294/217 | E8: Hyper Rare | F8: 800 | G8: 2500 | H8: 900 | I8: ⚠️ MARGINAL
A9: ◆ ⭐ TIER A — $300–$1,000 Raw
A10: Umbreon VMAX Alt Art | B10: Evolving Skies | C10: 2021 | D10: 215/203 | E10: SWSH Alt Art | F10: 350 | G10: 950 | H10: 350 | I10: ❌ DON'T GRADE
A11: Charizard ex SIR | B11: Paldean Evolved | C11: 2023 | D11: 241/193 | E11: Modern SIR | F11: 180 | G11: 700 | H11: 250 | I11: ⚠️ MARGINAL
A12: Mega Dragonite ex SIR #290 | B12: Ascended Heroes | C12: 2026 | D12: 290/217 | E12: Modern SIR | F12: 700 | G12: 2000 | H12: 700 | I12: ⚠️ MARGINAL
A13: Rayquaza VMAX Alt Art | B13: Evolving Skies | C13: 2021 | D13: 218/203 | E13: SWSH Alt Art | F13: 250 | G13: 800 | H13: 300 | I13: ⚠️ MARGINAL
A14: Charizard ex SIR | B14: Obsidian Flames | C14: 2023 | D14: 234/197 | E14: Modern SIR | F14: 200 | G14: 650 | H14: 225 | I14: ❌ DON'T GRADE
A15: Lugia V Alt Art | B15: Silver Tempest | C15: 2022 | D15: 211/195 | E15: SWSH Alt Art | F15: 200 | G15: 600 | H15: 200 | I15: ❌ DON'T GRADE
A16: Giratina VSTAR Alt Art | B16: Lost Origin | C16: 2022 | D16: 201/196 | E16: SWSH Alt Art | F16: 150 | G16: 500 | H16: 175 | I16: ❌ DON'T GRADE
A17: Snorlax SIR | B17: Surging Sparks | C17: 2024 | D17: — | E17: Modern SIR | F17: 300 | G17: 1500 | H17: 450 | I17: ✅ GRADE IT
A18: ◆ 💰 TIER B — $100–$300 Raw (Best Flip Zone)
A19: Giratina V Alt Art | B19: Lost Origin | C19: 2022 | D19: 182/196 | E19: SWSH Alt Art | F19: 120 | G19: 450 | H19: 160 | I19: ⚠️ MARGINAL
A20: Charizard V Alt Art | B20: Brilliant Stars | C20: 2022 | D20: 154/172 | E20: SWSH Alt Art | F20: 90 | G20: 300 | H20: 100 | I20: ❌ DON'T GRADE
A21: Venusaur ex SIR | B21: Scarlet & Violet 151 | C21: 2023 | D21: — | E21: Modern SIR | F21: 140 | G21: 580 | H21: 190 | I21: ⚠️ MARGINAL
A22: Blastoise ex SIR | B22: Scarlet & Violet 151 | C22: 2023 | D22: — | E22: Modern SIR | F22: 130 | G22: 550 | H22: 180 | I22: ⚠️ MARGINAL
A23: Pikachu with Paldean Starters Promo | B23: Pokemon Center Promo | C23: 2023 | D23: N/A | E23: Modern Promo | F23: 150 | G23: 1500 | H23: 400 | I23: ✅ STRONG GRADE
A24: Mew ex SIR #232 | B24: Paldean Fates | C24: 2024 | D24: 232/091 | E24: Modern SIR | F24: 90 | G24: 450 | H24: 155 | I24: ✅ GRADE IT
A25: Gengar ex SIR | B25: Paradox Rift | C25: 2023 | D25: — | E25: Modern SIR | F25: 100 | G25: 380 | H25: 130 | I25: ⚠️ MARGINAL
A26: Charizard ex SAR | B26: Scarlet & Violet 151 | C26: 2023 | D26: — | E26: Modern SAR | F26: 120 | G26: 420 | H26: 140 | I26: ⚠️ MARGINAL
A27: Mega Lucario ex SIR | B27: Ascended Heroes | C27: 2026 | D27: — | E27: Modern SIR | F27: 200 | G27: 1000 | H27: 350 | I27: ✅ GRADE IT
A28: ◆ 🔨 TIER C — Under $100 Raw (Budget Grind)
A29: Mew VMAX Alt Art | B29: Fusion Strike | C29: 2021 | D29: 269/264 | E29: SWSH Alt Art | F29: 60 | G29: 220 | H29: 80 | I29: ❌ DON'T GRADE
A30: Mew V Alt Art | B30: Fusion Strike | C30: 2021 | D30: 268/264 | E30: SWSH Alt Art | F30: 35 | G30: 150 | H30: 55 | I30: ❌ DON'T GRADE
A31: Gengar VMAX Alt Art | B31: Fusion Strike | C31: 2021 | D31: 271/264 | E31: SWSH Alt Art | F31: 80 | G31: 280 | H31: 95 | I31: ❌ DON'T GRADE
A32: Sylveon VMAX Alt Art | B32: Evolving Skies | C32: 2021 | D32: — | E32: SWSH Alt Art | F32: 70 | G32: 250 | H32: 90 | I32: ❌ DON'T GRADE
A33: Umbreon V Alt Art | B33: Evolving Skies | C33: 2021 | D33: — | E33: SWSH Alt Art | F33: 50 | G33: 180 | H33: 65 | I33: ❌ DON'T GRADE
A34: Pikachu 151 Illustration Rare | B34: Scarlet & Violet 151 | C34: 2023 | D34: 173/165 | E34: Modern IR | F34: 25 | G34: 180 | H34: 65 | I34: ⚠️ MARGINAL
A35: Charizard (Celebrations, Classic) | B35: Celebrations | C35: 2021 | D35: 4/25 | E35: Modern Promo | F35: 20 | G35: 80 | H35: 30 | I35: ❌ DON'T GRADE
